Workbook

Sheet Export Summary
B3: This document was exported from Numbers. Each table was converted to an Excel worksheet. All other objects on each Numbers sheet were placed on separate worksheets. Please be aware that formula calculations may differ in Excel.
B7: Numbers Sheet Name | C7: Numbers Table Name | D7: Excel Worksheet Name
B9: DASHBOARD
C10: Table 1 | D10: DASHBOARD
B11: QR Code
C12: Table 1 | D12: QR Code
B13: PLANO DE AÇÃO GERAL
C14: Table 1 | D14: PLANO DE AÇÃO GERAL
B15: BALANÇO
C16: Table 1 | D16: BALANÇO
B17: Endividamento
C18: Table 1 | D18: Endividamento
B19: Fluxo de Caixa
C20: Table 1 | D20: Fluxo de Caixa
B21: DRE
C22: Table 1 | D22: DRE
B23: Base DRE
C24: Table 1 | D24: Base DRE
B25: Base DRE Arquivo
C26: Table 1 | D26: Base DRE Arquivo
B27: Precificação
C28: Table 1 | D28: Precificação
B29: MARKUP
C30: Table 1 | D30: MARKUP
B31: INDUSTRIA
C32: Table 1 | D32: INDUSTRIA
B33: TABELA DE PREÇOS
C34: Table 1 | D34: TABELA DE PREÇOS
B35: SERVIÇO
C36: Table 1 | D36: SERVIÇO
B37: CUSTO FIXO
C38: Table 1 | D38: CUSTO FIXO
B39: CUSTO VARIAVEL
C40: Table 1 | D40: CUSTO VARIAVEL
B41: 1.Financeiro
C42: Table 1 | D42: 1.Financeiro
B43: 2.Comercial
C44: Table 1 | D44: 2.Comercial
B45: 3.Marketing
C46: Table 1 | D46: 3.Marketing
B47: 4.Operacional
C48: Table 1 | D48: 4.Operacional
B49: ANÁLISE HISTORICA
C50: Table 1 | D50: ANÁLISE HISTORICA
B51: 5.Recursos Humanos
C52: Table 1 | D52: 5.Recursos Humanos
B53: 6.Indicadores de Performance
C54: Table 1 | D54: 6.Indicadores de Performance
B55: Graficos Tasks
C56: Tabela dinâmica10 | D56: Graficos Tasks - Tabela dinâmic
C57: Tabela dinâmica6 | D57: Graficos Tasks - Tabela dinâmi1
C58: Tabela dinâmica3 | D58: Graficos Tasks - Tabela dinâmi2
C59: Tabela dinâmica4 | D59: Graficos Tasks - Tabela dinâmi3
C60: Tabela dinâmica2 | D60: Graficos Tasks - Tabela dinâmi4
C61: Tabela dinâmica7 | D61: Graficos Tasks - Tabela dinâmi5
C62: Tabela dinâmica9 | D62: Graficos Tasks - Tabela dinâmi6
C63: Tabela dinâmica8 | D63: Graficos Tasks - Tabela dinâmi7
C64: Tabela dinâmica5 | D64: Graficos Tasks - Tabela dinâmi8
C65: Tabela dinâmica1 | D65: Graficos Tasks - Tabela dinâmi9
C66: Table 1 | D66: Graficos Tasks - Table 1
C67: “All Drawings from the Sheet” | D67: Graficos Tasks - Drawings

Sheet DASHBOARD

Sheet QR Code

Sheet PLANO DE AÇÃO GERAL
A1: PLANO DE AÇÃO
A7: Item | B7: Ação | C7: Responsável | D7: PRAZO | E7: DATA EXEC | F7: Status | G7: Melhoria Esperada | H7: Observação
F8: {=IF(D8="","AGUARDANDO",IF(E8<>"","CONCLUIDO",IF(TODAY()<=D8,"EM ANDAMENTO",IF(TODAY()>D8,"ATRASADO","CONCLUIDO"))))} -> AGUARDANDO
F9: {=IF(D9="","AGUARDANDO",IF(TODAY()<=D9,"EM ANDAMENTO",IF(TODAY()>D9,"ATRASADO","CONCLUIDO")))} -> AGUARDANDO
F10: {=IF(D10="","AGUARDANDO",IF(TODAY()<=D10,"EM ANDAMENTO",IF(TODAY()>D10,"ATRASADO","CONCLUIDO")))} -> AGUARDANDO
F11: {=IF(D11="","AGUARDANDO",IF(TODAY()<=D11,"EM ANDAMENTO",IF(TODAY()>D11,"ATRASADO","CONCLUIDO")))} -> AGUARDANDO
F12: {=IF(D12="","AGUARDANDO",IF(TODAY()<=D12,"EM ANDAMENTO",IF(TODAY()>D12,"ATRASADO","CONCLUIDO")))} -> AGUARDANDO
F13: {=IF(D13="","AGUARDANDO",IF(TODAY()<=D13,"EM ANDAMENTO",IF(TODAY()>D13,"ATRASADO","CONCLUIDO")))} -> AGUARDANDO
F14: {=IF(D14="","AGUARDANDO",IF(TODAY()<=D14,"EM ANDAMENTO",IF(TODAY()>D14,"ATRASADO","CONCLUIDO")))} -> AGUARDANDO
F15: {=IF(D15="","AGUARDANDO",IF(TODAY()<=D15,"EM ANDAMENTO",IF(TODAY()>D15,"ATRASADO","CONCLUIDO")))} -> AGUARDANDO
F16: {=IF(D16="","AGUARDANDO",IF(TODAY()<=D16,"EM ANDAMENTO",IF(TODAY()>D16,"ATRASADO","CONCLUIDO")))} -> AGUARDANDO
F17: {=IF(D17="","AGUARDANDO",IF(TODAY()<=D17,"EM ANDAMENTO",IF(TODAY()>D17,"ATRASADO","CONCLUIDO")))} -> AGUARDANDO
F18: {=IF(D18="","AGUARDANDO",IF(TODAY()<=D18,"EM ANDAMENTO",IF(TODAY()>D18,"ATRASADO","CONCLUIDO")))} -> AGUARDANDO
F19: {=IF(D19="","AGUARDANDO",IF(TODAY()<=D19,"EM ANDAMENTO",IF(TODAY()>D19,"ATRASADO","CONCLUIDO")))} -> AGUARDANDO
F20: {=IF(D20="","AGUARDANDO",IF(TODAY()<=D20,"EM ANDAMENTO",IF(TODAY()>D20,"ATRASADO","CONCLUIDO")))} -> AGUARDANDO
... F28: {=IF(D28="","AGUARDANDO",IF(TODAY()<=D28,"EM ANDAMENTO",IF(TODAY()>D28,"ATRASADO","CONCLUIDO")))} -> AGUARDANDO

Sheet BALANÇO
C7: ATIVO | H7: PASSIVO
E8: Total do Ativo | F8: {=SUM(F9:F26)} -> 0 | I8: Total Passivo | J8: {=SUM(J9:J19)} -> 0
C9: Ativo | D9: Disponíveis | E9: Clientes a Receber ( - taxas) | H9: Passivo | I9: Fornecedores
E10: Conta Corrente | I10: Contas fixas a pagar
I11: Empréstimos
I17: Funcionários (última folha + 70%)
D20: Recursos Estocados | E20: Estoque
E21: Investimentos (aplicação) | H21: TOTAL DO ATIVO | J21: {=F8} -> 0
H23: TOTAL DO PASSIVO | J23: {=J8} -> 0
H25: PATRIMÔNIO LÍQUIDO | J25: {=J21-J23} -> 0

Sheet Endividamento
B8: SALDO DEVEDOR TOTAL | D8: {=E18} -> 0
B11: MODALIDADE | C11: Numero | D11: VALOR CONTRATADO | E11: SALDO DEVEDOR | F11: TX | G11: VENCIMENTO | H11: PARCELA | I11: PARCELAS PAGAS | J11: PROXIMAS PARCELAS | K11: ULTIMA PARCELA
B12: Banco 01 | C12: XXXXX
B13: Banco 02 | C13: XXXXX
B14: Banco 03 | C14: XXXXX
B15: Banco 04 | C15: XXXXX
B18: TOTAL | D18: {=SUM(D12:D17)} -> 0 | E18: {=SUM(E12:E17)} -> 0

Sheet Fluxo de Caixa
D8: SALDO INICIAL DO PLAN | F8: 0
C10: PLANEJADO | D10: RECEITAS | F10: 46023 | G10: 46054 | H10: 46082 | I10: 46113 | J10: 46143 | K10: 46174 | L10: 46204 | M10: 46235 | N10: 46266 | O10: 46296 | P10: 46327 | Q10: 46357
D11: RECEBIVEIS MENSAL | F11: {=SUM(F12:F21)} -> 0 | G11: {=SUM(G12:G21)} -> 0 | H11: {=SUM(H12:H21)} -> 0 | I11: {=SUM(I12:I21)} -> 0 | J11: {=SUM(J12:J21)} -> 5000 | K11: {=SUM(K12:K21)} -> 6000 | L11: {=SUM(L12:L21)} -> 4000 | M11: {=SUM(M12:M21)} -> 0 | ... Q11: {=SUM(Q12:Q21)} -> 0
D12: VENDAS A VISTA
D13: VENDAS EM 30 DIAS
D14: VENDAS EM 60 DIAS
D20: RESERVA DE EMERGÊNCIA | J20: 5000 | K20: 6000 | L20: 4000
D22: DESPESAS | F22: {=F10} -> 46023 | G22: {=G10} -> 46054 | H22: {=H10} -> 46082 | I22: {=I10} -> 46113 | J22: {=J10} -> 46143 | K22: {=K10} -> 46174 | L22: {=L10} -> 46204 | M22: {=M10} -> 46235 | ... Q22: {=Q10} -> 46357
D23: COMPROMISSO MENSAL | E23: % | F23: {=SUM(F24:F39)} -> 0 | G23: {=SUM(G24:G39)} -> 0 | H23: {=SUM(H24:H39)} -> 0 | I23: {=SUM(I24:I39)} -> 0 | J23: {=SUM(J24:J39)} -> 0 | K23: {=SUM(K24:K39)} -> 0 | L23: {=SUM(L24:L39)} -> 0 | M23: {=SUM(M24:M39)} -> 0 | ... Q23: {=SUM(Q24:Q39)} -> 0
D24: DESPESAS FIXAS
D25: DESPESAS VARIÁVEIS | E25: 0.2
D26: CUSTOS VARIÁVEIS | E26: 0.4
D27: DESPESAS FINANCEIRAS E OUTROS
D28: DISTRIBUIÇÃO DE LUCRO E PROLABORE
D38: RETIRADA PARA RESERVA DE EMERGÊNCIA
D41: RESULTADO RECEITAS - DESPESAS | F41: {=F11-F23} -> 0 | G41: {=G11-G23} -> 0 | H41: {=H11-H23} -> 0 | I41: {=I11-I23} -> 0 | J41: {=J11-J23} -> 5000 | K41: {=K11-K23} -> 6000 | L41: {=L11-L23} -> 4000 | M41: {=M11-M23} -> 0 | ... Q41: {=Q11-Q23} -> 0
D43: RESERVA DE EMERGENCIA (3 MESES DO CF) | F43: {=15000+F38-F20} -> 15000 | G43: {=F43+G38-G20} -> 15000 | H43: {=G43+H38-H20} -> 15000 | I43: {=H43+I38-I20} -> 15000 | J43: {=I43+J38-J20} -> 10000 | K43: {=J43+K38-K20} -> 4000 | L43: {=K43+L38-L20} -> 0 | M43: {=L43+M38-M20} -> 0 | N43: {=M43+N38-N20} -> 0 | ... Q43: {=P43+Q38-Q20} -> 0
D45: SALDO ACUMULADO | F45: {=F41+F8} -> 0 | G45: {=G41+F45} -> 0 | H45: {=H41+G45} -> 0 | I45: {=I41+H45} -> 0 | J45: {=J41+I45} -> 5000 | K45: {=K41+J45} -> 11000 | L45: {=L41+K45} -> 15000 | M45: {=M41+L45} -> 15000 | N45: {=N41+M45} -> 15000 | ... Q45: {=Q41+P45} -> 15000
C50: PREVISÃO DE RECEBÍVEIS A PRAZO | F50: Á Vista | G50: 30 Dias | H50: 60 Dias
C52: % | D52: FATURAMENTO TOTAL
C53: 0.4 | D53: VENDAS A VISTA | F53: {=F$52*$C53} -> 0 | G53: {=G$52*$C53} -> 0 | H53: {=H$52*$C53} -> 0
C54: 0.3 | D54: VENDAS EM 30 DIAS | F54: {=F$52*$C54} -> 0 | G54: {=G$52*$C54} -> 0 | H54: {=H$52*$C54} -> 0
C55: 0.3 | D55: VENDAS EM 60 DIAS | F55: {=F$52*$C55} -> 0 | G55: {=G$52*$C55} -> 0 | H55: {=H$52*$C55} -> 0

Sheet DRE
D2: SELECIONE O CENTRO DE CUSTO | H2: *
H4: {=H2} -> *
C6: DEMONSTRATIVO DE RESULTADO | D6: 2026 | F6: 2026 | H6: 2026 | J6: 2026 | L6: 2026 | N6: 2026 | P6: 2026 | R6: 2026 | T6: 2026 | V6: 2026 | X6: 2026 | Z6: 2026
C7: CONSOLIDADO | D7: 46054 | E7: % | F7: 46082 | G7: % | H7: 46113 | I7: % | J7: 46143 | K7: % | L7: 46173 | M7: % | N7: 46203 | O7: % | P7: 46233 | Q7: % | R7: 46263 | S7: % | T7: 46293 | U7: % | V7: 46323 | W7: % | X7: 46353 | Y7: % | Z7: 46383 | AA7: %
C8: ( = ) Receitas Operacionais | D8: {=D9} -> 0 | E8: {=_xlfn.IFERROR(D8/D$8,"")} | F8: {=F9} -> 0 | G8: {=_xlfn.IFERROR(F8/F$8,"")} | H8: {=H9} -> 0 | I8: {=_xlfn.IFERROR(H8/H$8,"")} | J8: {=J9} -> 0 | K8: {=_xlfn.IFERROR(J8/J$8,"")} | L8: {=L9} -> 0 | M8: {=_xlfn.IFERROR(L8/L$8,"")} | N8: {=N9} -> 0 | O8: {=_xlfn.IFERROR(N8/N$8,"")} | P8: {=P9} -> 0 | Q8: {=_xlfn.IFERROR(P8/P$8,"")} | R8: {=R9} -> 0 | S8: {=_xlfn.IFERROR(R8/R$8,"")} | T8: {=T9} -> 0 | U8: {=_xlfn.IFERROR(T8/T$8,"")} | V8: {=V9} -> 0 | W8: {=_xlfn.IFERROR(V8/V$8,"")} | X8: {=X9} -> 0 | Y8: {=_xlfn.IFERROR(X8/X$8,"")} | Z8: {=Z9} -> 0 | AA8: {=_xlfn.IFERROR(Z8/Z$8,"")}
B9: 1. | C9: ( + ) Receita de Vendas de Produtos e Serviços | D9: {=SUM(D10:D12)} -> 0 | E9: {=_xlfn.IFERROR(D9/D$8,"")} | F9: {=SUM(F10:F12)} -> 0 | G9: {=_xlfn.IFERROR(F9/F$8,"")} | H9: {=SUM(H10:H12)} -> 0 | I9: {=_xlfn.IFERROR(H9/H$8,"")} | J9: {=SUM(J10:J12)} -> 0 | K9: {=_xlfn.IFERROR(J9/J$8,"")} | L9: {=SUM(L10:L12)} -> 0 | M9: {=_xlfn.IFERROR(L9/L$8,"")} | N9: {=SUM(N10:N12)} -> 0 | O9: {=_xlfn.IFERROR(N9/N$8,"")} | P9: {=SUM(P10:P12)} -> 0 | Q9: {=_xlfn.IFERROR(P9/P$8,"")} | R9: {=SUM(R10:R12)} -> 0 | S9: {=_xlfn.IFERROR(R9/R$8,"")} | T9: {=SUM(T10:T12)} -> 0 | U9: {=_xlfn.IFERROR(T9/T$8,"")} | V9: {=SUM(V10:V12)} -> 0 | W9: {=_xlfn.IFERROR(V9/V$8,"")} | X9: {=SUM(X10:X12)} -> 0 | Y9: {=_xlfn.IFERROR(X9/X$8,"")} | Z9: {=SUM(Z10:Z12)} -> 0 | AA9: {=_xlfn.IFERROR(Z9/Z$8,"")}
B10: RECEITA | C10: Receita de Vendas - Produtos | D10: {=_xlfn.SUMIFS('Base DRE'!$E1:$E625,'Base DRE'!$I1:$I625,D$7,'Base DRE'!$L1:$L625,$C10,'Base DRE'!$K1:$K625,$H$2)} -> 0 | F10: {=_xlfn.SUMIFS('Base DRE'!$E1:$E625,'Base DRE'!$I1:$I625,F$7,'Base DRE'!$L1:$L625,$C10,'Base DRE'!$K1:$K625,$H$2)} -> 0 | H10: {=_xlfn.SUMIFS('Base DRE'!$E1:$E625,'Base DRE'!$I1:$I625,H$7,'Base DRE'!$L1:$L625,$C10,'Base DRE'!$K1:$K625,$H$2)} -> 0 | J10: {=_xlfn.SUMIFS('Base DRE'!$E1:$E625,'Base DRE'!$I1:$I625,J$7,'Base DRE'!$L1:$L625,$C10,'Base DRE'!$K1:$K625,$H$2)} -> 0 | L10: {=_xlfn.SUMIFS('Base DRE'!$E1:$E625,'Base DRE'!$I1:$I625,L$7,'Base DRE'!$L1:$L625,$C10,'Base DRE'!$K1:$K625,$H$2)} -> 0 | N10: {=_xlfn.SUMIFS('Base DRE'!$E1:$E625,'Base DRE'!$I1:$I625,N$7,'Base DRE'!$L1:$L625,$C10,'Base DRE'!$K1:$K625,$H$2)} -> 0 | P10: {=_xlfn.SUMIFS('Base DRE'!$E1:$E625,'Base DRE'!$I1:$I625,P$7,'Base DRE'!$L1:$L625,$C10,'Base DRE'!$K1:$K625,$H$2)} -> 0 | R10: {=_xlfn.SUMIFS('Base DRE'!$E1:$E625,'Base DRE'!$I1:$I625,R$7,'Base DRE'!$L1:$L625,$C10,'Base DRE'!$K1:$K625,$H$2)} -> 0 | T10: {=_xlfn.SUMIFS('Base DRE'!$E1:$E625,'Base DRE'!$I1:$I625,T$7,'Base DRE'!$L1:$L625,$C10,'Base DRE'!$K1:$K625,$H$2)} -> 0 | V10: {=_xlfn.SUMIFS('Base DRE'!$E1:$E625,'Base DRE'!$I1:$I625,V$7,'Base DRE'!$L1:$L625,$C10,'Base DRE'!$K1:$K625,$H$2)} -> 0 | X10: {=_xlfn.SUMIFS('Base DRE'!$E1:$E625,'Base DRE'!$I1:$I625,X$7,'Base DRE'!$L1:$L625,$C10,'Base DRE'!$K1:$K625,$H$2)} -> 0 | Z10: {=_xlfn.SUMIFS('Base DRE'!$E1:$E625,'Base DRE'!$I1:$I625,Z$7,'Base DRE'!$L1:$L625,$C10,'Base DRE'!$K1:$K625,$H$2)} -> 0
B11: RECEITA | C11: Receita de Vendas - Serviços | D11: {=_xlfn.SUMIFS('Base DRE'!$E1:$E625,'Base DRE'!$I1:$I625,D$7,'Base DRE'!$L1:$L625,$C11,'Base DRE'!$K1:$K625,$H$2)} -> 0 | F11: {=_xlfn.SUMIFS('Base DRE'!$E1:$E625,'Base DRE'!$I1:$I625,F$7,'Base DRE'!$L1:$L625,$C11,'Base DRE'!$K1:$K625,$H$2)} -> 0 | H11: {=_xlfn.SUMIFS('Base DRE'!$E1:$E625,'Base DRE'!$I1:$I625,H$7,'Base DRE'!$L1:$L625,$C11,'Base DRE'!$K1:$K625,$H$2)} -> 0 | J11: {=_xlfn.SUMIFS('Base DRE'!$E1:$E625,'Base DRE'!$I1:$I625,J$7,'Base DRE'!$L1:$L625,$C11,'Base DRE'!$K1:$K625,$H$2)} -> 0 | L11: {=_xlfn.SUMIFS('Base DRE'!$E1:$E625,'Base DRE'!$I1:$I625,L$7,'Base DRE'!$L1:$L625,$C11,'Base DRE'!$K1:$K625,$H$2)} -> 0 | N11: {=_xlfn.SUMIFS('Base DRE'!$E1:$E625,'Base DRE'!$I1:$I625,N$7,'Base DRE'!$L1:$L625,$C11,'Base DRE'!$K1:$K625,$H$2)} -> 0 | P11: {=_xlfn.SUMIFS('Base DRE'!$E1:$E625,'Base DRE'!$I1:$I625,P$7,'Base DRE'!$L1:$L625,$C11,'Base DRE'!$K1:$K625,$H$2)} -> 0 | R11: {=_xlfn.SUMIFS('Base DRE'!$E1:$E625,'Base DRE'!$I1:$I625,R$7,'Base DRE'!$L1:$L625,$C11,'Base DRE'!$K1:$K625,$H$2)} -> 0 | T11: {=_xlfn.SUMIFS('Base DRE'!$E1:$E625,'Base DRE'!$I1:$I625,T$7,'Base DRE'!$L1:$L625,$C11,'Base DRE'!$K1:$K625,$H$2)} -> 0 | V11: {=_xlfn.SUMIFS('Base DRE'!$E1:$E625,'Base DRE'!$I1:$I625,V$7,'Base DRE'!$L1:$L625,$C11,'Base DRE'!$K1:$K625,$H$2)} -> 0 | X11: {=_xlfn.SUMIFS('Base DRE'!$E1:$E625,'Base DRE'!$I1:$I625,X$7,'Base DRE'!$L1:$L625,$C11,'Base DRE'!$K1:$K625,$H$2)} -> 0 | Z11: {=_xlfn.SUMIFS('Base DRE'!$E1:$E625,'Base DRE'!$I1:$I625,Z$7,'Base DRE'!$L1:$L625,$C11,'Base DRE'!$K1:$K625,$H$2)} -> 0
C12: Receita de Aluguéis Recebidos | D12: {=_xlfn.SUMIFS('Base DRE'!$E1:$E625,'Base DRE'!$I1:$I625,D$7,'Base DRE'!$L1:$L625,$C12,'Base DRE'!$K1:$K625,$H$2)} -> 0 | F12: {=_xlfn.SUMIFS('Base DRE'!$E1:$E625,'Base DRE'!$I1:$I625,F$7,'Base DRE'!$L1:$L625,$C12,'Base DRE'!$K1:$K625,$H$2)} -> 0 | H12: {=_xlfn.SUMIFS('Base DRE'!$E1:$E625,'Base DRE'!$I1:$I625,H$7,'Base DRE'!$L1:$L625,$C12,'Base DRE'!$K1:$K625,$H$2)} -> 0 | J12: {=_xlfn.SUMIFS('Base DRE'!$E1:$E625,'Base DRE'!$I1:$I625,J$7,'Base DRE'!$L1:$L625,$C12,'Base DRE'!$K1:$K625,$H$2)} -> 0 | L12: {=_xlfn.SUMIFS('Base DRE'!$E1:$E625,'Base DRE'!$I1:$I625,L$7,'Base DRE'!$L1:$L625,$C12,'Base DRE'!$K1:$K625,$H$2)} -> 0 | N12: {=_xlfn.SUMIFS('Base DRE'!$E1:$E625,'Base DRE'!$I1:$I625,N$7,'Base DRE'!$L1:$L625,$C12,'Base DRE'!$K1:$K625,$H$2)} -> 0 | P12: {=_xlfn.SUMIFS('Base DRE'!$E1:$E625,'Base DRE'!$I1:$I625,P$7,'Base DRE'!$L1:$L625,$C12,'Base DRE'!$K1:$K625,$H$2)} -> 0 | R12: {=_xlfn.SUMIFS('Base DRE'!$E1:$E625,'Base DRE'!$I1:$I625,R$7,'Base DRE'!$L1:$L625,$C12,'Base DRE'!$K1:$K625,$H$2)} -> 0 | T12: {=_xlfn.SUMIFS('Base DRE'!$E1:$E625,'Base DRE'!$I1:$I625,T$7,'Base DRE'!$L1:$L625,$C12,'Base DRE'!$K1:$K625,$H$2)} -> 0 | V12: {=_xlfn.SUMIFS('Base DRE'!$E1:$E625,'Base DRE'!$I1:$I625,V$7,'Base DRE'!$L1:$L625,$C12,'Base DRE'!$K1:$K625,$H$2)} -> 0 | X12: {=_xlfn.SUMIFS('Base DRE'!$E1:$E625,'Base DRE'!$I1:$I625,X$7,'Base DRE'!$L1:$L625,$C12,'Base DRE'!$K1:$K625,$H$2)} -> 0 | Z12: {=_xlfn.SUMIFS('Base DRE'!$E1:$E625,'Base DRE'!$I1:$I625,Z$7,'Base DRE'!$L1:$L625,$C12,'Base DRE'!$K1:$K625,$H$2)} -> 0
C14: ( = ) Receita Bruta de Vendas | D14: {=D8} -> 0 | E14: {=_xlfn.IFERROR(D14/D$8,"")} | F14: {=F8} -> 0 | G14: {=_xlfn.IFERROR(F14/F$8,"")} | H14: {=H8} -> 0 | I14: {=_xlfn.IFERROR(H14/H$8,"")} | J14: {=J8} -> 0 | K14: {=_xlfn.IFERROR(J14/J$8,"")} | L14: {=L8} -> 0 | M14: {=_xlfn.IFERROR(L14/L$8,"")} | N14: {=N8} -> 0 | O14: {=_xlfn.IFERROR(N14/N$8,"")} | P14: {=P8} -> 0 | Q14: {=_xlfn.IFERROR(P14/P$8,"")} | R14: {=R8} -> 0 | S14: {=_xlfn.IFERROR(R14/R$8,"")} | T14: {=T8} -> 0 | U14: {=_xlfn.IFERROR(T14/T$8,"")} | V14: {=V8} -> 0 | W14: {=_xlfn.IFERROR(V14/V$8,"")} | X14: {=X8} -> 0 | Y14: {=_xlfn.IFERROR(X14/X$8,"")} | Z14: {=Z8} -> 0 | AA14: {=_xlfn.IFERROR(Z14/Z$8,"")}
B16: 2. | C16: ( - ) Deduções da Receita Bruta (Despesa Variável) | D16: {=D17} -> 0 | E16: {=_xlfn.IFERROR(D16/D$8,"")} | F16: {=F17} -> 0 | G16: {=_xlfn.IFERROR(F16/F$8,"")} | H16: {=H17} -> 0 | I16: {=_xlfn.IFERROR(H16/H$8,"")} | J16: {=J17} -> 0 | K16: {=_xlfn.IFERROR(J16/J$8,"")} | L16: {=L17} -> 0 | M16: {=_xlfn.IFERROR(L16/L$8,"")} | N16: {=N17} -> 0 | O16: {=_xlfn.IFERROR(N16/N$8,"")} | P16: {=P17} -> 0 | Q16: {=_xlfn.IFERROR(P16/P$8,"")} | R16: {=R17} -> 0 | S16: {=_xlfn.IFERROR(R16/R$8,"")} | T16: {=T17} -> 0 | U16: {=_xlfn.IFERROR(T16/T$8,"")} | V16: {=V17} -> 0 | W16: {=_xlfn.IFERROR(V16/V$8,"")} | X16: {=X17} -> 0 | Y16: {=_xlfn.IFERROR(X16/X$8,"")} | Z16: {=Z17} -> 0 | AA16: {=_xlfn.IFERROR(Z16/Z$8,"")}
C17: Dedições e impostos | D17: {=SUM(D18:D20)} -> 0 | E17: {=_xlfn.IFERROR(D17/D$8,"")} | F17: {=SUM(F18:F20)} -> 0 | G17: {=_xlfn.IFERROR(F17/F$8,"")} | H17: {=SUM(H18:H20)} -> 0 | I17: {=_xlfn.IFERROR(H17/H$8,"")} | J17: {=SUM(J18:J20)} -> 0 | K17: {=_xlfn.IFERROR(J17/J$8,"")} | L17: {=SUM(L18:L20)} -> 0 | M17: {=_xlfn.IFERROR(L17/L$8,"")} | N17: {=SUM(N18:N20)} -> 0 | O17: {=_xlfn.IFERROR(N17/N$8,"")} | P17: {=SUM(P18:P20)} -> 0 | Q17: {=_xlfn.IFERROR(P17/P$8,"")} | R17: {=SUM(R18:R20)} -> 0 | S17: {=_xlfn.IFERROR(R17/R$8,"")} | T17: {=SUM(T18:T20)} -> 0 | U17: {=_xlfn.IFERROR(T17/T$8,"")} | V17: {=SUM(V18:V20)} -> 0 | W17: {=_xlfn.IFERROR(V17/V$8,"")} | X17: {=SUM(X18:X20)} -> 0 | Y17: {=_xlfn.IFERROR(X17/X$8,"")} | Z17: {=SUM(Z18:Z20)} -> 0 | AA17: {=_xlfn.IFERROR(Z17/Z$8,"")}
B18: DESPESA | C18: Comissão de Vendas | D18: {=_xlfn.SUMIFS('Base DRE'!$E1:$E625,'Base DRE'!$I1:$I625,D$7,'Base DRE'!$L1:$L625,$C18,'Base DRE'!$K1:$K625,$H$2)} -> 0 | F18: {=_xlfn.SUMIFS('Base DRE'!$E1:$E625,'Base DRE'!$I1:$I625,F$7,'Base DRE'!$L1:$L625,$C18,'Base DRE'!$K1:$K625,$H$2)} -> 0 | H18: {=_xlfn.SUMIFS('Base DRE'!$E1:$E625,'Base DRE'!$I1:$I625,H$7,'Base DRE'!$L1:$L625,$C18,'Base DRE'!$K1:$K625,$H$2)} -> 0 | J18: {=_xlfn.SUMIFS('Base DRE'!$E1:$E625,'Base DRE'!$I1:$I625,J$7,'Base DRE'!$L1:$L625,$C18,'Base DRE'!$K1:$K625,$H$2)} -> 0 | L18: {=_xlfn.SUMIFS('Base DRE'!$E1:$E625,'Base DRE'!$I1:$I625,L$7,'Base DRE'!$L1:$L625,$C18,'Base DRE'!$K1:$K625,$H$2)} -> 0 | N18: {=_xlfn.SUMIFS('Base DRE'!$E1:$E625,'Base DRE'!$I1:$I625,N$7,'Base DRE'!$L1:$L625,$C18,'Base DRE'!$K1:$K625,$H$2)} -> 0 | P18: {=_xlfn.SUMIFS('Base DRE'!$E1:$E625,'Base DRE'!$I1:$I625,P$7,'Base DRE'!$L1:$L625,$C18,'Base DRE'!$K1:$K625,$H$2)} -> 0 | R18: {=_xlfn.SUMIFS('Base DRE'!$E1:$E625,'Base DRE'!$I1:$I625,R$7,'Base DRE'!$L1:$L625,$C18,'Base DRE'!$K1:$K625,$H$2)} -> 0 | T18: {=_xlfn.SUMIFS('Base DRE'!$E1:$E625,'Base DRE'!$I1:$I625,T$7,'Base DRE'!$L1:$L625,$C18,'Base DRE'!$K1:$K625,$H$2)} -> 0 | V18: {=_xlfn.SUMIFS('Base DRE'!$E1:$E625,'Base DRE'!$I1:$I625,V$7,'Base DRE'!$L1:$L625,$C18,'Base DRE'!$K1:$K625,$H$2)} -> 0 | X18: {=_xlfn.SUMIFS('Base DRE'!$E1:$E625,'Base DRE'!$I1:$I625,X$7,'Base DRE'!$L1:$L625,$C18,'Base DRE'!$K1:$K625,$H$2)} -> 0 | Z18: {=_xlfn.SUMIFS('Base DRE'!$E1:$E625,'Base DRE'!$I1:$I625,Z$7,'Base DRE'!$L1:$L625,$C18,'Base DRE'!$K1:$K625,$H$2)} -> 0
B19: DESPESA | C19: Impostos sobre vendas (ISS, ICMS, etc.) | D19: {=_xlfn.SUMIFS('Base DRE'!$E1:$E625,'Base DRE'!$I1:$I625,D$7,'Base DRE'!$L1:$L625,$C19,'Base DRE'!$K1:$K625,$H$2)} -> 0 | F19: {=_xlfn.SUMIFS('Base DRE'!$E1:$E625,'Base DRE'!$I1:$I625,F$7,'Base DRE'!$L1:$L625,$C19,'Base DRE'!$K1:$K625,$H$2)} -> 0 | H19: {=_xlfn.SUMIFS('Base DRE'!$E1:$E625,'Base DRE'!$I1:$I625,H$7,'Base DRE'!$L1:$L625,$C19,'Base DRE'!$K1:$K625,$H$2)} -> 0 | J19: {=_xlfn.SUMIFS('Base DRE'!$E1:$E625,'Base DRE'!$I1:$I625,J$7,'Base DRE'!$L1:$L625,$C19,'Base DRE'!$K1:$K625,$H$2)} -> 0 | L19: {=_xlfn.SUMIFS('Base DRE'!$E1:$E625,'Base DRE'!$I1:$I625,L$7,'Base DRE'!$L1:$L625,$C19,'Base DRE'!$K1:$K625,$H$2)} -> 0 | N19: {=_xlfn.SUMIFS('Base DRE'!$E1:$E625,'Base DRE'!$I1:$I625,N$7,'Base DRE'!$L1:$L625,$C19,'Base DRE'!$K1:$K625,$H$2)} -> 0 | P19: {=_xlfn.SUMIFS('Base DRE'!$E1:$E625,'Base DRE'!$I1:$I625,P$7,'Base DRE'!$L1:$L625,$C19,'Base DRE'!$K1:$K625,$H$2)} -> 0 | R19: {=_xlfn.SUMIFS('Base DRE'!$E1:$E625,'Base DRE'!$I1:$I625,R$7,'Base DRE'!$L1:$L625,$C19,'Base DRE'!$K1:$K625,$H$2)} -> 0 | T19: {=_xlfn.SUMIFS('Base DRE'!$E1:$E625,'Base DRE'!$I1:$I625,T$7,'Base DRE'!$L1:$L625,$C19,'Base DRE'!$K1:$K625,$H$2)} -> 0 | V19: {=_xlfn.SUMIFS('Base DRE'!$E1:$E625,'Base DRE'!$I1:$I625,V$7,'Base DRE'!$L1:$L625,$C19,'Base DRE'!$K1:$K625,$H$2)} -> 0 | X19: {=_xlfn.SUMIFS('Base DRE'!$E1:$E625,'Base DRE'!$I1:$I625,X$7,'Base DRE'!$L1:$L625,$C19,'Base DRE'!$K1:$K625,$H$2)} -> 0 | Z19: {=_xlfn.SUMIFS('Base DRE'!$E1:$E625,'Base DRE'!$I1:$I625,Z$7,'Base DRE'!$L1:$L625,$C19,'Base DRE'!$K1:$K625,$H$2)} -> 0
D20: {=_xlfn.SUMIFS('Base DRE'!$E1:$E625,'Base DRE'!$I1:$I625,D$7,'Base DRE'!$L1:$L625,$C20,'Base DRE'!$K1:$K625,$H$2)} -> 0 | F20: {=_xlfn.SUMIFS('Base DRE'!$E1:$E625,'Base DRE'!$I1:$I625,F$7,'Base DRE'!$L1:$L625,$C20,'Base DRE'!$K1:$K625,$H$2)} -> 0 | H20: {=_xlfn.SUMIFS('Base DRE'!$E1:$E625,'Base DRE'!$I1:$I625,H$7,'Base DRE'!$L1:$L625,$C20,'Base DRE'!$K1:$K625,$H$2)} -> 0 | J20: {=_xlfn.SUMIFS('Base DRE'!$E1:$E625,'Base DRE'!$I1:$I625,J$7,'Base DRE'!$L1:$L625,$C20,'Base DRE'!$K1:$K625,$H$2)} -> 0 | L20: {=_xlfn.SUMIFS('Base DRE'!$E1:$E625,'Base DRE'!$I1:$I625,L$7,'Base DRE'!$L1:$L625,$C20,'Base DRE'!$K1:$K625,$H$2)} -> 0 | N20: {=_xlfn.SUMIFS('Base DRE'!$E1:$E625,'Base DRE'!$I1:$I625,N$7,'Base DRE'!$L1:$L625,$C20,'Base DRE'!$K1:$K625,$H$2)} -> 0 | P20: {=_xlfn.SUMIFS('Base DRE'!$E1:$E625,'Base DRE'!$I1:$I625,P$7,'Base DRE'!$L1:$L625,$C20,'Base DRE'!$K1:$K625,$H$2)} -> 0 | R20: {=_xlfn.SUMIFS('Base DRE'!$E1:$E625,'Base DRE'!$I1:$I625,R$7,'Base DRE'!$L1:$L625,$C20,'Base DRE'!$K1:$K625,$H$2)} -> 0 | T20: {=_xlfn.SUMIFS('Base DRE'!$E1:$E625,'Base DRE'!$I1:$I625,T$7,'Base DRE'!$L1:$L625,$C20,'Base DRE'!$K1:$K625,$H$2)} -> 0 | V20: {=_xlfn.SUMIFS('Base DRE'!$E1:$E625,'Base DRE'!$I1:$I625,V$7,'Base DRE'!$L1:$L625,$C20,'Base DRE'!$K1:$K625,$H$2)} -> 0 | X20: {=_xlfn.SUMIFS('Base DRE'!$E1:$E625,'Base DRE'!$I1:$I625,X$7,'Base DRE'!$L1:$L625,$C20,'Base DRE'!$K1:$K625,$H$2)} -> 0 | Z20: {=_xlfn.SUMIFS('Base DRE'!$E1:$E625,'Base DRE'!$I1:$I625,Z$7,'Base DRE'!$L1:$L625,$C20,'Base DRE'!$K1:$K625,$H$2)} -> 0
C22: ( = ) Receita Líquida de Vendas | D22: {=D14+D16} -> 0 | E22: {=_xlfn.IFERROR(D22/D$8,"")} | F22: {=F14+F16} -> 0 | G22: {=_xlfn.IFERROR(F22/F$8,"")} | H22: {=H14+H16} -> 0 | I22: {=_xlfn.IFERROR(H22/H$8,"")} | J22: {=J14+J16} -> 0 | K22: {=_xlfn.IFERROR(J22/J$8,"")} | L22: {=L14+L16} -> 0 | M22: {=_xlfn.IFERROR(L22/L$8,"")} | N22: {=N14+N16} -> 0 | O22: {=_xlfn.IFERROR(N22/N$8,"")} | P22: {=P14+P16} -> 0 | Q22: {=_xlfn.IFERROR(P22/P$8,"")} | R22: {=R14+R16} -> 0 | S22: {=_xlfn.IFERROR(R22/R$8,"")} | T22: {=T14+T16} -> 0 | U22: {=_xlfn.IFERROR(T22/T$8,"")} | V22: {=V14+V16} -> 0 | W22: {=_xlfn.IFERROR(V22/V$8,"")} | X22: {=X14+X16} -> 0 | Y22: {=_xlfn.IFERROR(X22/X$8,"")} | Z22: {=Z14+Z16} -> 0 | AA22: {=_xlfn.IFERROR(Z22/Z$8,"")}
B24: 3. | C24: ( - ) Custos Operacionais (Custos Variáveis) | D24: {=D25} -> 0 | E24: {=_xlfn.IFERROR(D24/D$8,"")} | F24: {=F25} -> 0 | G24: {=_xlfn.IFERROR(F24/F$8,"")} | H24: {=H25} -> 0 | I24: {=_xlfn.IFERROR(H24/H$8,"")} | J24: {=J25} -> 0 | K24: {=_xlfn.IFERROR(J24/J$8,"")} | L24: {=L25} -> 0 | M24: {=_xlfn.IFERROR(L24/L$8,"")} | N24: {=N25} -> 0 | O24: {=_xlfn.IFERROR(N24/N$8,"")} | P24: {=P25} -> 0 | Q24: {=_xlfn.IFERROR(P24/P$8,"")} | R24: {=R25} -> 0 | S24: {=_xlfn.IFERROR(R24/R$8,"")} | T24: {=T25} -> 0 | U24: {=_xlfn.IFERROR(T24/T$8,"")} | V24: {=V25} -> 0 | W24: {=_xlfn.IFERROR(V24/V$8,"")} | X24: {=X25} -> 0 | Y24: {=_xlfn.IFERROR(X24/X$8,"")} | Z24: {=Z25} -> 0 | AA24: {=_xlfn.IFERROR(Z24/Z$8,"")}
C25: Custos Variáveis | D25: {=SUM(D26:D29)} -> 0 | E25: {=_xlfn.IFERROR(D25/D$8,"")} | F25: {=SUM(F26:F29)} -> 0 | G25: {=_xlfn.IFERROR(F25/F$8,"")} | H25: {=SUM(H26:H29)} -> 0 | I25: {=_xlfn.IFERROR(H25/H$8,"")} | J25: {=SUM(J26:J29)} -> 0 | K25: {=_xlfn.IFERROR(J25/J$8,"")} | L25: {=SUM(L26:L29)} -> 0 | M25: {=_xlfn.IFERROR(L25/L$8,"")} | N25: {=SUM(N26:N29)} -> 0 | O25: {=_xlfn.IFERROR(N25/N$8,"")} | P25: {=SUM(P26:P29)} -> 0 | Q25: {=_xlfn.IFERROR(P25/P$8,"")} | R25: {=SUM(R26:R29)} -> 0 | S25: {=_xlfn.IFERROR(R25/R$8,"")} | T25: {=SUM(T26:T29)} -> 0 | U25: {=_xlfn.IFERROR(T25/T$8,"")} | V25: {=SUM(V26:V29)} -> 0 | W25: {=_xlfn.IFERROR(V25/V$8,"")} | X25: {=SUM(X26:X29)} -> 0 | Y25: {=_xlfn.IFERROR(X25/X$8,"")} | Z25: {=SUM(Z26:Z29)} -> 0 | AA25: {=_xlfn.IFERROR(Z25/Z$8,"")}
B26: DESPESA | C26: Custo de Mercadoria Vendida (CMV) | D26: {=_xlfn.SUMIFS('Base DRE'!$E1:$E625,'Base DRE'!$I1:$I625,D$7,'Base DRE'!$L1:$L625,$C26,'Base DRE'!$K1:$K625,$H$2)} -> 0 | F26: {=_xlfn.SUMIFS('Base DRE'!$E1:$E625,'Base DRE'!$I1:$I625,F$7,'Base DRE'!$L1:$L625,$C26,'Base DRE'!$K1:$K625,$H$2)} -> 0 | H26: {=_xlfn.SUMIFS('Base DRE'!$E1:$E625,'Base DRE'!$I1:$I625,H$7,'Base DRE'!$L1:$L625,$C26,'Base DRE'!$K1:$K625,$H$2)} -> 0 | J26: {=_xlfn.SUMIFS('Base DRE'!$E1:$E625,'Base DRE'!$I1:$I625,J$7,'Base DRE'!$L1:$L625,$C26,'Base DRE'!$K1:$K625,$H$2)} -> 0 | L26: {=_xlfn.SUMIFS('Base DRE'!$E1:$E625,'Base DRE'!$I1:$I625,L$7,'Base DRE'!$L1:$L625,$C26,'Base DRE'!$K1:$K625,$H$2)} -> 0 | N26: {=_xlfn.SUMIFS('Base DRE'!$E1:$E625,'Base DRE'!$I1:$I625,N$7,'Base DRE'!$L1:$L625,$C26,'Base DRE'!$K1:$K625,$H$2)} -> 0 | P26: {=_xlfn.SUMIFS('Base DRE'!$E1:$E625,'Base DRE'!$I1:$I625,P$7,'Base DRE'!$L1:$L625,$C26,'Base DRE'!$K1:$K625,$H$2)} -> 0 | R26: {=_xlfn.SUMIFS('Base DRE'!$E1:$E625,'Base DRE'!$I1:$I625,R$7,'Base DRE'!$L1:$L625,$C26,'Base DRE'!$K1:$K625,$H$2)} -> 0 | T26: {=_xlfn.SUMIFS('Base DRE'!$E1:$E625,'Base DRE'!$I1:$I625,T$7,'Base DRE'!$L1:$L625,$C26,'Base DRE'!$K1:$K625,$H$2)} -> 0 | V26: {=_xlfn.SUMIFS('Base DRE'!$E1:$E625,'Base DRE'!$I1:$I625,V$7,'Base DRE'!$L1:$L625,$C26,'Base DRE'!$K1:$K625,$H$2)} -> 0 | X26: {=_xlfn.SUMIFS('Base DRE'!$E1:$E625,'Base DRE'!$I1:$I625,X$7,'Base DRE'!$L1:$L625,$C26,'Base DRE'!$K1:$K625,$H$2)} -> 0 | Z26: {=_xlfn.SUMIFS('Base DRE'!$E1:$E625,'Base DRE'!$I1:$I625,Z$7,'Base DRE'!$L1:$L625,$C26,'Base DRE'!$K1:$K625,$H$2)} -> 0
B27: DESPESA | C27: Matéria-prima Consumida | D27: {=_xlfn.SUMIFS('Base DRE'!$E1:$E625,'Base DRE'!$I1:$I625,D$7,'Base DRE'!$L1:$L625,$C27,'Base DRE'!$K1:$K625,$H$2)} -> 0 | F27: {=_xlfn.SUMIFS('Base DRE'!$E1:$E625,'Base DRE'!$I1:$I625,F$7,'Base DRE'!$L1:$L625,$C27,'Base DRE'!$K1:$K625,$H$2)} -> 0 | H27: {=_xlfn.SUMIFS('Base DRE'!$E1:$E625,'Base DRE'!$I1:$I625,H$7,'Base DRE'!$L1:$L625,$C27,'Base DRE'!$K1:$K625,$H$2)} -> 0 | J27: {=_xlfn.SUMIFS('Base DRE'!$E1:$E625,'Base DRE'!$I1:$I625,J$7,'Base DRE'!$L1:$L625,$C27,'Base DRE'!$K1:$K625,$H$2)} -> 0 | L27: {=_xlfn.SUMIFS('Base DRE'!$E1:$E625,'Base DRE'!$I1:$I625,L$7,'Base DRE'!$L1:$L625,$C27,'Base DRE'!$K1:$K625,$H$2)} -> 0 | N27: {=_xlfn.SUMIFS('Base DRE'!$E1:$E625,'Base DRE'!$I1:$I625,N$7,'Base DRE'!$L1:$L625,$C27,'Base DRE'!$K1:$K625,$H$2)} -> 0 | P27: {=_xlfn.SUMIFS('Base DRE'!$E1:$E625,'Base DRE'!$I1:$I625,P$7,'Base DRE'!$L1:$L625,$C27,'Base DRE'!$K1:$K625,$H$2)} -> 0 | R27: {=_xlfn.SUMIFS('Base DRE'!$E1:$E625,'Base DRE'!$I1:$I625,R$7,'Base DRE'!$L1:$L625,$C27,'Base DRE'!$K1:$K625,$H$2)} -> 0 | T27: {=_xlfn.SUMIFS('Base DRE'!$E1:$E625,'Base DRE'!$I1:$I625,T$7,'Base DRE'!$L1:$L625,$C27,'Base DRE'!$K1:$K625,$H$2)} -> 0 | V27: {=_xlfn.SUMIFS('Base DRE'!$E1:$E625,'Base DRE'!$I1:$I625,V$7,'Base DRE'!$L1:$L625,$C27,'Base DRE'!$K1:$K625,$H$2)} -> 0 | X27: {=_xlfn.SUMIFS('Base DRE'!$E1:$E625,'Base DRE'!$I1:$I625,X$7,'Base DRE'!$L1:$L625,$C27,'Base DRE'!$K1:$K625,$H$2)} -> 0 | Z27: {=_xlfn.SUMIFS('Base DRE'!$E1:$E625,'Base DRE'!$I1:$I625,Z$7,'Base DRE'!$L1:$L625,$C27,'Base DRE'!$K1:$K625,$H$2)} -> 0
B28: DESPESA | C28: Frete sobre vendas | D28: {=_xlfn.SUMIFS('Base DRE'!$E1:$E625,'Base DRE'!$I1:$I625,D$7,'Base DRE'!$L1:$L625,$C28,'Base DRE'!$K1:$K625,$H$2)} -> 0 | F28: {=_xlfn.SUMIFS('Base DRE'!$E1:$E625,'Base DRE'!$I1:$I625,F$7,'Base DRE'!$L1:$L625,$C28,'Base DRE'!$K1:$K625,$H$2)} -> 0 | H28: {=_xlfn.SUMIFS('Base DRE'!$E1:$E625,'Base DRE'!$I1:$I625,H$7,'Base DRE'!$L1:$L625,$C28,'Base DRE'!$K1:$K625,$H$2)} -> 0 | J28: {=_xlfn.SUMIFS('Base DRE'!$E1:$E625,'Base DRE'!$I1:$I625,J$7,'Base DRE'!$L1:$L625,$C28,'Base DRE'!$K1:$K625,$H$2)} -> 0 | L28: {=_xlfn.SUMIFS('Base DRE'!$E1:$E625,'Base DRE'!$I1:$I625,L$7,'Base DRE'!$L1:$L625,$C28,'Base DRE'!$K1:$K625,$H$2)} -> 0 | N28: {=_xlfn.SUMIFS('Base DRE'!$E1:$E625,'Base DRE'!$I1:$I625,N$7,'Base DRE'!$L1:$L625,$C28,'Base DRE'!$K1:$K625,$H$2)} -> 0 | P28: {=_xlfn.SUMIFS('Base DRE'!$E1:$E625,'Base DRE'!$I1:$I625,P$7,'Base DRE'!$L1:$L625,$C28,'Base DRE'!$K1:$K625,$H$2)} -> 0 | R28: {=_xlfn.SUMIFS('Base DRE'!$E1:$E625,'Base DRE'!$I1:$I625,R$7,'Base DRE'!$L1:$L625,$C28,'Base DRE'!$K1:$K625,$H$2)} -> 0 | T28: {=_xlfn.SUMIFS('Base DRE'!$E1:$E625,'Base DRE'!$I1:$I625,T$7,'Base DRE'!$L1:$L625,$C28,'Base DRE'!$K1:$K625,$H$2)} -> 0 | V28: {=_xlfn.SUMIFS('Base DRE'!$E1:$E625,'Base DRE'!$I1:$I625,V$7,'Base DRE'!$L1:$L625,$C28,'Base DRE'!$K1:$K625,$H$2)} -> 0 | X28: {=_xlfn.SUMIFS('Base DRE'!$E1:$E625,'Base DRE'!$I1:$I625,X$7,'Base DRE'!$L1:$L625,$C28,'Base DRE'!$K1:$K625,$H$2)} -> 0 | Z28: {=_xlfn.SUMIFS('Base DRE'!$E1:$E625,'Base DRE'!$I1:$I625,Z$7,'Base DRE'!$L1:$L625,$C28,'Base DRE'!$K1:$K625,$H$2)} -> 0
B29: DESPESA
C31: ( = ) Lucro Bruto | D31: {=D22+D24} -> 0 | E31: {=_xlfn.IFERROR(D31/D$8,"")} | F31: {=F22+F24} -> 0 | G31: {=_xlfn.IFERROR(F31/F$8,"")} | H31: {=H22+H24} -> 0 | I31: {=_xlfn.IFERROR(H31/H$8,"")} | J31: {=J22+J24} -> 0 | K31: {=_xlfn.IFERROR(J31/J$8,"")} | L31: {=L22+L24} -> 0 | M31: {=_xlfn.IFERROR(L31/L$8,"")} | N31: {=N22+N24} -> 0 | O31: {=_xlfn.IFERROR(N31/N$8,"")} | P31: {=P22+P24} -> 0 | Q31: {=_xlfn.IFERROR(P31/P$8,"")} | R31: {=R22+R24} -> 0 | S31: {=_xlfn.IFERROR(R31/R$8,"")} | T31: {=T22+T24} -> 0 | U31: {=_xlfn.IFERROR(T31/T$8,"")} | V31: {=V22+V24} -> 0 | W31: {=_xlfn.IFERROR(V31/V$8,"")} | X31: {=X22+X24} -> 0 | Y31: {=_xlfn.IFERROR(X31/X$8,"")} | Z31: {=Z22+Z24} -> 0 | AA31: {=_xlfn.IFERROR(Z31/Z$8,"")}
N32: {=N33/O31}
B33: 4. | C33: ( - ) Despesas Operacionais (Custos Fixos) | D33: {=SUM(D34,D39,D52)} -> 0 | E33: {=_xlfn.IFERROR(D33/D$8,"")} | F33: {=SUM(F34,F39,F52)} -> 0 | G33: {=_xlfn.IFERROR(F33/F$8,"")} | H33: {=SUM(H34,H39,H52)} -> 0 | I33: {=_xlfn.IFERROR(H33/H$8,"")} | J33: {=SUM(J34,J39,J52)} -> 0 | K33: {=_xlfn.IFERROR(J33/J$8,"")} | L33: {=SUM(L34,L39,L52)} -> 0 | M33: {=_xlfn.IFERROR(L33/L$8,"")} | N33: {=SUM(N34,N39,N52)} -> 0 | O33: {=_xlfn.IFERROR(N33/N$8,"")} | P33: {=SUM(P34,P39,P52)} -> 0 | Q33: {=_xlfn.IFERROR(P33/P$8,"")} | R33: {=SUM(R34,R39,R52)} -> 0 | S33: {=_xlfn.IFERROR(R33/R$8,"")} | T33: {=SUM(T34,T39,T52)} -> 0 | U33: {=_xlfn.IFERROR(T33/T$8,"")} | V33: {=SUM(V34,V39,V52)} -> 0 | W33: {=_xlfn.IFERROR(V33/V$8,"")} | X33: {=SUM(X34,X39,X52)} -> 0 | Y33: {=_xlfn.IFERROR(X33/X$8,"")} | Z33: {=SUM(Z34,Z39,Z52)} -> 0 | AA33: {=_xlfn.IFERROR(Z33/Z$8,"")}
B34: 4.1 | C34: Custos Fixos - Despesa Com Pessoal | D34: {=SUM(D35:D37)} -> 0 | E34: {=_xlfn.IFERROR(D34/D$8,"")} | F34: {=SUM(F35:F37)} -> 0 | G34: {=_xlfn.IFERROR(F34/F$8,"")} | H34: {=SUM(H35:H37)} -> 0 | I34: {=_xlfn.IFERROR(H34/H$8,"")} | J34: {=SUM(J35:J37)} -> 0 | K34: {=_xlfn.IFERROR(J34/J$8,"")} | L34: {=SUM(L35:L37)} -> 0 | M34: {=_xlfn.IFERROR(L34/L$8,"")} | N34: {=SUM(N35:N37)} -> 0 | O34: {=_xlfn.IFERROR(N34/N$8,"")} | P34: {=SUM(P35:P37)} -> 0 | Q34: {=_xlfn.IFERROR(P34/P$8,"")} | R34: {=SUM(R35:R37)} -> 0 | S34: {=_xlfn.IFERROR(R34/R$8,"")} | T34: {=SUM(T35:T37)} -> 0 | U34: {=_xlfn.IFERROR(T34/T$8,"")} | V34: {=SUM(V35:V37)} -> 0 | W34: {=_xlfn.IFERROR(V34/V$8,"")} | X34: {=SUM(X35:X37)} -> 0 | Y34: {=_xlfn.IFERROR(X34/X$8,"")} | Z34: {=SUM(Z35:Z37)} -> 0 | AA34: {=_xlfn.IFERROR(Z34/Z$8,"")}
C35: Salários e Encargos Administrativos | D35: {=_xlfn.SUMIFS('Base DRE'!$E1:$E625,'Base DRE'!$I1:$I625,D$7,'Base DRE'!$L1:$L625,$C35,'Base DRE'!$K1:$K625,$H$2)} -> 0 | F35: {=_xlfn.SUMIFS('Base DRE'!$E1:$E625,'Base DRE'!$I1:$I625,F$7,'Base DRE'!$L1:$L625,$C35,'Base DRE'!$K1:$K625,$H$2)} -> 0 | H35: {=_xlfn.SUMIFS('Base DRE'!$E1:$E625,'Base DRE'!$I1:$I625,H$7,'Base DRE'!$L1:$L625,$C35,'Base DRE'!$K1:$K625,$H$2)} -> 0 | J35: {=_xlfn.SUMIFS('Base DRE'!$E1:$E625,'Base DRE'!$I1:$I625,J$7,'Base DRE'!$L1:$L625,$C35,'Base DRE'!$K1:$K625,$H$2)} -> 0 | L35: {=_xlfn.SUMIFS('Base DRE'!$E1:$E625,'Base DRE'!$I1:$I625,L$7,'Base DRE'!$L1:$L625,$C35,'Base DRE'!$K1:$K625,$H$2)} -> 0 | N35: {=_xlfn.SUMIFS('Base DRE'!$E1:$E625,'Base DRE'!$I1:$I625,N$7,'Base DRE'!$L1:$L625,$C35,'Base DRE'!$K1:$K625,$H$2)} -> 0 | P35: {=_xlfn.SUMIFS('Base DRE'!$E1:$E625,'Base DRE'!$I1:$I625,P$7,'Base DRE'!$L1:$L625,$C35,'Base DRE'!$K1:$K625,$H$2)} -> 0 | R35: {=_xlfn.SUMIFS('Base DRE'!$E1:$E625,'Base DRE'!$I1:$I625,R$7,'Base DRE'!$L1:$L625,$C35,'Base DRE'!$K1:$K625,$H$2)} -> 0 | T35: {=_xlfn.SUMIFS('Base DRE'!$E1:$E625,'Base DRE'!$I1:$I625,T$7,'Base DRE'!$L1:$L625,$C35,'Base DRE'!$K1:$K625,$H$2)} -> 0 | V35: {=_xlfn.SUMIFS('Base DRE'!$E1:$E625,'Base DRE'!$I1:$I625,V$7,'Base DRE'!$L1:$L625,$C35,'Base DRE'!$K1:$K625,$H$2)} -> 0 | X35: {=_xlfn.SUMIFS('Base DRE'!$E1:$E625,'Base DRE'!$I1:$I625,X$7,'Base DRE'!$L1:$L625,$C35,'Base DRE'!$K1:$K625,$H$2)} -> 0 | Z35: {=_xlfn.SUMIFS('Base DRE'!$E1:$E625,'Base DRE'!$I1:$I625,Z$7,'Base DRE'!$L1:$L625,$C35,'Base DRE'!$K1:$K625,$H$2)} -> 0
C36: Salários e Encargos do Comercial | D36: {=_xlfn.SUMIFS('Base DRE'!$E1:$E625,'Base DRE'!$I1:$I625,D$7,'Base DRE'!$L1:$L625,$C36,'Base DRE'!$K1:$K625,$H$2)} -> 0 | F36: {=_xlfn.SUMIFS('Base DRE'!$E1:$E625,'Base DRE'!$I1:$I625,F$7,'Base DRE'!$L1:$L625,$C36,'Base DRE'!$K1:$K625,$H$2)} -> 0 | H36: {=_xlfn.SUMIFS('Base DRE'!$E1:$E625,'Base DRE'!$I1:$I625,H$7,'Base DRE'!$L1:$L625,$C36,'Base DRE'!$K1:$K625,$H$2)} -> 0 | J36: {=_xlfn.SUMIFS('Base DRE'!$E1:$E625,'Base DRE'!$I1:$I625,J$7,'Base DRE'!$L1:$L625,$C36,'Base DRE'!$K1:$K625,$H$2)} -> 0 | L36: {=_xlfn.SUMIFS('Base DRE'!$E1:$E625,'Base DRE'!$I1:$I625,L$7,'Base DRE'!$L1:$L625,$C36,'Base DRE'!$K1:$K625,$H$2)} -> 0 | N36: {=_xlfn.SUMIFS('Base DRE'!$E1:$E625,'Base DRE'!$I1:$I625,N$7,'Base DRE'!$L1:$L625,$C36,'Base DRE'!$K1:$K625,$H$2)} -> 0 | P36: {=_xlfn.SUMIFS('Base DRE'!$E1:$E625,'Base DRE'!$I1:$I625,P$7,'Base DRE'!$L1:$L625,$C36,'Base DRE'!$K1:$K625,$H$2)} -> 0 | R36: {=_xlfn.SUMIFS('Base DRE'!$E1:$E625,'Base DRE'!$I1:$I625,R$7,'Base DRE'!$L1:$L625,$C36,'Base DRE'!$K1:$K625,$H$2)} -> 0 | T36: {=_xlfn.SUMIFS('Base DRE'!$E1:$E625,'Base DRE'!$I1:$I625,T$7,'Base DRE'!$L1:$L625,$C36,'Base DRE'!$K1:$K625,$H$2)} -> 0 | V36: {=_xlfn.SUMIFS('Base DRE'!$E1:$E625,'Base DRE'!$I1:$I625,V$7,'Base DRE'!$L1:$L625,$C36,'Base DRE'!$K1:$K625,$H$2)} -> 0 | X36: {=_xlfn.SUMIFS('Base DRE'!$E1:$E625,'Base DRE'!$I1:$I625,X$7,'Base DRE'!$L1:$L625,$C36,'Base DRE'!$K1:$K625,$H$2)} -> 0 | Z36: {=_xlfn.SUMIFS('Base DRE'!$E1:$E625,'Base DRE'!$I1:$I625,Z$7,'Base DRE'!$L1:$L625,$C36,'Base DRE'!$K1:$K625,$H$2)} -> 0
C37: Provisões (13º, férias, etc.) | D37: {=_xlfn.SUMIFS('Base DRE'!$E1:$E625,'Base DRE'!$I1:$I625,D$7,'Base DRE'!$L1:$L625,$C37,'Base DRE'!$K1:$K625,$H$2)} -> 0 | F37: {=_xlfn.SUMIFS('Base DRE'!$E1:$E625,'Base DRE'!$I1:$I625,F$7,'Base DRE'!$L1:$L625,$C37,'Base DRE'!$K1:$K625,$H$2)} -> 0 | H37: {=_xlfn.SUMIFS('Base DRE'!$E1:$E625,'Base DRE'!$I1:$I625,H$7,'Base DRE'!$L1:$L625,$C37,'Base DRE'!$K1:$K625,$H$2)} -> 0 | J37: {=_xlfn.SUMIFS('Base DRE'!$E1:$E625,'Base DRE'!$I1:$I625,J$7,'Base DRE'!$L1:$L625,$C37,'Base DRE'!$K1:$K625,$H$2)} -> 0 | L37: {=_xlfn.SUMIFS('Base DRE'!$E1:$E625,'Base DRE'!$I1:$I625,L$7,'Base DRE'!$L1:$L625,$C37,'Base DRE'!$K1:$K625,$H$2)} -> 0 | N37: {=_xlfn.SUMIFS('Base DRE'!$E1:$E625,'Base DRE'!$I1:$I625,N$7,'Base DRE'!$L1:$L625,$C37,'Base DRE'!$K1:$K625,$H$2)} -> 0 | P37: {=_xlfn.SUMIFS('Base DRE'!$E1:$E625,'Base DRE'!$I1:$I625,P$7,'Base DRE'!$L1:$L625,$C37,'Base DRE'!$K1:$K625,$H$2)} -> 0 | R37: {=_xlfn.SUMIFS('Base DRE'!$E1:$E625,'Base DRE'!$I1:$I625,R$7,'Base DRE'!$L1:$L625,$C37,'Base DRE'!$K1:$K625,$H$2)} -> 0 | T37: {=_xlfn.SUMIFS('Base DRE'!$E1:$E625,'Base DRE'!$I1:$I625,T$7,'Base DRE'!$L1:$L625,$C37,'Base DRE'!$K1:$K625,$H$2)} -> 0 | V37: {=_xlfn.SUMIFS('Base DRE'!$E1:$E625,'Base DRE'!$I1:$I625,V$7,'Base DRE'!$L1:$L625,$C37,'Base DRE'!$K1:$K625,$H$2)} -> 0 | X37: {=_xlfn.SUMIFS('Base DRE'!$E1:$E625,'Base DRE'!$I1:$I625,X$7,'Base DRE'!$L1:$L625,$C37,'Base DRE'!$K1:$K625,$H$2)} -> 0 | Z37: {=_xlfn.SUMIFS('Base DRE'!$E1:$E625,'Base DRE'!$I1:$I625,Z$7,'Base DRE'!$L1:$L625,$C37,'Base DRE'!$K1:$K625,$H$2)} -> 0
B39: 4.2 | C39: Custos Fixos - Despesa Administrativa | D39: {=SUM(D40:D51)} -> 0 | E39: {=_xlfn.IFERROR(D39/D$8,"")} | F39: {=SUM(F40:F54)} -> 0 | G39: {=_xlfn.IFERROR(F39/F$8,"")} | H39: {=SUM(H40:H54)} -> 0 | I39: {=_xlfn.IFERROR(H39/H$8,"")} | J39: {=SUM(J40:J54)} -> 0 | K39: {=_xlfn.IFERROR(J39/J$8,"")} | L39: {=SUM(L40:L54)} -> 0 | M39: {=_xlfn.IFERROR(L39/L$8,"")} | N39: {=SUM(N40:N54)} -> 0 | O39: {=_xlfn.IFERROR(N39/N$8,"")} | P39: {=SUM(P40:P54)} -> 0 | Q39: {=_xlfn.IFERROR(P39/P$8,"")} | R39: {=SUM(R40:R54)} -> 0 | S39: {=_xlfn.IFERROR(R39/R$8,"")} | T39: {=SUM(T40:T54)} -> 0 | U39: {=_xlfn.IFERROR(T39/T$8,"")} | V39: {=SUM(V40:V54)} -> 0 | W39: {=_xlfn.IFERROR(V39/V$8,"")} | X39: {=SUM(X40:X54)} -> 0 | Y39: {=_xlfn.IFERROR(X39/X$8,"")} | Z39: {=SUM(Z40:Z54)} -> 0 | AA39: {=_xlfn.IFERROR(Z39/Z$8,"")}
B40: DESPESA | C40: Aluguel | D40: {=_xlfn.SUMIFS('Base DRE'!$E1:$E625,'Base DRE'!$I1:$I625,D$7,'Base DRE'!$L1:$L625,$C40,'Base DRE'!$K1:$K625,$H$2)} -> 0 | F40: {=_xlfn.SUMIFS('Base DRE'!$E1:$E625,'Base DRE'!$I1:$I625,F$7,'Base DRE'!$L1:$L625,$C40,'Base DRE'!$K1:$K625,$H$2)} -> 0 | H40: {=_xlfn.SUMIFS('Base DRE'!$E1:$E625,'Base DRE'!$I1:$I625,H$7,'Base DRE'!$L1:$L625,$C40,'Base DRE'!$K1:$K625,$H$2)} -> 0 | J40: {=_xlfn.SUMIFS('Base DRE'!$E1:$E625,'Base DRE'!$I1:$I625,J$7,'Base DRE'!$L1:$L625,$C40,'Base DRE'!$K1:$K625,$H$2)} -> 0 | L40: {=_xlfn.SUMIFS('Base DRE'!$E1:$E625,'Base DRE'!$I1:$I625,L$7,'Base DRE'!$L1:$L625,$C40,'Base DRE'!$K1:$K625,$H$2)} -> 0 | N40: {=_xlfn.SUMIFS('Base DRE'!$E1:$E625,'Base DRE'!$I1:$I625,N$7,'Base DRE'!$L1:$L625,$C40,'Base DRE'!$K1:$K625,$H$2)} -> 0 | P40: {=_xlfn.SUMIFS('Base DRE'!$E1:$E625,'Base DRE'!$I1:$I625,P$7,'Base DRE'!$L1:$L625,$C40,'Base DRE'!$K1:$K625,$H$2)} -> 0 | R40: {=_xlfn.SUMIFS('Base DRE'!$E1:$E625,'Base DRE'!$I1:$I625,R$7,'Base DRE'!$L1:$L625,$C40,'Base DRE'!$K1:$K625,$H$2)} -> 0 | T40: {=_xlfn.SUMIFS('Base DRE'!$E1:$E625,'Base DRE'!$I1:$I625,T$7,'Base DRE'!$L1:$L625,$C40,'Base DRE'!$K1:$K625,$H$2)} -> 0 | V40: {=_xlfn.SUMIFS('Base DRE'!$E1:$E625,'Base DRE'!$I1:$I625,V$7,'Base DRE'!$L1:$L625,$C40,'Base DRE'!$K1:$K625,$H$2)} -> 0 | X40: {=_xlfn.SUMIFS('Base DRE'!$E1:$E625,'Base DRE'!$I1:$I625,X$7,'Base DRE'!$L1:$L625,$C40,'Base DRE'!$K1:$K625,$H$2)} -> 0 | Z40: {=_xlfn.SUMIFS('Base DRE'!$E1:$E625,'Base DRE'!$I1:$I625,Z$7,'Base DRE'!$L1:$L625,$C40,'Base DRE'!$K1:$K625,$H$2)} -> 0
C41: Contabilidade | D41: {=_xlfn.SUMIFS('Base DRE'!$E1:$E625,'Base DRE'!$I1:$I625,D$7,'Base DRE'!$L1:$L625,$C41,'Base DRE'!$K1:$K625,$H$2)} -> 0 | F41: {=_xlfn.SUMIFS('Base DRE'!$E1:$E625,'Base DRE'!$I1:$I625,F$7,'Base DRE'!$L1:$L625,$C41,'Base DRE'!$K1:$K625,$H$2)} -> 0 | H41: {=_xlfn.SUMIFS('Base DRE'!$E1:$E625,'Base DRE'!$I1:$I625,H$7,'Base DRE'!$L1:$L625,$C41,'Base DRE'!$K1:$K625,$H$2)} -> 0 | J41: {=_xlfn.SUMIFS('Base DRE'!$E1:$E625,'Base DRE'!$I1:$I625,J$7,'Base DRE'!$L1:$L625,$C41,'Base DRE'!$K1:$K625,$H$2)} -> 0 | L41: {=_xlfn.SUMIFS('Base DRE'!$E1:$E625,'Base DRE'!$I1:$I625,L$7,'Base DRE'!$L1:$L625,$C41,'Base DRE'!$K1:$K625,$H$2)} -> 0 | N41: {=_xlfn.SUMIFS('Base DRE'!$E1:$E625,'Base DRE'!$I1:$I625,N$7,'Base DRE'!$L1:$L625,$C41,'Base DRE'!$K1:$K625,$H$2)} -> 0 | P41: {=_xlfn.SUMIFS('Base DRE'!$E1:$E625,'Base DRE'!$I1:$I625,P$7,'Base DRE'!$L1:$L625,$C41,'Base DRE'!$K1:$K625,$H$2)} -> 0 | R41: {=_xlfn.SUMIFS('Base DRE'!$E1:$E625,'Base DRE'!$I1:$I625,R$7,'Base DRE'!$L1:$L625,$C41,'Base DRE'!$K1:$K625,$H$2)} -> 0 | T41: {=_xlfn.SUMIFS('Base DRE'!$E1:$E625,'Base DRE'!$I1:$I625,T$7,'Base DRE'!$L1:$L625,$C41,'Base DRE'!$K1:$K625,$H$2)} -> 0 | V41: {=_xlfn.SUMIFS('Base DRE'!$E1:$E625,'Base DRE'!$I1:$I625,V$7,'Base DRE'!$L1:$L625,$C41,'Base DRE'!$K1:$K625,$H$2)} -> 0 | X41: {=_xlfn.SUMIFS('Base DRE'!$E1:$E625,'Base DRE'!$I1:$I625,X$7,'Base DRE'!$L1:$L625,$C41,'Base DRE'!$K1:$K625,$H$2)} -> 0 | Z41: {=_xlfn.SUMIFS('Base DRE'!$E1:$E625,'Base DRE'!$I1:$I625,Z$7,'Base DRE'!$L1:$L625,$C41,'Base DRE'!$K1:$K625,$H$2)} -> 0
C42: Consultorias | D42: {=_xlfn.SUMIFS('Base DRE'!$E1:$E625,'Base DRE'!$I1:$I625,D$7,'Base DRE'!$L1:$L625,$C42,'Base DRE'!$K1:$K625,$H$2)} -> 0 | F42: {=_xlfn.SUMIFS('Base DRE'!$E1:$E625,'Base DRE'!$I1:$I625,F$7,'Base DRE'!$L1:$L625,$C42,'Base DRE'!$K1:$K625,$H$2)} -> 0 | H42: {=_xlfn.SUMIFS('Base DRE'!$E1:$E625,'Base DRE'!$I1:$I625,H$7,'Base DRE'!$L1:$L625,$C42,'Base DRE'!$K1:$K625,$H$2)} -> 0 | J42: {=_xlfn.SUMIFS('Base DRE'!$E1:$E625,'Base DRE'!$I1:$I625,J$7,'Base DRE'!$L1:$L625,$C42,'Base DRE'!$K1:$K625,$H$2)} -> 0 | L42: {=_xlfn.SUMIFS('Base DRE'!$E1:$E625,'Base DRE'!$I1:$I625,L$7,'Base DRE'!$L1:$L625,$C42,'Base DRE'!$K1:$K625,$H$2)} -> 0 | N42: {=_xlfn.SUMIFS('Base DRE'!$E1:$E625,'Base DRE'!$I1:$I625,N$7,'Base DRE'!$L1:$L625,$C42,'Base DRE'!$K1:$K625,$H$2)} -> 0 | P42: {=_xlfn.SUMIFS('Base DRE'!$E1:$E625,'Base DRE'!$I1:$I625,P$7,'Base DRE'!$L1:$L625,$C42,'Base DRE'!$K1:$K625,$H$2)} -> 0 | R42: {=_xlfn.SUMIFS('Base DRE'!$E1:$E625,'Base DRE'!$I1:$I625,R$7,'Base DRE'!$L1:$L625,$C42,'Base DRE'!$K1:$K625,$H$2)} -> 0 | T42: {=_xlfn.SUMIFS('Base DRE'!$E1:$E625,'Base DRE'!$I1:$I625,T$7,'Base DRE'!$L1:$L625,$C42,'Base DRE'!$K1:$K625,$H$2)} -> 0 | V42: {=_xlfn.SUMIFS('Base DRE'!$E1:$E625,'Base DRE'!$I1:$I625,V$7,'Base DRE'!$L1:$L625,$C42,'Base DRE'!$K1:$K625,$H$2)} -> 0 | X42: {=_xlfn.SUMIFS('Base DRE'!$E1:$E625,'Base DRE'!$I1:$I625,X$7,'Base DRE'!$L1:$L625,$C42,'Base DRE'!$K1:$K625,$H$2)} -> 0 | Z42: {=_xlfn.SUMIFS('Base DRE'!$E1:$E625,'Base DRE'!$I1:$I625,Z$7,'Base DRE'!$L1:$L625,$C42,'Base DRE'!$K1:$K625,$H$2)} -> 0
C43: Licenças e Softwares e TI | D43: {=_xlfn.SUMIFS('Base DRE'!$E1:$E625,'Base DRE'!$I1:$I625,D$7,'Base DRE'!$L1:$L625,$C43,'Base DRE'!$K1:$K625,$H$2)} -> 0 | F43: {=_xlfn.SUMIFS('Base DRE'!$E1:$E625,'Base DRE'!$I1:$I625,F$7,'Base DRE'!$L1:$L625,$C43,'Base DRE'!$K1:$K625,$H$2)} -> 0 | H43: {=_xlfn.SUMIFS('Base DRE'!$E1:$E625,'Base DRE'!$I1:$I625,H$7,'Base DRE'!$L1:$L625,$C43,'Base DRE'!$K1:$K625,$H$2)} -> 0 | J43: {=_xlfn.SUMIFS('Base DRE'!$E1:$E625,'Base DRE'!$I1:$I625,J$7,'Base DRE'!$L1:$L625,$C43,'Base DRE'!$K1:$K625,$H$2)} -> 0 | L43: {=_xlfn.SUMIFS('Base DRE'!$E1:$E625,'Base DRE'!$I1:$I625,L$7,'Base DRE'!$L1:$L625,$C43,'Base DRE'!$K1:$K625,$H$2)} -> 0 | N43: {=_xlfn.SUMIFS('Base DRE'!$E1:$E625,'Base DRE'!$I1:$I625,N$7,'Base DRE'!$L1:$L625,$C43,'Base DRE'!$K1:$K625,$H$2)} -> 0 | P43: {=_xlfn.SUMIFS('Base DRE'!$E1:$E625,'Base DRE'!$I1:$I625,P$7,'Base DRE'!$L1:$L625,$C43,'Base DRE'!$K1:$K625,$H$2)} -> 0 | R43: {=_xlfn.SUMIFS('Base DRE'!$E1:$E625,'Base DRE'!$I1:$I625,R$7,'Base DRE'!$L1:$L625,$C43,'Base DRE'!$K1:$K625,$H$2)} -> 0 | T43: {=_xlfn.SUMIFS('Base DRE'!$E1:$E625,'Base DRE'!$I1:$I625,T$7,'Base DRE'!$L1:$L625,$C43,'Base DRE'!$K1:$K625,$H$2)} -> 0 | V43: {=_xlfn.SUMIFS('Base DRE'!$E1:$E625,'Base DRE'!$I1:$I625,V$7,'Base DRE'!$L1:$L625,$C43,'Base DRE'!$K1:$K625,$H$2)} -> 0 | X43: {=_xlfn.SUMIFS('Base DRE'!$E1:$E625,'Base DRE'!$I1:$I625,X$7,'Base DRE'!$L1:$L625,$C43,'Base DRE'!$K1:$K625,$H$2)} -> 0 | Z43: {=_xlfn.SUMIFS('Base DRE'!$E1:$E625,'Base DRE'!$I1:$I625,Z$7,'Base DRE'!$L1:$L625,$C43,'Base DRE'!$K1:$K625,$H$2)} -> 0
C44: Marketing e Publicidade | D44: {=_xlfn.SUMIFS('Base DRE'!$E1:$E625,'Base DRE'!$I1:$I625,D$7,'Base DRE'!$L1:$L625,$C44,'Base DRE'!$K1:$K625,$H$2)} -> 0 | F44: {=_xlfn.SUMIFS('Base DRE'!$E1:$E625,'Base DRE'!$I1:$I625,F$7,'Base DRE'!$L1:$L625,$C44,'Base DRE'!$K1:$K625,$H$2)} -> 0 | H44: {=_xlfn.SUMIFS('Base DRE'!$E1:$E625,'Base DRE'!$I1:$I625,H$7,'Base DRE'!$L1:$L625,$C44,'Base DRE'!$K1:$K625,$H$2)} -> 0 | J44: {=_xlfn.SUMIFS('Base DRE'!$E1:$E625,'Base DRE'!$I1:$I625,J$7,'Base DRE'!$L1:$L625,$C44,'Base DRE'!$K1:$K625,$H$2)} -> 0 | L44: {=_xlfn.SUMIFS('Base DRE'!$E1:$E625,'Base DRE'!$I1:$I625,L$7,'Base DRE'!$L1:$L625,$C44,'Base DRE'!$K1:$K625,$H$2)} -> 0 | N44: {=_xlfn.SUMIFS('Base DRE'!$E1:$E625,'Base DRE'!$I1:$I625,N$7,'Base DRE'!$L1:$L625,$C44,'Base DRE'!$K1:$K625,$H$2)} -> 0 | P44: {=_xlfn.SUMIFS('Base DRE'!$E1:$E625,'Base DRE'!$I1:$I625,P$7,'Base DRE'!$L1:$L625,$C44,'Base DRE'!$K1:$K625,$H$2)} -> 0 | R44: {=_xlfn.SUMIFS('Base DRE'!$E1:$E625,'Base DRE'!$I1:$I625,R$7,'Base DRE'!$L1:$L625,$C44,'Base DRE'!$K1:$K625,$H$2)} -> 0 | T44: {=_xlfn.SUMIFS('Base DRE'!$E1:$E625,'Base DRE'!$I1:$I625,T$7,'Base DRE'!$L1:$L625,$C44,'Base DRE'!$K1:$K625,$H$2)} -> 0 | V44: {=_xlfn.SUMIFS('Base DRE'!$E1:$E625,'Base DRE'!$I1:$I625,V$7,'Base DRE'!$L1:$L625,$C44,'Base DRE'!$K1:$K625,$H$2)} -> 0 | X44: {=_xlfn.SUMIFS('Base DRE'!$E1:$E625,'Base DRE'!$I1:$I625,X$7,'Base DRE'!$L1:$L625,$C44,'Base DRE'!$K1:$K625,$H$2)} -> 0 | Z44: {=_xlfn.SUMIFS('Base DRE'!$E1:$E625,'Base DRE'!$I1:$I625,Z$7,'Base DRE'!$L1:$L625,$C44,'Base DRE'!$K1:$K625,$H$2)} -> 0
C45: Ferramentas de CRM ou automação | D45: {=_xlfn.SUMIFS('Base DRE'!$E1:$E625,'Base DRE'!$I1:$I625,D$7,'Base DRE'!$L1:$L625,$C45,'Base DRE'!$K1:$K625,$H$2)} -> 0 | F45: {=_xlfn.SUMIFS('Base DRE'!$E1:$E625,'Base DRE'!$I1:$I625,F$7,'Base DRE'!$L1:$L625,$C45,'Base DRE'!$K1:$K625,$H$2)} -> 0 | H45: {=_xlfn.SUMIFS('Base DRE'!$E1:$E625,'Base DRE'!$I1:$I625,H$7,'Base DRE'!$L1:$L625,$C45,'Base DRE'!$K1:$K625,$H$2)} -> 0 | J45: {=_xlfn.SUMIFS('Base DRE'!$E1:$E625,'Base DRE'!$I1:$I625,J$7,'Base DRE'!$L1:$L625,$C45,'Base DRE'!$K1:$K625,$H$2)} -> 0 | L45: {=_xlfn.SUMIFS('Base DRE'!$E1:$E625,'Base DRE'!$I1:$I625,L$7,'Base DRE'!$L1:$L625,$C45,'Base DRE'!$K1:$K625,$H$2)} -> 0 | N45: {=_xlfn.SUMIFS('Base DRE'!$E1:$E625,'Base DRE'!$I1:$I625,N$7,'Base DRE'!$L1:$L625,$C45,'Base DRE'!$K1:$K625,$H$2)} -> 0 | P45: {=_xlfn.SUMIFS('Base DRE'!$E1:$E625,'Base DRE'!$I1:$I625,P$7,'Base DRE'!$L1:$L625,$C45,'Base DRE'!$K1:$K625,$H$2)} -> 0 | R45: {=_xlfn.SUMIFS('Base DRE'!$E1:$E625,'Base DRE'!$I1:$I625,R$7,'Base DRE'!$L1:$L625,$C45,'Base DRE'!$K1:$K625,$H$2)} -> 0 | T45: {=_xlfn.SUMIFS('Base DRE'!$E1:$E625,'Base DRE'!$I1:$I625,T$7,'Base DRE'!$L1:$L625,$C45,'Base DRE'!$K1:$K625,$H$2)} -> 0 | V45: {=_xlfn.SUMIFS('Base DRE'!$E1:$E625,'Base DRE'!$I1:$I625,V$7,'Base DRE'!$L1:$L625,$C45,'Base DRE'!$K1:$K625,$H$2)} -> 0 | X45: {=_xlfn.SUMIFS('Base DRE'!$E1:$E625,'Base DRE'!$I1:$I625,X$7,'Base DRE'!$L1:$L625,$C45,'Base DRE'!$K1:$K625,$H$2)} -> 0 | Z45: {=_xlfn.SUMIFS('Base DRE'!$E1:$E625,'Base DRE'!$I1:$I625,Z$7,'Base DRE'!$L1:$L625,$C45,'Base DRE'!$K1:$K625,$H$2)} -> 0
C46: Viagens e Refeições Comerciais | D46: {=_xlfn.SUMIFS('Base DRE'!$E1:$E625,'Base DRE'!$I1:$I625,D$7,'Base DRE'!$L1:$L625,$C46,'Base DRE'!$K1:$K625,$H$2)} -> 0 | F46: {=_xlfn.SUMIFS('Base DRE'!$E1:$E625,'Base DRE'!$I1:$I625,F$7,'Base DRE'!$L1:$L625,$C46,'Base DRE'!$K1:$K625,$H$2)} -> 0 | H46: {=_xlfn.SUMIFS('Base DRE'!$E1:$E625,'Base DRE'!$I1:$I625,H$7,'Base DRE'!$L1:$L625,$C46,'Base DRE'!$K1:$K625,$H$2)} -> 0 | J46: {=_xlfn.SUMIFS('Base DRE'!$E1:$E625,'Base DRE'!$I1:$I625,J$7,'Base DRE'!$L1:$L625,$C46,'Base DRE'!$K1:$K625,$H$2)} -> 0 | L46: {=_xlfn.SUMIFS('Base DRE'!$E1:$E625,'Base DRE'!$I1:$I625,L$7,'Base DRE'!$L1:$L625,$C46,'Base DRE'!$K1:$K625,$H$2)} -> 0 | N46: {=_xlfn.SUMIFS('Base DRE'!$E1:$E625,'Base DRE'!$I1:$I625,N$7,'Base DRE'!$L1:$L625,$C46,'Base DRE'!$K1:$K625,$H$2)} -> 0 | P46: {=_xlfn.SUMIFS('Base DRE'!$E1:$E625,'Base DRE'!$I1:$I625,P$7,'Base DRE'!$L1:$L625,$C46,'Base DRE'!$K1:$K625,$H$2)} -> 0 | R46: {=_xlfn.SUMIFS('Base DRE'!$E1:$E625,'Base DRE'!$I1:$I625,R$7,'Base DRE'!$L1:$L625,$C46,'Base DRE'!$K1:$K625,$H$2)} -> 0 | T46: {=_xlfn.SUMIFS('Base DRE'!$E1:$E625,'Base DRE'!$I1:$I625,T$7,'Base DRE'!$L1:$L625,$C46,'Base DRE'!$K1:$K625,$H$2)} -> 0 | V46: {=_xlfn.SUMIFS('Base DRE'!$E1:$E625,'Base DRE'!$I1:$I625,V$7,'Base DRE'!$L1:$L625,$C46,'Base DRE'!$K1:$K625,$H$2)} -> 0 | X46: {=_xlfn.SUMIFS('Base DRE'!$E1:$E625,'Base DRE'!$I1:$I625,X$7,'Base DRE'!$L1:$L625,$C46,'Base DRE'!$K1:$K625,$H$2)} -> 0 | Z46: {=_xlfn.SUMIFS('Base DRE'!$E1:$E625,'Base DRE'!$I1:$I625,Z$7,'Base DRE'!$L1:$L625,$C46,'Base DRE'!$K1:$K625,$H$2)} -> 0
C47: Energia Elétrica | D47: {=_xlfn.SUMIFS('Base DRE'!$E1:$E625,'Base DRE'!$I1:$I625,D$7,'Base DRE'!$L1:$L625,$C47,'Base DRE'!$K1:$K625,$H$2)} -> 0 | F47: {=_xlfn.SUMIFS('Base DRE'!$E1:$E625,'Base DRE'!$I1:$I625,F$7,'Base DRE'!$L1:$L625,$C47,'Base DRE'!$K1:$K625,$H$2)} -> 0 | H47: {=_xlfn.SUMIFS('Base DRE'!$E1:$E625,'Base DRE'!$I1:$I625,H$7,'Base DRE'!$L1:$L625,$C47,'Base DRE'!$K1:$K625,$H$2)} -> 0 | J47: {=_xlfn.SUMIFS('Base DRE'!$E1:$E625,'Base DRE'!$I1:$I625,J$7,'Base DRE'!$L1:$L625,$C47,'Base DRE'!$K1:$K625,$H$2)} -> 0 | L47: {=_xlfn.SUMIFS('Base DRE'!$E1:$E625,'Base DRE'!$I1:$I625,L$7,'Base DRE'!$L1:$L625,$C47,'Base DRE'!$K1:$K625,$H$2)} -> 0 | N47: {=_xlfn.SUMIFS('Base DRE'!$E1:$E625,'Base DRE'!$I1:$I625,N$7,'Base DRE'!$L1:$L625,$C47,'Base DRE'!$K1:$K625,$H$2)} -> 0 | P47: {=_xlfn.SUMIFS('Base DRE'!$E1:$E625,'Base DRE'!$I1:$I625,P$7,'Base DRE'!$L1:$L625,$C47,'Base DRE'!$K1:$K625,$H$2)} -> 0 | R47: {=_xlfn.SUMIFS('Base DRE'!$E1:$E625,'Base DRE'!$I1:$I625,R$7,'Base DRE'!$L1:$L625,$C47,'Base DRE'!$K1:$K625,$H$2)} -> 0 | T47: {=_xlfn.SUMIFS('Base DRE'!$E1:$E625,'Base DRE'!$I1:$I625,T$7,'Base DRE'!$L1:$L625,$C47,'Base DRE'!$K1:$K625,$H$2)} -> 0 | V47: {=_xlfn.SUMIFS('Base DRE'!$E1:$E625,'Base DRE'!$I1:$I625,V$7,'Base DRE'!$L1:$L625,$C47,'Base DRE'!$K1:$K625,$H$2)} -> 0 | X47: {=_xlfn.SUMIFS('Base DRE'!$E1:$E625,'Base DRE'!$I1:$I625,X$7,'Base DRE'!$L1:$L625,$C47,'Base DRE'!$K1:$K625,$H$2)} -> 0 | Z47: {=_xlfn.SUMIFS('Base DRE'!$E1:$E625,'Base DRE'!$I1:$I625,Z$7,'Base DRE'!$L1:$L625,$C47,'Base DRE'!$K1:$K625,$H$2)} -> 0
C48: Água | D48: {=_xlfn.SUMIFS('Base DRE'!$E1:$E625,'Base DRE'!$I1:$I625,D$7,'Base DRE'!$L1:$L625,$C48,'Base DRE'!$K1:$K625,$H$2)} -> 0 | F48: {=_xlfn.SUMIFS('Base DRE'!$E1:$E625,'Base DRE'!$I1:$I625,F$7,'Base DRE'!$L1:$L625,$C48,'Base DRE'!$K1:$K625,$H$2)} -> 0 | H48: {=_xlfn.SUMIFS('Base DRE'!$E1:$E625,'Base DRE'!$I1:$I625,H$7,'Base DRE'!$L1:$L625,$C48,'Base DRE'!$K1:$K625,$H$2)} -> 0 | J48: {=_xlfn.SUMIFS('Base DRE'!$E1:$E625,'Base DRE'!$I1:$I625,J$7,'Base DRE'!$L1:$L625,$C48,'Base DRE'!$K1:$K625,$H$2)} -> 0 | L48: {=_xlfn.SUMIFS('Base DRE'!$E1:$E625,'Base DRE'!$I1:$I625,L$7,'Base DRE'!$L1:$L625,$C48,'Base DRE'!$K1:$K625,$H$2)} -> 0 | N48: {=_xlfn.SUMIFS('Base DRE'!$E1:$E625,'Base DRE'!$I1:$I625,N$7,'Base DRE'!$L1:$L625,$C48,'Base DRE'!$K1:$K625,$H$2)} -> 0 | P48: {=_xlfn.SUMIFS('Base DRE'!$E1:$E625,'Base DRE'!$I1:$I625,P$7,'Base DRE'!$L1:$L625,$C48,'Base DRE'!$K1:$K625,$H$2)} -> 0 | R48: {=_xlfn.SUMIFS('Base DRE'!$E1:$E625,'Base DRE'!$I1:$I625,R$7,'Base DRE'!$L1:$L625,$C48,'Base DRE'!$K1:$K625,$H$2)} -> 0 | T48: {=_xlfn.SUMIFS('Base DRE'!$E1:$E625,'Base DRE'!$I1:$I625,T$7,'Base DRE'!$L1:$L625,$C48,'Base DRE'!$K1:$K625,$H$2)} -> 0 | V48: {=_xlfn.SUMIFS('Base DRE'!$E1:$E625,'Base DRE'!$I1:$I625,V$7,'Base DRE'!$L1:$L625,$C48,'Base DRE'!$K1:$K625,$H$2)} -> 0 | X48: {=_xlfn.SUMIFS('Base DRE'!$E1:$E625,'Base DRE'!$I1:$I625,X$7,'Base DRE'!$L1:$L625,$C48,'Base DRE'!$K1:$K625,$H$2)} -> 0 | Z48: {=_xlfn.SUMIFS('Base DRE'!$E1:$E625,'Base DRE'!$I1:$I625,Z$7,'Base DRE'!$L1:$L625,$C48,'Base DRE'!$K1:$K625,$H$2)} -> 0
C49: Internet e Telefonia | D49: {=_xlfn.SUMIFS('Base DRE'!$E1:$E625,'Base DRE'!$I1:$I625,D$7,'Base DRE'!$L1:$L625,$C49,'Base DRE'!$K1:$K625,$H$2)} -> 0 | F49: {=_xlfn.SUMIFS('Base DRE'!$E1:$E625,'Base DRE'!$I1:$I625,F$7,'Base DRE'!$L1:$L625,$C49,'Base DRE'!$K1:$K625,$H$2)} -> 0 | H49: {=_xlfn.SUMIFS('Base DRE'!$E1:$E625,'Base DRE'!$I1:$I625,H$7,'Base DRE'!$L1:$L625,$C49,'Base DRE'!$K1:$K625,$H$2)} -> 0 | J49: {=_xlfn.SUMIFS('Base DRE'!$E1:$E625,'Base DRE'!$I1:$I625,J$7,'Base DRE'!$L1:$L625,$C49,'Base DRE'!$K1:$K625,$H$2)} -> 0 | L49: {=_xlfn.SUMIFS('Base DRE'!$E1:$E625,'Base DRE'!$I1:$I625,L$7,'Base DRE'!$L1:$L625,$C49,'Base DRE'!$K1:$K625,$H$2)} -> 0 | N49: {=_xlfn.SUMIFS('Base DRE'!$E1:$E625,'Base DRE'!$I1:$I625,N$7,'Base DRE'!$L1:$L625,$C49,'Base DRE'!$K1:$K625,$H$2)} -> 0 | P49: {=_xlfn.SUMIFS('Base DRE'!$E1:$E625,'Base DRE'!$I1:$I625,P$7,'Base DRE'!$L1:$L625,$C49,'Base DRE'!$K1:$K625,$H$2)} -> 0 | R49: {=_xlfn.SUMIFS('Base DRE'!$E1:$E625,'Base DRE'!$I1:$I625,R$7,'Base DRE'!$L1:$L625,$C49,'Base DRE'!$K1:$K625,$H$2)} -> 0 | T49: {=_xlfn.SUMIFS('Base DRE'!$E1:$E625,'Base DRE'!$I1:$I625,T$7,'Base DRE'!$L1:$L625,$C49,'Base DRE'!$K1:$K625,$H$2)} -> 0 | V49: {=_xlfn.SUMIFS('Base DRE'!$E1:$E625,'Base DRE'!$I1:$I625,V$7,'Base DRE'!$L1:$L625,$C49,'Base DRE'!$K1:$K625,$H$2)} -> 0 | X49: {=_xlfn.SUMIFS('Base DRE'!$E1:$E625,'Base DRE'!$I1:$I625,X$7,'Base DRE'!$L1:$L625,$C49,'Base DRE'!$K1:$K625,$H$2)} -> 0 | Z49: {=_xlfn.SUMIFS('Base DRE'!$E1:$E625,'Base DRE'!$I1:$I625,Z$7,'Base DRE'!$L1:$L625,$C49,'Base DRE'!$K1:$K625,$H$2)} -> 0
C50: Manutenção de Equipamentos | D50: {=_xlfn.SUMIFS('Base DRE'!$E1:$E625,'Base DRE'!$I1:$I625,D$7,'Base DRE'!$L1:$L625,$C50,'Base DRE'!$K1:$K625,$H$2)} -> 0 | F50: {=_xlfn.SUMIFS('Base DRE'!$E1:$E625,'Base DRE'!$I1:$I625,F$7,'Base DRE'!$L1:$L625,$C50,'Base DRE'!$K1:$K625,$H$2)} -> 0 | H50: {=_xlfn.SUMIFS('Base DRE'!$E1:$E625,'Base DRE'!$I1:$I625,H$7,'Base DRE'!$L1:$L625,$C50,'Base DRE'!$K1:$K625,$H$2)} -> 0 | J50: {=_xlfn.SUMIFS('Base DRE'!$E1:$E625,'Base DRE'!$I1:$I625,J$7,'Base DRE'!$L1:$L625,$C50,'Base DRE'!$K1:$K625,$H$2)} -> 0 | L50: {=_xlfn.SUMIFS('Base DRE'!$E1:$E625,'Base DRE'!$I1:$I625,L$7,'Base DRE'!$L1:$L625,$C50,'Base DRE'!$K1:$K625,$H$2)} -> 0 | N50: {=_xlfn.SUMIFS('Base DRE'!$E1:$E625,'Base DRE'!$I1:$I625,N$7,'Base DRE'!$L1:$L625,$C50,'Base DRE'!$K1:$K625,$H$2)} -> 0 | P50: {=_xlfn.SUMIFS('Base DRE'!$E1:$E625,'Base DRE'!$I1:$I625,P$7,'Base DRE'!$L1:$L625,$C50,'Base DRE'!$K1:$K625,$H$2)} -> 0 | R50: {=_xlfn.SUMIFS('Base DRE'!$E1:$E625,'Base DRE'!$I1:$I625,R$7,'Base DRE'!$L1:$L625,$C50,'Base DRE'!$K1:$K625,$H$2)} -> 0 | T50: {=_xlfn.SUMIFS('Base DRE'!$E1:$E625,'Base DRE'!$I1:$I625,T$7,'Base DRE'!$L1:$L625,$C50,'Base DRE'!$K1:$K625,$H$2)} -> 0 | V50: {=_xlfn.SUMIFS('Base DRE'!$E1:$E625,'Base DRE'!$I1:$I625,V$7,'Base DRE'!$L1:$L625,$C50,'Base DRE'!$K1:$K625,$H$2)} -> 0 | X50: {=_xlfn.SUMIFS('Base DRE'!$E1:$E625,'Base DRE'!$I1:$I625,X$7,'Base DRE'!$L1:$L625,$C50,'Base DRE'!$K1:$K625,$H$2)} -> 0 | Z50: {=_xlfn.SUMIFS('Base DRE'!$E1:$E625,'Base DRE'!$I1:$I625,Z$7,'Base DRE'!$L1:$L625,$C50,'Base DRE'!$K1:$K625,$H$2)} -> 0
B51: DESPESA
B52: 4.3 | C52: Custos Fixos - Despesa Com Sócios | D52: {=SUM(D53:D54)} -> 0 | E52: {=_xlfn.IFERROR(D52/D$8,"")} | F52: {=SUM(F53:F54)} -> 0 | G52: {=_xlfn.IFERROR(F52/F$8,"")} | H52: {=SUM(H53:H54)} -> 0 | I52: {=_xlfn.IFERROR(H52/H$8,"")} | J52: {=SUM(J53:J54)} -> 0 | K52: {=_xlfn.IFERROR(J52/J$8,"")} | L52: {=SUM(L53:L54)} -> 0 | M52: {=_xlfn.IFERROR(L52/L$8,"")} | N52: {=SUM(N53:N54)} -> 0 | O52: {=_xlfn.IFERROR(N52/N$8,"")} | P52: {=SUM(P53:P54)} -> 0 | Q52: {=_xlfn.IFERROR(P52/P$8,"")} | R52: {=SUM(R53:R54)} -> 0 | S52: {=_xlfn.IFERROR(R52/R$8,"")} | T52: {=SUM(T53:T54)} -> 0 | U52: {=_xlfn.IFERROR(T52/T$8,"")} | V52: {=SUM(V53:V54)} -> 0 | W52: {=_xlfn.IFERROR(V52/V$8,"")} | X52: {=SUM(X53:X54)} -> 0 | Y52: {=_xlfn.IFERROR(X52/X$8,"")} | Z52: {=SUM(Z53:Z54)} -> 0 | AA52: {=_xlfn.IFERROR(Z52/Z$8,"")}
B53: DESPESA | C53: Pró-Labore | D53: {=_xlfn.SUMIFS('Base DRE'!$E1:$E625,'Base DRE'!$I1:$I625,D$7,'Base DRE'!$L1:$L625,$C53,'Base DRE'!$K1:$K625,$H$2)} -> 0 | F53: {=_xlfn.SUMIFS('Base DRE'!$E1:$E625,'Base DRE'!$I1:$I625,F$7,'Base DRE'!$L1:$L625,$C53,'Base DRE'!$K1:$K625,$H$2)} -> 0 | H53: {=_xlfn.SUMIFS('Base DRE'!$E1:$E625,'Base DRE'!$I1:$I625,H$7,'Base DRE'!$L1:$L625,$C53,'Base DRE'!$K1:$K625,$H$2)} -> 0 | J53: {=_xlfn.SUMIFS('Base DRE'!$E1:$E625,'Base DRE'!$I1:$I625,J$7,'Base DRE'!$L1:$L625,$C53,'Base DRE'!$K1:$K625,$H$2)} -> 0 | L53: {=_xlfn.SUMIFS('Base DRE'!$E1:$E625,'Base DRE'!$I1:$I625,L$7,'Base DRE'!$L1:$L625,$C53,'Base DRE'!$K1:$K625,$H$2)} -> 0 | N53: {=_xlfn.SUMIFS('Base DRE'!$E1:$E625,'Base DRE'!$I1:$I625,N$7,'Base DRE'!$L1:$L625,$C53,'Base DRE'!$K1:$K625,$H$2)} -> 0 | P53: {=_xlfn.SUMIFS('Base DRE'!$E1:$E625,'Base DRE'!$I1:$I625,P$7,'Base DRE'!$L1:$L625,$C53,'Base DRE'!$K1:$K625,$H$2)} -> 0 | R53: {=_xlfn.SUMIFS('Base DRE'!$E1:$E625,'Base DRE'!$I1:$I625,R$7,'Base DRE'!$L1:$L625,$C53,'Base DRE'!$K1:$K625,$H$2)} -> 0 | T53: {=_xlfn.SUMIFS('Base DRE'!$E1:$E625,'Base DRE'!$I1:$I625,T$7,'Base DRE'!$L1:$L625,$C53,'Base DRE'!$K1:$K625,$H$2)} -> 0 | V53: {=_xlfn.SUMIFS('Base DRE'!$E1:$E625,'Base DRE'!$I1:$I625,V$7,'Base DRE'!$L1:$L625,$C53,'Base DRE'!$K1:$K625,$H$2)} -> 0 | X53: {=_xlfn.SUMIFS('Base DRE'!$E1:$E625,'Base DRE'!$I1:$I625,X$7,'Base DRE'!$L1:$L625,$C53,'Base DRE'!$K1:$K625,$H$2)} -> 0 | Z53: {=_xlfn.SUMIFS('Base DRE'!$E1:$E625,'Base DRE'!$I1:$I625,Z$7,'Base DRE'!$L1:$L625,$C53,'Base DRE'!$K1:$K625,$H$2)} -> 0
C56: ( = ) Lucro / Prejuízo Operacional | D56: {=D31+D33} -> 0 | E56: {=_xlfn.IFERROR(D56/D$8,"")} | F56: {=F31+F33} -> 0 | H56: {=H31+H33} -> 0 | J56: {=J31+J33} -> 0 | L56: {=L31+L33} -> 0 | N56: {=N31+N33} -> 0 | P56: {=P31+P33} -> 0 | R56: {=R31+R33} -> 0 | T56: {=T31+T33} -> 0 | V56: {=V31+V33} -> 0 | X56: {=X31+X33} -> 0 | Z56: {=Z31+Z33} -> 0
C58: EBITDA | D58: {=_xlfn.IFERROR(D56/D8,"")} | F58: {=_xlfn.IFERROR(F56/F8,"")} | H58: {=_xlfn.IFERROR(H56/H8,"")} | J58: {=_xlfn.IFERROR(J56/J8,"")} | L58: {=_xlfn.IFERROR(L56/L8,"")} | N58: {=_xlfn.IFERROR(N56/N8,"")} | P58: {=_xlfn.IFERROR(P56/P8,"")} | R58: {=_xlfn.IFERROR(R56/R8,"")} | T58: {=_xlfn.IFERROR(T56/T8,"")} | V58: {=_xlfn.IFERROR(V56/V8,"")} | X58: {=_xlfn.IFERROR(X56/X8,"")} | Z58: {=_xlfn.IFERROR(Z56/Z8,"")}
B60: 5. | C60: Receitas e Despesas Financeiras | D60: {=SUM(D61,D67)} -> 0 | F60: {=SUM(F61,F67)} -> 0 | H60: {=SUM(H61,H67)} -> 0 | J60: {=SUM(J61,J67)} -> 0 | L60: {=SUM(L61,L67)} -> 0 | N60: {=SUM(N61,N67)} -> 0 | P60: {=SUM(P61,P67)} -> 0 | R60: {=SUM(R61,R67)} -> 0 | T60: {=SUM(T61,T67)} -> 0 | V60: {=SUM(V61,V67)} -> 0 | X60: {=SUM(X61,X67)} -> 0 | Z60: {=SUM(Z61,Z67)} -> 0
B61: 5.1 | C61: Despesas Financeiras | D61: {=SUM(D62:D66)} -> 0 | F61: {=SUM(F62:F66)} -> 0 | H61: {=SUM(H62:H66)} -> 0 | J61: {=SUM(J62:J66)} -> 0 | L61: {=SUM(L62:L66)} -> 0 | N61: {=SUM(N62:N66)} -> 0 | P61: {=SUM(P62:P66)} -> 0 | R61: {=SUM(R62:R66)} -> 0 | T61: {=SUM(T62:T66)} -> 0 | V61: {=SUM(V62:V66)} -> 0 | X61: {=SUM(X62:X66)} -> 0 | Z61: {=SUM(Z62:Z66)} -> 0
B62: DESPESA | C62: Juros sobre Empréstimos | D62: {=_xlfn.SUMIFS('Base DRE'!$E1:$E625,'Base DRE'!$I1:$I625,D$7,'Base DRE'!$L1:$L625,$C62,'Base DRE'!$K1:$K625,$H$2)} -> 0 | F62: {=_xlfn.SUMIFS('Base DRE'!$E1:$E625,'Base DRE'!$I1:$I625,F$7,'Base DRE'!$L1:$L625,$C62,'Base DRE'!$K1:$K625,$H$2)} -> 0 | H62: {=_xlfn.SUMIFS('Base DRE'!$E1:$E625,'Base DRE'!$I1:$I625,H$7,'Base DRE'!$L1:$L625,$C62,'Base DRE'!$K1:$K625,$H$2)} -> 0 | J62: {=_xlfn.SUMIFS('Base DRE'!$E1:$E625,'Base DRE'!$I1:$I625,J$7,'Base DRE'!$L1:$L625,$C62,'Base DRE'!$K1:$K625,$H$2)} -> 0 | L62: {=_xlfn.SUMIFS('Base DRE'!$E1:$E625,'Base DRE'!$I1:$I625,L$7,'Base DRE'!$L1:$L625,$C62,'Base DRE'!$K1:$K625,$H$2)} -> 0 | N62: {=_xlfn.SUMIFS('Base DRE'!$E1:$E625,'Base DRE'!$I1:$I625,N$7,'Base DRE'!$L1:$L625,$C62,'Base DRE'!$K1:$K625,$H$2)} -> 0 | P62: {=_xlfn.SUMIFS('Base DRE'!$E1:$E625,'Base DRE'!$I1:$I625,P$7,'Base DRE'!$L1:$L625,$C62,'Base DRE'!$K1:$K625,$H$2)} -> 0 | R62: {=_xlfn.SUMIFS('Base DRE'!$E1:$E625,'Base DRE'!$I1:$I625,R$7,'Base DRE'!$L1:$L625,$C62,'Base DRE'!$K1:$K625,$H$2)} -> 0 | T62: {=_xlfn.SUMIFS('Base DRE'!$E1:$E625,'Base DRE'!$I1:$I625,T$7,'Base DRE'!$L1:$L625,$C62,'Base DRE'!$K1:$K625,$H$2)} -> 0 | V62: {=_xlfn.SUMIFS('Base DRE'!$E1:$E625,'Base DRE'!$I1:$I625,V$7,'Base DRE'!$L1:$L625,$C62,'Base DRE'!$K1:$K625,$H$2)} -> 0 | X62: {=_xlfn.SUMIFS('Base DRE'!$E1:$E625,'Base DRE'!$I1:$I625,X$7,'Base DRE'!$L1:$L625,$C62,'Base DRE'!$K1:$K625,$H$2)} -> 0 | Z62: {=_xlfn.SUMIFS('Base DRE'!$E1:$E625,'Base DRE'!$I1:$I625,Z$7,'Base DRE'!$L1:$L625,$C62,'Base DRE'!$K1:$K625,$H$2)} -> 0
C63: Tarifas Bancárias | D63: {=_xlfn.SUMIFS('Base DRE'!$E1:$E625,'Base DRE'!$I1:$I625,D$7,'Base DRE'!$L1:$L625,$C63,'Base DRE'!$K1:$K625,$H$2)} -> 0 | F63: {=_xlfn.SUMIFS('Base DRE'!$E1:$E625,'Base DRE'!$I1:$I625,F$7,'Base DRE'!$L1:$L625,$C63,'Base DRE'!$K1:$K625,$H$2)} -> 0 | H63: {=_xlfn.SUMIFS('Base DRE'!$E1:$E625,'Base DRE'!$I1:$I625,H$7,'Base DRE'!$L1:$L625,$C63,'Base DRE'!$K1:$K625,$H$2)} -> 0 | J63: {=_xlfn.SUMIFS('Base DRE'!$E1:$E625,'Base DRE'!$I1:$I625,J$7,'Base DRE'!$L1:$L625,$C63,'Base DRE'!$K1:$K625,$H$2)} -> 0 | L63: {=_xlfn.SUMIFS('Base DRE'!$E1:$E625,'Base DRE'!$I1:$I625,L$7,'Base DRE'!$L1:$L625,$C63,'Base DRE'!$K1:$K625,$H$2)} -> 0 | N63: {=_xlfn.SUMIFS('Base DRE'!$E1:$E625,'Base DRE'!$I1:$I625,N$7,'Base DRE'!$L1:$L625,$C63,'Base DRE'!$K1:$K625,$H$2)} -> 0 | P63: {=_xlfn.SUMIFS('Base DRE'!$E1:$E625,'Base DRE'!$I1:$I625,P$7,'Base DRE'!$L1:$L625,$C63,'Base DRE'!$K1:$K625,$H$2)} -> 0 | R63: {=_xlfn.SUMIFS('Base DRE'!$E1:$E625,'Base DRE'!$I1:$I625,R$7,'Base DRE'!$L1:$L625,$C63,'Base DRE'!$K1:$K625,$H$2)} -> 0 | T63: {=_xlfn.SUMIFS('Base DRE'!$E1:$E625,'Base DRE'!$I1:$I625,T$7,'Base DRE'!$L1:$L625,$C63,'Base DRE'!$K1:$K625,$H$2)} -> 0 | V63: {=_xlfn.SUMIFS('Base DRE'!$E1:$E625,'Base DRE'!$I1:$I625,V$7,'Base DRE'!$L1:$L625,$C63,'Base DRE'!$K1:$K625,$H$2)} -> 0 | X63: {=_xlfn.SUMIFS('Base DRE'!$E1:$E625,'Base DRE'!$I1:$I625,X$7,'Base DRE'!$L1:$L625,$C63,'Base DRE'!$K1:$K625,$H$2)} -> 0 | Z63: {=_xlfn.SUMIFS('Base DRE'!$E1:$E625,'Base DRE'!$I1:$I625,Z$7,'Base DRE'!$L1:$L625,$C63,'Base DRE'!$K1:$K625,$H$2)} -> 0
C64: Multas e Encargos | D64: {=_xlfn.SUMIFS('Base DRE'!$E1:$E625,'Base DRE'!$I1:$I625,D$7,'Base DRE'!$L1:$L625,$C64,'Base DRE'!$K1:$K625,$H$2)} -> 0 | F64: {=_xlfn.SUMIFS('Base DRE'!$E1:$E625,'Base DRE'!$I1:$I625,F$7,'Base DRE'!$L1:$L625,$C64,'Base DRE'!$K1:$K625,$H$2)} -> 0 | H64: {=_xlfn.SUMIFS('Base DRE'!$E1:$E625,'Base DRE'!$I1:$I625,H$7,'Base DRE'!$L1:$L625,$C64,'Base DRE'!$K1:$K625,$H$2)} -> 0 | J64: {=_xlfn.SUMIFS('Base DRE'!$E1:$E625,'Base DRE'!$I1:$I625,J$7,'Base DRE'!$L1:$L625,$C64,'Base DRE'!$K1:$K625,$H$2)} -> 0 | L64: {=_xlfn.SUMIFS('Base DRE'!$E1:$E625,'Base DRE'!$I1:$I625,L$7,'Base DRE'!$L1:$L625,$C64,'Base DRE'!$K1:$K625,$H$2)} -> 0 | N64: {=_xlfn.SUMIFS('Base DRE'!$E1:$E625,'Base DRE'!$I1:$I625,N$7,'Base DRE'!$L1:$L625,$C64,'Base DRE'!$K1:$K625,$H$2)} -> 0 | P64: {=_xlfn.SUMIFS('Base DRE'!$E1:$E625,'Base DRE'!$I1:$I625,P$7,'Base DRE'!$L1:$L625,$C64,'Base DRE'!$K1:$K625,$H$2)} -> 0 | R64: {=_xlfn.SUMIFS('Base DRE'!$E1:$E625,'Base DRE'!$I1:$I625,R$7,'Base DRE'!$L1:$L625,$C64,'Base DRE'!$K1:$K625,$H$2)} -> 0 | T64: {=_xlfn.SUMIFS('Base DRE'!$E1:$E625,'Base DRE'!$I1:$I625,T$7,'Base DRE'!$L1:$L625,$C64,'Base DRE'!$K1:$K625,$H$2)} -> 0 | V64: {=_xlfn.SUMIFS('Base DRE'!$E1:$E625,'Base DRE'!$I1:$I625,V$7,'Base DRE'!$L1:$L625,$C64,'Base DRE'!$K1:$K625,$H$2)} -> 0 | X64: {=_xlfn.SUMIFS('Base DRE'!$E1:$E625,'Base DRE'!$I1:$I625,X$7,'Base DRE'!$L1:$L625,$C64,'Base DRE'!$K1:$K625,$H$2)} -> 0 | Z64: {=_xlfn.SUMIFS('Base DRE'!$E1:$E625,'Base DRE'!$I1:$I625,Z$7,'Base DRE'!$L1:$L625,$C64,'Base DRE'!$K1:$K625,$H$2)} -> 0
C65: Descontos Concedidos | D65: {=_xlfn.SUMIFS('Base DRE'!$E1:$E625,'Base DRE'!$I1:$I625,D$7,'Base DRE'!$L1:$L625,$C65,'Base DRE'!$K1:$K625,$H$2)} -> 0 | F65: {=_xlfn.SUMIFS('Base DRE'!$E1:$E625,'Base DRE'!$I1:$I625,F$7,'Base DRE'!$L1:$L625,$C65,'Base DRE'!$K1:$K625,$H$2)} -> 0 | H65: {=_xlfn.SUMIFS('Base DRE'!$E1:$E625,'Base DRE'!$I1:$I625,H$7,'Base DRE'!$L1:$L625,$C65,'Base DRE'!$K1:$K625,$H$2)} -> 0 | J65: {=_xlfn.SUMIFS('Base DRE'!$E1:$E625,'Base DRE'!$I1:$I625,J$7,'Base DRE'!$L1:$L625,$C65,'Base DRE'!$K1:$K625,$H$2)} -> 0 | L65: {=_xlfn.SUMIFS('Base DRE'!$E1:$E625,'Base DRE'!$I1:$I625,L$7,'Base DRE'!$L1:$L625,$C65,'Base DRE'!$K1:$K625,$H$2)} -> 0 | N65: {=_xlfn.SUMIFS('Base DRE'!$E1:$E625,'Base DRE'!$I1:$I625,N$7,'Base DRE'!$L1:$L625,$C65,'Base DRE'!$K1:$K625,$H$2)} -> 0 | P65: {=_xlfn.SUMIFS('Base DRE'!$E1:$E625,'Base DRE'!$I1:$I625,P$7,'Base DRE'!$L1:$L625,$C65,'Base DRE'!$K1:$K625,$H$2)} -> 0 | R65: {=_xlfn.SUMIFS('Base DRE'!$E1:$E625,'Base DRE'!$I1:$I625,R$7,'Base DRE'!$L1:$L625,$C65,'Base DRE'!$K1:$K625,$H$2)} -> 0 | T65: {=_xlfn.SUMIFS('Base DRE'!$E1:$E625,'Base DRE'!$I1:$I625,T$7,'Base DRE'!$L1:$L625,$C65,'Base DRE'!$K1:$K625,$H$2)} -> 0 | V65: {=_xlfn.SUMIFS('Base DRE'!$E1:$E625,'Base DRE'!$I1:$I625,V$7,'Base DRE'!$L1:$L625,$C65,'Base DRE'!$K1:$K625,$H$2)} -> 0 | X65: {=_xlfn.SUMIFS('Base DRE'!$E1:$E625,'Base DRE'!$I1:$I625,X$7,'Base DRE'!$L1:$L625,$C65,'Base DRE'!$K1:$K625,$H$2)} -> 0 | Z65: {=_xlfn.SUMIFS('Base DRE'!$E1:$E625,'Base DRE'!$I1:$I625,Z$7,'Base DRE'!$L1:$L625,$C65,'Base DRE'!$K1:$K625,$H$2)} -> 0
B66: DESPESA
B67: 5.2 | C67: Receitas Financeiras | D67: {=SUM(D68:D70)} -> 0 | F67: {=SUM(F68:F70)} -> 0 | H67: {=SUM(H68:H70)} -> 0 | J67: {=SUM(J68:J70)} -> 0 | L67: {=SUM(L68:L70)} -> 0 | N67: {=SUM(N68:N70)} -> 0 | P67: {=SUM(P68:P70)} -> 0 | R67: {=SUM(R68:R70)} -> 0 | T67: {=SUM(T68:T70)} -> 0 | V67: {=SUM(V68:V70)} -> 0 | X67: {=SUM(X68:X70)} -> 0 | Z67: {=SUM(Z68:Z70)} -> 0
C68: Receita Financeira | D68: {=_xlfn.SUMIFS('Base DRE'!$E1:$E625,'Base DRE'!$I1:$I625,D$7,'Base DRE'!$L1:$L625,$C68,'Base DRE'!$K1:$K625,$H$2)} -> 0 | F68: {=_xlfn.SUMIFS('Base DRE'!$E1:$E625,'Base DRE'!$I1:$I625,F$7,'Base DRE'!$L1:$L625,$C68,'Base DRE'!$K1:$K625,$H$2)} -> 0 | H68: {=_xlfn.SUMIFS('Base DRE'!$E1:$E625,'Base DRE'!$I1:$I625,H$7,'Base DRE'!$L1:$L625,$C68,'Base DRE'!$K1:$K625,$H$2)} -> 0 | J68: {=_xlfn.SUMIFS('Base DRE'!$E1:$E625,'Base DRE'!$I1:$I625,J$7,'Base DRE'!$L1:$L625,$C68,'Base DRE'!$K1:$K625,$H$2)} -> 0 | L68: {=_xlfn.SUMIFS('Base DRE'!$E1:$E625,'Base DRE'!$I1:$I625,L$7,'Base DRE'!$L1:$L625,$C68,'Base DRE'!$K1:$K625,$H$2)} -> 0 | N68: {=_xlfn.SUMIFS('Base DRE'!$E1:$E625,'Base DRE'!$I1:$I625,N$7,'Base DRE'!$L1:$L625,$C68,'Base DRE'!$K1:$K625,$H$2)} -> 0 | P68: {=_xlfn.SUMIFS('Base DRE'!$E1:$E625,'Base DRE'!$I1:$I625,P$7,'Base DRE'!$L1:$L625,$C68,'Base DRE'!$K1:$K625,$H$2)} -> 0 | R68: {=_xlfn.SUMIFS('Base DRE'!$E1:$E625,'Base DRE'!$I1:$I625,R$7,'Base DRE'!$L1:$L625,$C68,'Base DRE'!$K1:$K625,$H$2)} -> 0 | T68: {=_xlfn.SUMIFS('Base DRE'!$E1:$E625,'Base DRE'!$I1:$I625,T$7,'Base DRE'!$L1:$L625,$C68,'Base DRE'!$K1:$K625,$H$2)} -> 0 | V68: {=_xlfn.SUMIFS('Base DRE'!$E1:$E625,'Base DRE'!$I1:$I625,V$7,'Base DRE'!$L1:$L625,$C68,'Base DRE'!$K1:$K625,$H$2)} -> 0 | X68: {=_xlfn.SUMIFS('Base DRE'!$E1:$E625,'Base DRE'!$I1:$I625,X$7,'Base DRE'!$L1:$L625,$C68,'Base DRE'!$K1:$K625,$H$2)} -> 0 | Z68: {=_xlfn.SUMIFS('Base DRE'!$E1:$E625,'Base DRE'!$I1:$I625,Z$7,'Base DRE'!$L1:$L625,$C68,'Base DRE'!$K1:$K625,$H$2)} -> 0
B70: DESPESA
B71: 6. | C71: Outras Receitas e Despesas Não Operacionais | D71: {=SUM(D72,D76)} -> 0 | F71: {=SUM(F72,F76)} -> 0 | H71: {=SUM(H72,H76)} -> 0 | J71: {=SUM(J72,J76)} -> 0 | L71: {=SUM(L72,L76)} -> 0 | N71: {=SUM(N72,N76)} -> 0 | P71: {=SUM(P72,P76)} -> 0 | R71: {=SUM(R72,R76)} -> 0 | T71: {=SUM(T72,T76)} -> 0 | V71: {=SUM(V72,V76)} -> 0 | X71: {=SUM(X72,X76)} -> 0 | Z71: {=SUM(Z72,Z76)} -> 0
B72: 6.1 | C72: Receitas não operacionais | D72: {=SUM(D73:D75)} -> 0 | F72: {=SUM(F73:F75)} -> 0 | H72: {=SUM(H73:H75)} -> 0 | J72: {=SUM(J73:J75)} -> 0 | L72: {=SUM(L73:L75)} -> 0 | N72: {=SUM(N73:N75)} -> 0 | P72: {=SUM(P73:P75)} -> 0 | R72: {=SUM(R73:R75)} -> 0 | T72: {=SUM(T73:T75)} -> 0 | V72: {=SUM(V73:V75)} -> 0 | X72: {=SUM(X73:X75)} -> 0 | Z72: {=SUM(Z73:Z75)} -> 0
B73: RECEITA | C73: Outras Receitas Operacionais | D73: {=_xlfn.SUMIFS('Base DRE'!$E1:$E625,'Base DRE'!$I1:$I625,D$7,'Base DRE'!$L1:$L625,$C73,'Base DRE'!$K1:$K625,$H$2)} -> 0 | F73: {=_xlfn.SUMIFS('Base DRE'!$E1:$E625,'Base DRE'!$I1:$I625,F$7,'Base DRE'!$L1:$L625,$C73,'Base DRE'!$K1:$K625,$H$2)} -> 0 | H73: {=_xlfn.SUMIFS('Base DRE'!$E1:$E625,'Base DRE'!$I1:$I625,H$7,'Base DRE'!$L1:$L625,$C73,'Base DRE'!$K1:$K625,$H$2)} -> 0 | J73: {=_xlfn.SUMIFS('Base DRE'!$E1:$E625,'Base DRE'!$I1:$I625,J$7,'Base DRE'!$L1:$L625,$C73,'Base DRE'!$K1:$K625,$H$2)} -> 0 | L73: {=_xlfn.SUMIFS('Base DRE'!$E1:$E625,'Base DRE'!$I1:$I625,L$7,'Base DRE'!$L1:$L625,$C73,'Base DRE'!$K1:$K625,$H$2)} -> 0 | N73: {=_xlfn.SUMIFS('Base DRE'!$E1:$E625,'Base DRE'!$I1:$I625,N$7,'Base DRE'!$L1:$L625,$C73,'Base DRE'!$K1:$K625,$H$2)} -> 0 | P73: {=_xlfn.SUMIFS('Base DRE'!$E1:$E625,'Base DRE'!$I1:$I625,P$7,'Base DRE'!$L1:$L625,$C73,'Base DRE'!$K1:$K625,$H$2)} -> 0 | R73: {=_xlfn.SUMIFS('Base DRE'!$E1:$E625,'Base DRE'!$I1:$I625,R$7,'Base DRE'!$L1:$L625,$C73,'Base DRE'!$K1:$K625,$H$2)} -> 0 | T73: {=_xlfn.SUMIFS('Base DRE'!$E1:$E625,'Base DRE'!$I1:$I625,T$7,'Base DRE'!$L1:$L625,$C73,'Base DRE'!$K1:$K625,$H$2)} -> 0 | V73: {=_xlfn.SUMIFS('Base DRE'!$E1:$E625,'Base DRE'!$I1:$I625,V$7,'Base DRE'!$L1:$L625,$C73,'Base DRE'!$K1:$K625,$H$2)} -> 0 | X73: {=_xlfn.SUMIFS('Base DRE'!$E1:$E625,'Base DRE'!$I1:$I625,X$7,'Base DRE'!$L1:$L625,$C73,'Base DRE'!$K1:$K625,$H$2)} -> 0 | Z73: {=_xlfn.SUMIFS('Base DRE'!$E1:$E625,'Base DRE'!$I1:$I625,Z$7,'Base DRE'!$L1:$L625,$C73,'Base DRE'!$K1:$K625,$H$2)} -> 0
B76: 6.2 | C76: Despesas não operacionais | D76: {=SUM(D77:D77)} -> 0 | F76: {=SUM(F77:F77)} -> 0 | H76: {=SUM(H77:H77)} -> 0 | J76: {=SUM(J77:J77)} -> 0 | L76: {=SUM(L77:L77)} -> 0 | N76: {=SUM(N77:N77)} -> 0 | P76: {=SUM(P77:P77)} -> 0 | R76: {=SUM(R77:R77)} -> 0 | T76: {=SUM(T77:T77)} -> 0 | V76: {=SUM(V77:V77)} -> 0 | X76: {=SUM(X77:X77)} -> 0 | Z76: {=SUM(Z77:Z77)} -> 0
B77: RECEITA
C78: Lucro / Prejuízo Líquido | D78: {=D60+D56+D71} -> 0 | F78: {=F60+F56+F71} -> 0 | H78: {=H60+H56+H71} -> 0 | J78: {=J60+J56+J71} -> 0 | L78: {=L60+L56+L71} -> 0 | N78: {=N60+N56+N71} -> 0 | P78: {=P60+P56+P71} -> 0 | R78: {=R60+R56+R71} -> 0 | T78: {=T60+T56+T71} -> 0 | V78: {=V60+V56+V71} -> 0 | X78: {=X60+X56+X71} -> 0 | Z78: {=Z60+Z56+Z71} -> 0
B80: 7. | C80: Despesas e Receitas com Investimentos e Empréstimos | D80: {=SUM(D81,D88,D85)} -> 0 | F80: {=SUM(F81,F88,F85)} -> 0 | H80: {=SUM(H81,H88,H85)} -> 0 | J80: {=SUM(J81,J88,J85)} -> 0 | L80: {=SUM(L81,L88,L85)} -> 0 | N80: {=SUM(N81,N88,N85)} -> 0 | P80: {=SUM(P81,P88,P85)} -> 0 | R80: {=SUM(R81,R88,R85)} -> 0 | T80: {=SUM(T81,T88,T85)} -> 0 | V80: {=SUM(V81,V88,V85)} -> 0 | X80: {=SUM(X81,X88,X85)} -> 0 | Z80: {=SUM(Z81,Z88,Z85)} -> 0
B81: 7.1 | C81: Investimentos | D81: {=SUM(D82:D84)} -> 0 | F81: {=SUM(F82:F84)} -> 0 | H81: {=SUM(H82:H84)} -> 0 | J81: {=SUM(J82:J84)} -> 0 | L81: {=SUM(L82:L84)} -> 0 | N81: {=SUM(N82:N84)} -> 0 | P81: {=SUM(P82:P84)} -> 0 | R81: {=SUM(R82:R84)} -> 0 | T81: {=SUM(T82:T84)} -> 0 | V81: {=SUM(V82:V84)} -> 0 | X81: {=SUM(X82:X84)} -> 0 | Z81: {=SUM(Z82:Z84)} -> 0
B82: DESPESA | C82: Investimentos | D82: {=_xlfn.SUMIFS('Base DRE'!$E1:$E625,'Base DRE'!$I1:$I625,D$7,'Base DRE'!$L1:$L625,$C82,'Base DRE'!$K1:$K625,$H$2)} -> 0 | F82: {=_xlfn.SUMIFS('Base DRE'!$E1:$E625,'Base DRE'!$I1:$I625,F$7,'Base DRE'!$L1:$L625,$C82,'Base DRE'!$K1:$K625,$H$2)} -> 0 | H82: {=_xlfn.SUMIFS('Base DRE'!$E1:$E625,'Base DRE'!$I1:$I625,H$7,'Base DRE'!$L1:$L625,$C82,'Base DRE'!$K1:$K625,$H$2)} -> 0 | J82: {=_xlfn.SUMIFS('Base DRE'!$E1:$E625,'Base DRE'!$I1:$I625,J$7,'Base DRE'!$L1:$L625,$C82,'Base DRE'!$K1:$K625,$H$2)} -> 0 | L82: {=_xlfn.SUMIFS('Base DRE'!$E1:$E625,'Base DRE'!$I1:$I625,L$7,'Base DRE'!$L1:$L625,$C82,'Base DRE'!$K1:$K625,$H$2)} -> 0 | N82: {=_xlfn.SUMIFS('Base DRE'!$E1:$E625,'Base DRE'!$I1:$I625,N$7,'Base DRE'!$L1:$L625,$C82,'Base DRE'!$K1:$K625,$H$2)} -> 0 | P82: {=_xlfn.SUMIFS('Base DRE'!$E1:$E625,'Base DRE'!$I1:$I625,P$7,'Base DRE'!$L1:$L625,$C82,'Base DRE'!$K1:$K625,$H$2)} -> 0 | R82: {=_xlfn.SUMIFS('Base DRE'!$E1:$E625,'Base DRE'!$I1:$I625,R$7,'Base DRE'!$L1:$L625,$C82,'Base DRE'!$K1:$K625,$H$2)} -> 0 | T82: {=_xlfn.SUMIFS('Base DRE'!$E1:$E625,'Base DRE'!$I1:$I625,T$7,'Base DRE'!$L1:$L625,$C82,'Base DRE'!$K1:$K625,$H$2)} -> 0 | V82: {=_xlfn.SUMIFS('Base DRE'!$E1:$E625,'Base DRE'!$I1:$I625,V$7,'Base DRE'!$L1:$L625,$C82,'Base DRE'!$K1:$K625,$H$2)} -> 0 | X82: {=_xlfn.SUMIFS('Base DRE'!$E1:$E625,'Base DRE'!$I1:$I625,X$7,'Base DRE'!$L1:$L625,$C82,'Base DRE'!$K1:$K625,$H$2)} -> 0 | Z82: {=_xlfn.SUMIFS('Base DRE'!$E1:$E625,'Base DRE'!$I1:$I625,Z$7,'Base DRE'!$L1:$L625,$C82,'Base DRE'!$K1:$K625,$H$2)} -> 0
B83: DESPESA
B84: DESPESA
B85: 7.2 | C85: Pagamentos de Fornecedor Atrasado | D85: {=SUM(D86:D87)} -> 0 | F85: {=SUM(F86:F87)} -> 0 | H85: {=SUM(H86:H87)} -> 0 | J85: {=SUM(J86:J87)} -> 0 | L85: {=SUM(L86:L87)} -> 0 | N85: {=SUM(N86:N87)} -> 0 | P85: {=SUM(P86:P87)} -> 0 | R85: {=SUM(R86:R87)} -> 0 | T85: {=SUM(T86:T87)} -> 0 | V85: {=SUM(V86:V87)} -> 0 | X85: {=SUM(X86:X87)} -> 0 | Z85: {=SUM(Z86:Z87)} -> 0
B86: DESPESA | D86: {=_xlfn.SUMIFS('Base DRE'!$E1:$E625,'Base DRE'!$I1:$I625,D$7,'Base DRE'!$L1:$L625,$C86,'Base DRE'!$K1:$K625,$H$2)} -> 0 | F86: {=_xlfn.SUMIFS('Base DRE'!$E1:$E625,'Base DRE'!$I1:$I625,F$7,'Base DRE'!$L1:$L625,$C86,'Base DRE'!$K1:$K625,$H$2)} -> 0 | H86: {=_xlfn.SUMIFS('Base DRE'!$E1:$E625,'Base DRE'!$I1:$I625,H$7,'Base DRE'!$L1:$L625,$C86,'Base DRE'!$K1:$K625,$H$2)} -> 0 | J86: {=_xlfn.SUMIFS('Base DRE'!$E1:$E625,'Base DRE'!$I1:$I625,J$7,'Base DRE'!$L1:$L625,$C86,'Base DRE'!$K1:$K625,$H$2)} -> 0 | L86: {=_xlfn.SUMIFS('Base DRE'!$E1:$E625,'Base DRE'!$I1:$I625,L$7,'Base DRE'!$L1:$L625,$C86,'Base DRE'!$K1:$K625,$H$2)} -> 0 | N86: {=_xlfn.SUMIFS('Base DRE'!$E1:$E625,'Base DRE'!$I1:$I625,N$7,'Base DRE'!$L1:$L625,$C86,'Base DRE'!$K1:$K625,$H$2)} -> 0 | P86: {=_xlfn.SUMIFS('Base DRE'!$E1:$E625,'Base DRE'!$I1:$I625,P$7,'Base DRE'!$L1:$L625,$C86,'Base DRE'!$K1:$K625,$H$2)} -> 0 | R86: {=_xlfn.SUMIFS('Base DRE'!$E1:$E625,'Base DRE'!$I1:$I625,R$7,'Base DRE'!$L1:$L625,$C86,'Base DRE'!$K1:$K625,$H$2)} -> 0 | T86: {=_xlfn.SUMIFS('Base DRE'!$E1:$E625,'Base DRE'!$I1:$I625,T$7,'Base DRE'!$L1:$L625,$C86,'Base DRE'!$K1:$K625,$H$2)} -> 0 | V86: {=_xlfn.SUMIFS('Base DRE'!$E1:$E625,'Base DRE'!$I1:$I625,V$7,'Base DRE'!$L1:$L625,$C86,'Base DRE'!$K1:$K625,$H$2)} -> 0 | X86: {=_xlfn.SUMIFS('Base DRE'!$E1:$E625,'Base DRE'!$I1:$I625,X$7,'Base DRE'!$L1:$L625,$C86,'Base DRE'!$K1:$K625,$H$2)} -> 0 | Z86: {=_xlfn.SUMIFS('Base DRE'!$E1:$E625,'Base DRE'!$I1:$I625,Z$7,'Base DRE'!$L1:$L625,$C86,'Base DRE'!$K1:$K625,$H$2)} -> 0
B88: 7.3 | C88: Empréstimos e Dívidas | D88: {=SUM(D89:D90)} -> 0 | F88: {=SUM(F89:F90)} -> 0 | H88: {=SUM(H89:H90)} -> 0 | J88: {=SUM(J89:J90)} -> 0 | L88: {=SUM(L89:L90)} -> 0 | N88: {=SUM(N89:N90)} -> 0 | P88: {=SUM(P89:P90)} -> 0 | R88: {=SUM(R89:R90)} -> 0 | T88: {=SUM(T89:T90)} -> 0 | V88: {=SUM(V89:V90)} -> 0 | X88: {=SUM(X89:X90)} -> 0 | Z88: {=SUM(Z89:Z90)} -> 0
B89: DESPESA | C89: Empréstimos e Financiamentos | D89: {=_xlfn.SUMIFS('Base DRE'!$E1:$E625,'Base DRE'!$I1:$I625,D$7,'Base DRE'!$L1:$L625,$C89,'Base DRE'!$K1:$K625,$H$2)} -> 0 | F89: {=_xlfn.SUMIFS('Base DRE'!$E1:$E625,'Base DRE'!$I1:$I625,F$7,'Base DRE'!$L1:$L625,$C89,'Base DRE'!$K1:$K625,$H$2)} -> 0 | H89: {=_xlfn.SUMIFS('Base DRE'!$E1:$E625,'Base DRE'!$I1:$I625,H$7,'Base DRE'!$L1:$L625,$C89,'Base DRE'!$K1:$K625,$H$2)} -> 0 | J89: {=_xlfn.SUMIFS('Base DRE'!$E1:$E625,'Base DRE'!$I1:$I625,J$7,'Base DRE'!$L1:$L625,$C89,'Base DRE'!$K1:$K625,$H$2)} -> 0 | L89: {=_xlfn.SUMIFS('Base DRE'!$E1:$E625,'Base DRE'!$I1:$I625,L$7,'Base DRE'!$L1:$L625,$C89,'Base DRE'!$K1:$K625,$H$2)} -> 0 | N89: {=_xlfn.SUMIFS('Base DRE'!$E1:$E625,'Base DRE'!$I1:$I625,N$7,'Base DRE'!$L1:$L625,$C89,'Base DRE'!$K1:$K625,$H$2)} -> 0 | P89: {=_xlfn.SUMIFS('Base DRE'!$E1:$E625,'Base DRE'!$I1:$I625,P$7,'Base DRE'!$L1:$L625,$C89,'Base DRE'!$K1:$K625,$H$2)} -> 0 | R89: {=_xlfn.SUMIFS('Base DRE'!$E1:$E625,'Base DRE'!$I1:$I625,R$7,'Base DRE'!$L1:$L625,$C89,'Base DRE'!$K1:$K625,$H$2)} -> 0 | T89: {=_xlfn.SUMIFS('Base DRE'!$E1:$E625,'Base DRE'!$I1:$I625,T$7,'Base DRE'!$L1:$L625,$C89,'Base DRE'!$K1:$K625,$H$2)} -> 0 | V89: {=_xlfn.SUMIFS('Base DRE'!$E1:$E625,'Base DRE'!$I1:$I625,V$7,'Base DRE'!$L1:$L625,$C89,'Base DRE'!$K1:$K625,$H$2)} -> 0 | X89: {=_xlfn.SUMIFS('Base DRE'!$E1:$E625,'Base DRE'!$I1:$I625,X$7,'Base DRE'!$L1:$L625,$C89,'Base DRE'!$K1:$K625,$H$2)} -> 0 | Z89: {=_xlfn.SUMIFS('Base DRE'!$E1:$E625,'Base DRE'!$I1:$I625,Z$7,'Base DRE'!$L1:$L625,$C89,'Base DRE'!$K1:$K625,$H$2)} -> 0
B90: RECEITA
B92: 8. | C92: Despesas a Identificar | D92: {=SUM(D93:D95)} -> 0 | F92: {=SUM(F93:F95)} -> 0 | H92: {=SUM(H93:H95)} -> 0 | J92: {=SUM(J93:J95)} -> 0 | L92: {=SUM(L93:L95)} -> 0 | N92: {=SUM(N93:N95)} -> 0 | P92: {=SUM(P93:P95)} -> 0 | R92: {=SUM(R93:R95)} -> 0 | T92: {=SUM(T93:T95)} -> 0 | V92: {=SUM(V93:V95)} -> 0 | X92: {=SUM(X93:X95)} -> 0 | Z92: {=SUM(Z93:Z95)} -> 0
B93: DESPESA | C93: Distribuição de Lucros | D93: {=_xlfn.SUMIFS('Base DRE'!$E1:$E625,'Base DRE'!$I1:$I625,D$7,'Base DRE'!$L1:$L625,$C93,'Base DRE'!$K1:$K625,$H$2)} -> 0 | F93: {=_xlfn.SUMIFS('Base DRE'!$E1:$E625,'Base DRE'!$I1:$I625,F$7,'Base DRE'!$L1:$L625,$C93,'Base DRE'!$K1:$K625,$H$2)} -> 0 | H93: {=_xlfn.SUMIFS('Base DRE'!$E1:$E625,'Base DRE'!$I1:$I625,H$7,'Base DRE'!$L1:$L625,$C93,'Base DRE'!$K1:$K625,$H$2)} -> 0 | J93: {=_xlfn.SUMIFS('Base DRE'!$E1:$E625,'Base DRE'!$I1:$I625,J$7,'Base DRE'!$L1:$L625,$C93,'Base DRE'!$K1:$K625,$H$2)} -> 0 | L93: {=_xlfn.SUMIFS('Base DRE'!$E1:$E625,'Base DRE'!$I1:$I625,L$7,'Base DRE'!$L1:$L625,$C93,'Base DRE'!$K1:$K625,$H$2)} -> 0 | N93: {=_xlfn.SUMIFS('Base DRE'!$E1:$E625,'Base DRE'!$I1:$I625,N$7,'Base DRE'!$L1:$L625,$C93,'Base DRE'!$K1:$K625,$H$2)} -> 0 | P93: {=_xlfn.SUMIFS('Base DRE'!$E1:$E625,'Base DRE'!$I1:$I625,P$7,'Base DRE'!$L1:$L625,$C93,'Base DRE'!$K1:$K625,$H$2)} -> 0 | R93: {=_xlfn.SUMIFS('Base DRE'!$E1:$E625,'Base DRE'!$I1:$I625,R$7,'Base DRE'!$L1:$L625,$C93,'Base DRE'!$K1:$K625,$H$2)} -> 0 | T93: {=_xlfn.SUMIFS('Base DRE'!$E1:$E625,'Base DRE'!$I1:$I625,T$7,'Base DRE'!$L1:$L625,$C93,'Base DRE'!$K1:$K625,$H$2)} -> 0 | V93: {=_xlfn.SUMIFS('Base DRE'!$E1:$E625,'Base DRE'!$I1:$I625,V$7,'Base DRE'!$L1:$L625,$C93,'Base DRE'!$K1:$K625,$H$2)} -> 0 | X93: {=_xlfn.SUMIFS('Base DRE'!$E1:$E625,'Base DRE'!$I1:$I625,X$7,'Base DRE'!$L1:$L625,$C93,'Base DRE'!$K1:$K625,$H$2)} -> 0 | Z93: {=_xlfn.SUMIFS('Base DRE'!$E1:$E625,'Base DRE'!$I1:$I625,Z$7,'Base DRE'!$L1:$L625,$C93,'Base DRE'!$K1:$K625,$H$2)} -> 0
B94: DESPESA | C94: Lançamentos a Identificar | D94: {=_xlfn.SUMIFS('Base DRE'!$E1:$E625,'Base DRE'!$I1:$I625,D$7,'Base DRE'!$L1:$L625,$C94,'Base DRE'!$K1:$K625,$H$2)} -> 0 | F94: {=_xlfn.SUMIFS('Base DRE'!$E1:$E625,'Base DRE'!$I1:$I625,F$7,'Base DRE'!$L1:$L625,$C94,'Base DRE'!$K1:$K625,$H$2)} -> 0 | H94: {=_xlfn.SUMIFS('Base DRE'!$E1:$E625,'Base DRE'!$I1:$I625,H$7,'Base DRE'!$L1:$L625,$C94,'Base DRE'!$K1:$K625,$H$2)} -> 0 | J94: {=_xlfn.SUMIFS('Base DRE'!$E1:$E625,'Base DRE'!$I1:$I625,J$7,'Base DRE'!$L1:$L625,$C94,'Base DRE'!$K1:$K625,$H$2)} -> 0 | L94: {=_xlfn.SUMIFS('Base DRE'!$E1:$E625,'Base DRE'!$I1:$I625,L$7,'Base DRE'!$L1:$L625,$C94,'Base DRE'!$K1:$K625,$H$2)} -> 0 | N94: {=_xlfn.SUMIFS('Base DRE'!$E1:$E625,'Base DRE'!$I1:$I625,N$7,'Base DRE'!$L1:$L625,$C94,'Base DRE'!$K1:$K625,$H$2)} -> 0 | P94: {=_xlfn.SUMIFS('Base DRE'!$E1:$E625,'Base DRE'!$I1:$I625,P$7,'Base DRE'!$L1:$L625,$C94,'Base DRE'!$K1:$K625,$H$2)} -> 0 | R94: {=_xlfn.SUMIFS('Base DRE'!$E1:$E625,'Base DRE'!$I1:$I625,R$7,'Base DRE'!$L1:$L625,$C94,'Base DRE'!$K1:$K625,$H$2)} -> 0 | T94: {=_xlfn.SUMIFS('Base DRE'!$E1:$E625,'Base DRE'!$I1:$I625,T$7,'Base DRE'!$L1:$L625,$C94,'Base DRE'!$K1:$K625,$H$2)} -> 0 | V94: {=_xlfn.SUMIFS('Base DRE'!$E1:$E625,'Base DRE'!$I1:$I625,V$7,'Base DRE'!$L1:$L625,$C94,'Base DRE'!$K1:$K625,$H$2)} -> 0 | X94: {=_xlfn.SUMIFS('Base DRE'!$E1:$E625,'Base DRE'!$I1:$I625,X$7,'Base DRE'!$L1:$L625,$C94,'Base DRE'!$K1:$K625,$H$2)} -> 0 | Z94: {=_xlfn.SUMIFS('Base DRE'!$E1:$E625,'Base DRE'!$I1:$I625,Z$7,'Base DRE'!$L1:$L625,$C94,'Base DRE'!$K1:$K625,$H$2)} -> 0
B95: DESPESA
C97: Lucro / Prejuízo Final | D97: {=D78+D80+D92} -> 0 | F97: {=F78+F80+F92} -> 0 | H97: {=H78+H80+H92} -> 0 | J97: {=J78+J80+J92} -> 0 | L97: {=L78+L80+L92} -> 0 | N97: {=N78+N80+N92} -> 0 | P97: {=P78+P80+P92} -> 0 | R97: {=R78+R80+R92} -> 0 | T97: {=T78+T80+T92} -> 0 | V97: {=V78+V80+V92} -> 0 | X97: {=X78+X80+X92} -> 0 | Z97: {=Z78+Z80+Z92} -> 0

Sheet Base DRE
E2: *
E4: {=IF(E2="*","TODOS",E2)} -> TODOS
E5: {=SUBTOTAL(9,E6:E619)} -> 0
B6: Data | C6: Descrição | D6: Documento | E6: Valor (R$) | F6: Saldo (R$) | G6: Banco | H6: Tipo Conta | I6: Mês | J6: Tipo | K6: Centro de Custo | L6: CATEGORIA | M6: TIPO | N6: COD | P6: CATEGORIA | Q6: TIPO | R6: COD | T6: CENTRO DE CUSTO | Z6: Lançamentos | AA6: Categorias
M7: {=_xlfn.IFERROR(VLOOKUP(L7,P1:R625,2,0),"")} | N7: {=_xlfn.IFERROR(VLOOKUP(L7,P1:R625,3,0),"")} | P7: Receita de Vendas - Produtos | Q7: Receita | R7: 1 | T7: Pessoal | Z7: DEBITO CONVENIOS 02558157000162 VIVO | AA7: Internet e Telefonia
M8: {=_xlfn.IFERROR(VLOOKUP(L8,P1:R625,2,0),"")} | N8: {=_xlfn.IFERROR(VLOOKUP(L8,P1:R625,3,0),"")} | P8: Receita de Vendas - Serviços | Q8: Receita | R8: 1 | T8: Empresa | Z8: LIQUIDACAO BOLETO 01703365000145 ESPERANTO COMER | AA8: Lançamentos a Identificar
M9: {=_xlfn.IFERROR(VLOOKUP(L9,P1:R625,2,0),"")} | N9: {=_xlfn.IFERROR(VLOOKUP(L9,P1:R625,3,0),"")} | P9: Receita de Aluguéis Recebidos | Q9: Receita | R9: 1 | Z9: LIQUIDACAO BOLETO 22037446000123 HYGIBRAS COMERC | AA9: Lançamentos a Identificar
M10: {=_xlfn.IFERROR(VLOOKUP(L10,P1:R625,2,0),"")} | N10: {=_xlfn.IFERROR(VLOOKUP(L10,P1:R625,3,0),"")} | P10: Receita Financeira | Q10: Receita | R10: 5.2 | Z10: LIQUIDACAO BOLETO 00489050000184 JJGC INDUSTRIA | AA10: Lançamentos a Identificar
M11: {=_xlfn.IFERROR(VLOOKUP(L11,P1:R625,2,0),"")} | N11: {=_xlfn.IFERROR(VLOOKUP(L11,P1:R625,3,0),"")} | P11: Outras Receitas Operacionais | Q11: Receita | R11: 6.1 | Z11: RECEBIMENTO PIX 06299336854 LUCIA DE FATIMA COST | AA11: Receita de Vendas - Serviços
M12: {=_xlfn.IFERROR(VLOOKUP(L12,P1:R625,2,0),"")} | N12: {=_xlfn.IFERROR(VLOOKUP(L12,P1:R625,3,0),"")} | P12: Custo de Mercadoria Vendida (CMV) | Q12: Custo Variável | R12: 3 | Z12: TARIFA COM R LIQUIDACAO | AA12: Tarifas Bancárias
M13: {=_xlfn.IFERROR(VLOOKUP(L13,P1:R625,2,0),"")} | N13: {=_xlfn.IFERROR(VLOOKUP(L13,P1:R625,3,0),"")} | P13: Matéria-prima Consumida | Q13: Custo Variável | R13: 3 | Z13: SUB CR VISA | EVOLUSERVI | 0001-26 | AA13: Receita de Vendas - Produtos
M14: {=_xlfn.IFERROR(VLOOKUP(L14,P1:R625,2,0),"")} | N14: {=_xlfn.IFERROR(VLOOKUP(L14,P1:R625,3,0),"")} | P14: Comissão de Vendas | Q14: Custo Variável | R14: 2 | Z14: SUB CR MASTER | EVOLUSERVI | 0001-26 | AA14: Receita de Vendas - Produtos
M15: {=_xlfn.IFERROR(VLOOKUP(L15,P1:R625,2,0),"")} | N15: {=_xlfn.IFERROR(VLOOKUP(L15,P1:R625,3,0),"")} | P15: Frete sobre vendas | Q15: Custo Variável | R15: 3 | Z15: SUB DB MASTER | SUMUP | 0001-26 | AA15: Receita de Vendas - Produtos
M16: {=_xlfn.IFERROR(VLOOKUP(L16,P1:R625,2,0),"")} | N16: {=_xlfn.IFERROR(VLOOKUP(L16,P1:R625,3,0),"")} | P16: Impostos sobre vendas (ISS, ICMS, etc.) | Q16: Custo Variável | R16: 2 | T16: * | Z16: TED 19540550000121 ASAAS GESTAO FINANCEIRA S.A. | AA16: Receita de Vendas - Serviços
M17: {=_xlfn.IFERROR(VLOOKUP(L17,P1:R625,2,0),"")} | N17: {=_xlfn.IFERROR(VLOOKUP(L17,P1:R625,3,0),"")} | P17: Salários e Encargos Administrativos | Q17: Despesa Administrativa | R17: 4.1 | Z17: SEGURO PRESTAMISTA | AA17: Lançamentos a Identificar
M18: {=_xlfn.IFERROR(VLOOKUP(L18,P1:R625,2,0),"")} | N18: {=_xlfn.IFERROR(VLOOKUP(L18,P1:R625,3,0),"")} | P18: Aluguel | Q18: Despesa Administrativa | R18: 4.2 | Z18: LIQ.COBRANCA SIMPLES | AA18: Outras Receitas Operacionais
M19: {=_xlfn.IFERROR(VLOOKUP(L19,P1:R625,2,0),"")} | N19: {=_xlfn.IFERROR(VLOOKUP(L19,P1:R625,3,0),"")} | P19: Contabilidade | Q19: Despesa Administrativa | R19: 4.2 | Z19: PAGAMENTO PIX 11369419000131 GELCOM | AA19: Lançamentos a Identificar
M20: {=_xlfn.IFERROR(VLOOKUP(L20,P1:R625,2,0),"")} | N20: {=_xlfn.IFERROR(VLOOKUP(L20,P1:R625,3,0),"")} | P20: Consultorias | Q20: Despesa Administrativa | R20: 4.2 | Z20: PAGAMENTO PIX 44466916861 Izadora Toloti Da Silv | AA20: Salários e Encargos Administrativos
M21: {=_xlfn.IFERROR(VLOOKUP(L21,P1:R625,2,0),"")} | N21: {=_xlfn.IFERROR(VLOOKUP(L21,P1:R625,3,0),"")} | P21: Licenças e Softwares e TI | Q21: Despesa Administrativa | R21: 4.2 | Z21: PAGAMENTO PIX 45950682807 Larissa Franco Amaro | AA21: Salários e Encargos Administrativos
M22: {=_xlfn.IFERROR(VLOOKUP(L22,P1:R625,2,0),"")} | N22: {=_xlfn.IFERROR(VLOOKUP(L22,P1:R625,3,0),"")} | P22: Salários e Encargos do Comercial | Q22: Despesa Comercial | R22: 4.1 | Z22: PAGAMENTO PIX 42439634875 Nathalia Cristina Tave | AA22: Salários e Encargos Administrativos
M23: {=_xlfn.IFERROR(VLOOKUP(L23,P1:R625,2,0),"")} | N23: {=_xlfn.IFERROR(VLOOKUP(L23,P1:R625,3,0),"")} | P23: Marketing e Publicidade | Q23: Despesa Comercial | R23: 4.2 | Z23: PAGAMENTO PIX 38814883831 FABIANA GARCIA | AA23: Salários e Encargos Administrativos
M24: {=_xlfn.IFERROR(VLOOKUP(L24,P1:R625,2,0),"")} | N24: {=_xlfn.IFERROR(VLOOKUP(L24,P1:R625,3,0),"")} | P24: Ferramentas de CRM ou automação | Q24: Despesa Comercial | R24: 4.2 | Z24: PAGAMENTO PIX 41305135000142 TRIANGULO ENGENHARI | AA24: Manutenção de Equipamentos
M25: {=_xlfn.IFERROR(VLOOKUP(L25,P1:R625,2,0),"")} | N25: {=_xlfn.IFERROR(VLOOKUP(L25,P1:R625,3,0),"")} | P25: Viagens e Refeições Comerciais | Q25: Despesa Comercial | R25: 4.2 | Z25: PAGAMENTO PIX 20018692826 ADEMIR JOSE CARNEIRO | AA25: Salários e Encargos Administrativos
M26: {=_xlfn.IFERROR(VLOOKUP(L26,P1:R625,2,0),"")} | N26: {=_xlfn.IFERROR(VLOOKUP(L26,P1:R625,3,0),"")} | P26: Energia Elétrica | Q26: Despesa Operacional | R26: 4.2 | Z26: PAGAMENTO PIX 02639887831 EUNICE GOMES DOS SANTO | AA26: Salários e Encargos Administrativos
M27: {=_xlfn.IFERROR(VLOOKUP(L27,P1:R625,2,0),"")} | N27: {=_xlfn.IFERROR(VLOOKUP(L27,P1:R625,3,0),"")} | P27: Água | Q27: Despesa Operacional | R27: 4.2 | Z27: CUSTAS DE PROTESTO | AA27: Multas e Encargos
M28: {=_xlfn.IFERROR(VLOOKUP(L28,P1:R625,2,0),"")} | N28: {=_xlfn.IFERROR(VLOOKUP(L28,P1:R625,3,0),"")} | P28: Internet e Telefonia | Q28: Despesa Operacional | R28: 4.2 | Z28: TARIFA DE PROTESTO | AA28: Tarifas Bancárias
M29: {=_xlfn.IFERROR(VLOOKUP(L29,P1:R625,2,0),"")} | N29: {=_xlfn.IFERROR(VLOOKUP(L29,P1:R625,3,0),"")} | P29: Manutenção de Equipamentos | Q29: Despesa Operacional | R29: 4.2 | Z29: SUB DB ELO | EVOLUSERVI | 0001-26 | AA29: Receita de Vendas - Produtos
M30: {=_xlfn.IFERROR(VLOOKUP(L30,P1:R625,2,0),"")} | N30: {=_xlfn.IFERROR(VLOOKUP(L30,P1:R625,3,0),"")} | P30: Juros sobre Empréstimos | Q30: Despesa Financeira | R30: 5.1 | Z30: PAGAMENTO PIX 53238195883 Thayná Bachiego Cossol | AA30: Salários e Encargos Administrativos
M31: {=_xlfn.IFERROR(VLOOKUP(L31,P1:R625,2,0),"")} | N31: {=_xlfn.IFERROR(VLOOKUP(L31,P1:R625,3,0),"")} | P31: Tarifas Bancárias | Q31: Despesa Financeira | R31: 5.1 | Z31: PAGAMENTO PIX 50316590843 TAMARA GABRIELE DOMING | AA31: Salários e Encargos Administrativos
M32: {=_xlfn.IFERROR(VLOOKUP(L32,P1:R625,2,0),"")} | N32: {=_xlfn.IFERROR(VLOOKUP(L32,P1:R625,3,0),"")} | P32: Multas e Encargos | Q32: Despesa Financeira | R32: 5.1 | Z32: PAGAMENTO PIX 38052340829 ANA CLAUDIA DE OLIVEIR | AA32: Salários e Encargos Administrativos
M33: {=_xlfn.IFERROR(VLOOKUP(L33,P1:R625,2,0),"")} | N33: {=_xlfn.IFERROR(VLOOKUP(L33,P1:R625,3,0),"")} | P33: Descontos Concedidos | Q33: Despesa Financeira | R33: 5.1 | Z33: PAGAMENTO PIX SICREDI 25481403854 MIRIAM RAQUEL | AA33: Salários e Encargos Administrativos
M34: {=_xlfn.IFERROR(VLOOKUP(L34,P1:R625,2,0),"")} | N34: {=_xlfn.IFERROR(VLOOKUP(L34,P1:R625,3,0),"")} | P34: Pró-Labore | Q34: Outros | R34: 4.3 | Z34: PAGAMENTO PIX 54774767883 Rafaela Claudino da Si | AA34: Salários e Encargos Administrativos
M35: {=_xlfn.IFERROR(VLOOKUP(L35,P1:R625,2,0),"")} | N35: {=_xlfn.IFERROR(VLOOKUP(L35,P1:R625,3,0),"")} | P35: Distribuição de Lucros | Q35: Outros | R35: 8 | Z35: SUB DB MASTER | EVOLUSERVI | 0001-26 | AA35: Receita de Vendas - Produtos
M36: {=_xlfn.IFERROR(VLOOKUP(L36,P1:R625,2,0),"")} | N36: {=_xlfn.IFERROR(VLOOKUP(L36,P1:R625,3,0),"")} | P36: Investimentos | Q36: Outros | R36: 7.1 | Z36: RECEBIMENTO PIX 01664924850 MARTA F.MASSARO | AA36: Receita de Vendas - Serviços
M37: {=_xlfn.IFERROR(VLOOKUP(L37,P1:R625,2,0),"")} | N37: {=_xlfn.IFERROR(VLOOKUP(L37,P1:R625,3,0),"")} | P37: Empréstimos e Financiamentos | Q37: Outros | R37: 7.3 | Z37: RECEBIMENTO PIX 05241466835 MARIA HELENA PEDRINA | AA37: Receita de Vendas - Serviços
M38: {=_xlfn.IFERROR(VLOOKUP(L38,P1:R625,2,0),"")} | N38: {=_xlfn.IFERROR(VLOOKUP(L38,P1:R625,3,0),"")} | P38: Provisões (13º, férias, etc.) | Q38: Outros | R38: 4.1 | Z38: MANUTENCAO DE TITULOS | AA38: Tarifas Bancárias
M39: {=_xlfn.IFERROR(VLOOKUP(L39,P1:R625,2,0),"")} | N39: {=_xlfn.IFERROR(VLOOKUP(L39,P1:R625,3,0),"")} | P39: Lançamentos a Identificar | Q39: Outros | R39: 8 | Z39: SUB CR VISA | SUMUP | 0001-26 | AA39: Receita de Vendas - Produtos
M40: {=_xlfn.IFERROR(VLOOKUP(L40,P1:R625,2,0),"")} | N40: {=_xlfn.IFERROR(VLOOKUP(L40,P1:R625,3,0),"")} | Z40: RECEBIMENTO PIX 39766716811 Debora Paina Alonso | AA40: Receita de Vendas - Serviços
M41: {=_xlfn.IFERROR(VLOOKUP(L41,P1:R625,2,0),"")} | N41: {=_xlfn.IFERROR(VLOOKUP(L41,P1:R625,3,0),"")} | Z41: PAGAMENTO PIX 09804828448 JOSE FERNANDO ALVES MA | AA41: Salários e Encargos Administrativos
M42: {=_xlfn.IFERROR(VLOOKUP(L42,P1:R625,2,0),"")} | N42: {=_xlfn.IFERROR(VLOOKUP(L42,P1:R625,3,0),"")} | Z42: PAGAMENTO PIX SICREDI 37405075000162 AJ MOVEIS E | AA42: Manutenção de Equipamentos
M43: {=_xlfn.IFERROR(VLOOKUP(L43,P1:R625,2,0),"")} | N43: {=_xlfn.IFERROR(VLOOKUP(L43,P1:R625,3,0),"")} | Z43: PAGAMENTO PIX 29618754000191 GRAN TEC MANUTENCAO | AA43: Manutenção de Equipamentos
M44: {=_xlfn.IFERROR(VLOOKUP(L44,P1:R625,2,0),"")} | N44: {=_xlfn.IFERROR(VLOOKUP(L44,P1:R625,3,0),"")} | Z44: RECEBIMENTO PIX SICREDI 12448725000126 A M M ODO | AA44: Receita de Vendas - Produtos
M45: {=_xlfn.IFERROR(VLOOKUP(L45,P1:R625,2,0),"")} | N45: {=_xlfn.IFERROR(VLOOKUP(L45,P1:R625,3,0),"")} | Z45: PAGAMENTO PIX 07275920000161 LENOVO TECNOLOGIA B | AA45: Licenças e Softwares e TI
M46: {=_xlfn.IFERROR(VLOOKUP(L46,P1:R625,2,0),"")} | N46: {=_xlfn.IFERROR(VLOOKUP(L46,P1:R625,3,0),"")} | Z46: PAGAMENTO PIX 38607389840 Rui Carvalho Nasciment | AA46: Salários e Encargos Administrativos
M47: {=_xlfn.IFERROR(VLOOKUP(L47,P1:R625,2,0),"")} | N47: {=_xlfn.IFERROR(VLOOKUP(L47,P1:R625,3,0),"")} | Z47: PAGAMENTO PIX 12007975661 GABRIEL DE PAULA RODRI | AA47: Salários e Encargos Administrativos
M48: {=_xlfn.IFERROR(VLOOKUP(L48,P1:R625,2,0),"")} | N48: {=_xlfn.IFERROR(VLOOKUP(L48,P1:R625,3,0),"")} | Z48: DEVOLUCAO PIX 12007975661 GABRIEL DE PAULA RODRI | AA48: Descontos Concedidos
M49: {=_xlfn.IFERROR(VLOOKUP(L49,P1:R625,2,0),"")} | N49: {=_xlfn.IFERROR(VLOOKUP(L49,P1:R625,3,0),"")} | Z49: PAGAMENTO PIX 71850406804 JOAO EDUARDO MORAES | AA49: Salários e Encargos Administrativos
M50: {=_xlfn.IFERROR(VLOOKUP(L50,P1:R625,2,0),"")} | N50: {=_xlfn.IFERROR(VLOOKUP(L50,P1:R625,3,0),"")} | Z50: PAGAMENTO PIX 64565587000169 GABRIEL DE PAULA RO | AA50: Salários e Encargos Administrativos
M51: {=_xlfn.IFERROR(VLOOKUP(L51,P1:R625,2,0),"")} | N51: {=_xlfn.IFERROR(VLOOKUP(L51,P1:R625,3,0),"")} | Z51: DEBITO CONVENIOS 40432544000147 CLARSP11G | AA51: Internet e Telefonia
M52: {=_xlfn.IFERROR(VLOOKUP(L52,P1:R625,2,0),"")} | N52: {=_xlfn.IFERROR(VLOOKUP(L52,P1:R625,3,0),"")} | Z52: RECEBIMENTO PIX 71850406804 JOAO EDUARDO MORAES | AA52: Receita de Vendas - Serviços
M53: {=_xlfn.IFERROR(VLOOKUP(L53,P1:R625,2,0),"")} | N53: {=_xlfn.IFERROR(VLOOKUP(L53,P1:R625,3,0),"")} | Z53: LIQUIDACAO BOLETO 29915312000107 BIONNOVATION BI | AA53: Lançamentos a Identificar
M54: {=_xlfn.IFERROR(VLOOKUP(L54,P1:R625,2,0),"")} | N54: {=_xlfn.IFERROR(VLOOKUP(L54,P1:R625,3,0),"")} | Z54: LIQUIDACAO BOLETO 21279354000197 ODONTO PREMIUM | AA54: Lançamentos a Identificar
M55: {=_xlfn.IFERROR(VLOOKUP(L55,P1:R625,2,0),"")} | N55: {=_xlfn.IFERROR(VLOOKUP(L55,P1:R625,3,0),"")} | Z55: COMPRA DEBITO MASTER FEST PAO MOCOCA BR | AA55: Viagens e Refeições Comerciais
M56: {=_xlfn.IFERROR(VLOOKUP(L56,P1:R625,2,0),"")} | N56: {=_xlfn.IFERROR(VLOOKUP(L56,P1:R625,3,0),"")} | Z56: RECEBIMENTO PIX 68700300810 NELSON COSTI FILHO | AA56: Receita de Vendas - Serviços
M57: {=_xlfn.IFERROR(VLOOKUP(L57,P1:R625,2,0),"")} | N57: {=_xlfn.IFERROR(VLOOKUP(L57,P1:R625,3,0),"")} | Z57: PAGAMENTO PIX 10573521000191 PIX Marketplace | AA57: Ferramentas de CRM ou automação
M58: {=_xlfn.IFERROR(VLOOKUP(L58,P1:R625,2,0),"")} | N58: {=_xlfn.IFERROR(VLOOKUP(L58,P1:R625,3,0),"")} | Z58: PAGAMENTO PIX SICREDI 33930045818 ANDRE FERREIRA | AA58: Salários e Encargos Administrativos
M59: {=_xlfn.IFERROR(VLOOKUP(L59,P1:R625,2,0),"")} | N59: {=_xlfn.IFERROR(VLOOKUP(L59,P1:R625,3,0),"")} | Z59: RECEB. COB HIBRIDA (I) 39656334817SUSIMARI FURLA | AA59: Receita de Vendas - Serviços
M60: {=_xlfn.IFERROR(VLOOKUP(L60,P1:R625,2,0),"")} | N60: {=_xlfn.IFERROR(VLOOKUP(L60,P1:R625,3,0),"")} | Z60: TARIFA LIQUIDACAO PIXCOB | AA60: Tarifas Bancárias
M61: {=_xlfn.IFERROR(VLOOKUP(L61,P1:R625,2,0),"")} | N61: {=_xlfn.IFERROR(VLOOKUP(L61,P1:R625,3,0),"")} | Z61: LIQUIDACAO BOLETO 47000211000198 ECO ESCRITORIO | AA61: Lançamentos a Identificar
M62: {=_xlfn.IFERROR(VLOOKUP(L62,P1:R625,2,0),"")} | N62: {=_xlfn.IFERROR(VLOOKUP(L62,P1:R625,3,0),"")} | Z62: LIQUIDACAO BOLETO SICREDI 37405075000162 AJ MOVE | AA62: Manutenção de Equipamentos
M63: {=_xlfn.IFERROR(VLOOKUP(L63,P1:R625,2,0),"")} | N63: {=_xlfn.IFERROR(VLOOKUP(L63,P1:R625,3,0),"")} | Z63: SUB CR MASTER | SUMUP | 0001-26 | AA63: Receita de Vendas - Produtos
M64: {=_xlfn.IFERROR(VLOOKUP(L64,P1:R625,2,0),"")} | N64: {=_xlfn.IFERROR(VLOOKUP(L64,P1:R625,3,0),"")} | Z64: LIQUIDACAO BOLETO 45233574000148 SIND EMPREG EST | AA64: Lançamentos a Identificar
M65: {=_xlfn.IFERROR(VLOOKUP(L65,P1:R625,2,0),"")} | N65: {=_xlfn.IFERROR(VLOOKUP(L65,P1:R625,3,0),"")} | Z65: LIQUIDACAO BOLETO SICREDI 15299200000164 RESIDEN | AA65: Aluguel
M66: {=_xlfn.IFERROR(VLOOKUP(L66,P1:R625,2,0),"")} | N66: {=_xlfn.IFERROR(VLOOKUP(L66,P1:R625,3,0),"")} | Z66: LIQUIDACAO BOLETO 46396925000102 ASSOCIACAO COME | AA66: Lançamentos a Identificar
M67: {=_xlfn.IFERROR(VLOOKUP(L67,P1:R625,2,0),"")} | N67: {=_xlfn.IFERROR(VLOOKUP(L67,P1:R625,3,0),"")} | Z67: PLANO INT CAPITAL | AA67: Investimentos
M68: {=_xlfn.IFERROR(VLOOKUP(L68,P1:R625,2,0),"")} | N68: {=_xlfn.IFERROR(VLOOKUP(L68,P1:R625,3,0),"")} | Z68: DEBITO CONVENIOS 53859112000169 CPFLJA-CB | AA68: Energia Elétrica
M69: {=_xlfn.IFERROR(VLOOKUP(L69,P1:R625,2,0),"")} | N69: {=_xlfn.IFERROR(VLOOKUP(L69,P1:R625,3,0),"")} | Z69: PAGAMENTO PIX 06330387000120 MAXIMUS INDUSTRIA E | AA69: Custo de Mercadoria Vendida (CMV)
M70: {=_xlfn.IFERROR(VLOOKUP(L70,P1:R625,2,0),"")} | N70: {=_xlfn.IFERROR(VLOOKUP(L70,P1:R625,3,0),"")} | Z70: PAGAMENTO PIX 43416001000124 43.416.001 TALITA M | AA70: Salários e Encargos Administrativos
M71: {=_xlfn.IFERROR(VLOOKUP(L71,P1:R625,2,0),"")} | N71: {=_xlfn.IFERROR(VLOOKUP(L71,P1:R625,3,0),"")} | Z71: PAGAMENTO PIX 10293774000101 CHAVEIRO VENTANIA L | AA71: Manutenção de Equipamentos
M72: {=_xlfn.IFERROR(VLOOKUP(L72,P1:R625,2,0),"")} | N72: {=_xlfn.IFERROR(VLOOKUP(L72,P1:R625,3,0),"")} | Z72: PAGAMENTO PIX 42075759000183 42 075 759 LUCAS DE | AA72: Salários e Encargos Administrativos
M73: {=_xlfn.IFERROR(VLOOKUP(L73,P1:R625,2,0),"")} | N73: {=_xlfn.IFERROR(VLOOKUP(L73,P1:R625,3,0),"")} | Z73: DEB.CTA.FATURA | AA73: Lançamentos a Identificar
M74: {=_xlfn.IFERROR(VLOOKUP(L74,P1:R625,2,0),"")} | N74: {=_xlfn.IFERROR(VLOOKUP(L74,P1:R625,3,0),"")} | Z74: LIQUIDACAO BOLETO 04657685000102 M M AMBIENTAL | AA74: Manutenção de Equipamentos
M75: {=_xlfn.IFERROR(VLOOKUP(L75,P1:R625,2,0),"")} | N75: {=_xlfn.IFERROR(VLOOKUP(L75,P1:R625,3,0),"")} | Z75: RECEB. COB HIBRIDA (I) 04099118878BENEDITO APARE | AA75: Receita de Vendas - Serviços
M76: {=_xlfn.IFERROR(VLOOKUP(L76,P1:R625,2,0),"")} | N76: {=_xlfn.IFERROR(VLOOKUP(L76,P1:R625,3,0),"")} | Z76: TARIFA BAIXA DE TITULOS | AA76: Tarifas Bancárias
M77: {=_xlfn.IFERROR(VLOOKUP(L77,P1:R625,2,0),"")} | N77: {=_xlfn.IFERROR(VLOOKUP(L77,P1:R625,3,0),"")} | Z77: RECEBIMENTO PIX 30059106875 ALESSANDRA URIAS DA | AA77: Receita de Vendas - Serviços
M78: {=_xlfn.IFERROR(VLOOKUP(L78,P1:R625,2,0),"")} | N78: {=_xlfn.IFERROR(VLOOKUP(L78,P1:R625,3,0),"")} | Z78: LIQUIDACAO BOLETO 00814559000155 SURYA DENTAL CO | AA78: Custo de Mercadoria Vendida (CMV)
M79: {=_xlfn.IFERROR(VLOOKUP(L79,P1:R625,2,0),"")} | N79: {=_xlfn.IFERROR(VLOOKUP(L79,P1:R625,3,0),"")} | Z79: PAGAMENTO PIX SICREDI 21207005000160 JUNQUEIRA E | AA79: Consultorias
M80: {=_xlfn.IFERROR(VLOOKUP(L80,P1:R625,2,0),"")} | N80: {=_xlfn.IFERROR(VLOOKUP(L80,P1:R625,3,0),"")} | Z80: PAGAMENTO PIX 11972256000187 11972256 LUCAS FRAN | AA80: Salários e Encargos Administrativos
M81: {=_xlfn.IFERROR(VLOOKUP(L81,P1:R625,2,0),"")} | N81: {=_xlfn.IFERROR(VLOOKUP(L81,P1:R625,3,0),"")} | Z81: COMPRA DEBITO MASTER GABRIEL MIACHON SANTO MOCOC | AA81: Viagens e Refeições Comerciais
M82: {=_xlfn.IFERROR(VLOOKUP(L82,P1:R625,2,0),"")} | N82: {=_xlfn.IFERROR(VLOOKUP(L82,P1:R625,3,0),"")} | Z82: PAGAMENTO PIX 42563672000155 PAGALEVE INSTITUICA | AA82: Ferramentas de CRM ou automação
M83: {=_xlfn.IFERROR(VLOOKUP(L83,P1:R625,2,0),"")} | N83: {=_xlfn.IFERROR(VLOOKUP(L83,P1:R625,3,0),"")} | Z83: PAGAMENTO PIX 06347409000165 SBF COMERCIO DE PRO | AA83: Custo de Mercadoria Vendida (CMV)
M84: {=_xlfn.IFERROR(VLOOKUP(L84,P1:R625,2,0),"")} | N84: {=_xlfn.IFERROR(VLOOKUP(L84,P1:R625,3,0),"")} | Z84: PAGTO FATURA MASTER | AA84: Lançamentos a Identificar
M85: {=_xlfn.IFERROR(VLOOKUP(L85,P1:R625,2,0),"")} | N85: {=_xlfn.IFERROR(VLOOKUP(L85,P1:R625,3,0),"")} | Z85: RECEB. COB HIBRIDA (I) 09672381883NELSON TEODORO | AA85: Receita de Vendas - Serviços
M86: {=_xlfn.IFERROR(VLOOKUP(L86,P1:R625,2,0),"")} | N86: {=_xlfn.IFERROR(VLOOKUP(L86,P1:R625,3,0),"")} | Z86: PAGAMENTO PIX 38184368860 MARCELA PUCIARELLI MAD | AA86: Salários e Encargos Administrativos
M87: {=_xlfn.IFERROR(VLOOKUP(L87,P1:R625,2,0),"")} | N87: {=_xlfn.IFERROR(VLOOKUP(L87,P1:R625,3,0),"")} | Z87: PAGAMENTO PIX 54342725000197 FERNANDA TEIXEIRA G | AA87: Consultorias
M88: {=_xlfn.IFERROR(VLOOKUP(L88,P1:R625,2,0),"")} | N88: {=_xlfn.IFERROR(VLOOKUP(L88,P1:R625,3,0),"")} | Z88: RECEBIMENTO PIX 16833154805 LUIS ANTONIO DONIZET | AA88: Receita de Vendas - Serviços
M89: {=_xlfn.IFERROR(VLOOKUP(L89,P1:R625,2,0),"")} | N89: {=_xlfn.IFERROR(VLOOKUP(L89,P1:R625,3,0),"")} | Z89: RECEBIMENTO PIX 57308043000156 FF SUPERVISAO E F | AA89: Receita de Vendas - Serviços
M90: {=_xlfn.IFERROR(VLOOKUP(L90,P1:R625,2,0),"")} | N90: {=_xlfn.IFERROR(VLOOKUP(L90,P1:R625,3,0),"")} | Z90: PAGAMENTO PIX 00360305000104 CEF MATRIZ | AA90: Empréstimos e Financiamentos
M91: {=_xlfn.IFERROR(VLOOKUP(L91,P1:R625,2,0),"")} | N91: {=_xlfn.IFERROR(VLOOKUP(L91,P1:R625,3,0),"")} | Z91: DEBITO ARRECADACAO 00394460005887 DARFC0385 | AA91: Impostos sobre vendas (ISS, ICMS, etc.)
M92: {=_xlfn.IFERROR(VLOOKUP(L92,P1:R625,2,0),"")} | N92: {=_xlfn.IFERROR(VLOOKUP(L92,P1:R625,3,0),"")} | Z92: DEBITO ARRECADACAO | AA92: Impostos sobre vendas (ISS, ICMS, etc.)
M93: {=_xlfn.IFERROR(VLOOKUP(L93,P1:R625,2,0),"")} | N93: {=_xlfn.IFERROR(VLOOKUP(L93,P1:R625,3,0),"")} | Z93: LIQUIDACAO BOLETO 33164021000100 TOKIO MARINE SE | AA93: Lançamentos a Identificar
M94: {=_xlfn.IFERROR(VLOOKUP(L94,P1:R625,2,0),"")} | N94: {=_xlfn.IFERROR(VLOOKUP(L94,P1:R625,3,0),"")} | Z94: LIQUIDACAO BOLETO 46601853000180 SILVEIRA TREINA | AA94: Consultorias
M95: {=_xlfn.IFERROR(VLOOKUP(L95,P1:R625,2,0),"")} | N95: {=_xlfn.IFERROR(VLOOKUP(L95,P1:R625,3,0),"")} | Z95: COMPRA DEBITO MASTER CasaDeBolos MOCOCA BR | AA95: Viagens e Refeições Comerciais
M96: {=_xlfn.IFERROR(VLOOKUP(L96,P1:R625,2,0),"")} | N96: {=_xlfn.IFERROR(VLOOKUP(L96,P1:R625,3,0),"")} | Z96: PAGAMENTO PIX 08749840000163 PREVINI - CONSULTOR | AA96: Consultorias
M97: {=_xlfn.IFERROR(VLOOKUP(L97,P1:R625,2,0),"")} | N97: {=_xlfn.IFERROR(VLOOKUP(L97,P1:R625,3,0),"")} | Z97: PAGAMENTO PIX 25129666000175 25.129.666 BRUNO BO | AA97: Consultorias
M98: {=_xlfn.IFERROR(VLOOKUP(L98,P1:R625,2,0),"")} | N98: {=_xlfn.IFERROR(VLOOKUP(L98,P1:R625,3,0),"")} | Z98: RECEBIMENTO PIX SICREDI 25481403854 MIRIAM RAQUE | AA98: Receita de Vendas - Serviços
M99: {=_xlfn.IFERROR(VLOOKUP(L99,P1:R625,2,0),"")} | N99: {=_xlfn.IFERROR(VLOOKUP(L99,P1:R625,3,0),"")} | Z99: PAGAMENTO PIX SICREDI 41894931000168 STAFF MONIT | AA99: Manutenção de Equipamentos
M100: {=_xlfn.IFERROR(VLOOKUP(L100,P1:R625,2,0),"")} | N100: {=_xlfn.IFERROR(VLOOKUP(L100,P1:R625,3,0),"")} | Z100: DEBITO CONVENIOS 03795072000160 PMOCOCASP | AA100: Impostos sobre vendas (ISS, ICMS, etc.)
M101: {=_xlfn.IFERROR(VLOOKUP(L101,P1:R625,2,0),"")} | N101: {=_xlfn.IFERROR(VLOOKUP(L101,P1:R625,3,0),"")} | Z101: RECEBIMENTO PIX SICREDI 44832368001163 DIOCESE D | AA101: Outras Receitas Operacionais
M102: {=_xlfn.IFERROR(VLOOKUP(L102,P1:R625,2,0),"")} | N102: {=_xlfn.IFERROR(VLOOKUP(L102,P1:R625,3,0),"")} | Z102: PAGAMENTO PIX SICREDI 44832368001163 DIOCESE DE | AA102: Lançamentos a Identificar
...

Sheet Base DRE Arquivo
D1: {=SUBTOTAL(9,D2:D306)} -> -18987.94
A2: DATA | B2: DOCUMENTO | C2: HISTÓRICO | D2: VALOR | E2: CATEGORIA | F2: TIPO | G2: MÊS | H2: Classificação | I2: CAT | J2: obs | L2: Item Original | M2: Categoria | N2: Tipo | O2: Descrição Sugerida | P2: Frequência Estimada
A3: 03/02/2025 | B3: Pix | C3: PIX EMITIDO OUTRA IF | D3: -250 | E3: certificado digital notas | F3: DESPESA | G3: FEV | H3: {=VLOOKUP(E3,L1:N306,2,0)} -> Despesa Fixa | I3: {=VLOOKUP(E3,L1:N306,3,0)} -> Administrativa | L3: certificado digital notas | M3: Despesa Fixa | N3: Administrativa | O3: Certificado digital para emissão de NF | P3: Anual
A4: 03/02/2025 | B4: Pix | C4: PIX RECEBIDO - OUTRA IF | D4: 2690 | E4: venda | F4: RECEITA | G4: FEV | H4: Receita | I4: VENDA | L4: financiamento casa que aluga | M4: Investimento | N4: Financiamento | O4: Financiamento de imóvel alugado | P4: Mensal
A5: 03/02/2025 | B5: Pix | C5: PIX RECEBIDO - OUTRA IF | D5: 175.23 | E5: ESTORNO E DEVOLUÇÃO | F5: RECEITA | G5: FEV | H5: Receita | I5: devoluçao mercado livre | L5: serviço mulck | M5: Despesa Variável | N5: Operacional | O5: Serviço eventual (verificar finalidade) | P5: Eventual
A6: 03/02/2025 | B6: Pix | C6: PIX EMITIDO OUTRA IF | D6: -900 | E6: financiamento CASA INVESTIMENTO | F6: DESPESA | G6: FEV | H6: {=VLOOKUP(E6,L1:N306,2,0)} | I6: {=VLOOKUP(E6,L1:N306,3,0)} | L6: financiamento placa solar | M6: Investimento | N6: Financiamento | O6: Parcelas de placas solares | P6: Mensal
A7: 03/02/2025 | B7: Pix | C7: PIX EMITIDO OUTRA IF | D7: -2100 | E7: serviço de Terceiro | F7: DESPESA | G7: FEV | H7: {=VLOOKUP(E7,L1:N306,2,0)} | I7: Munk | L7: salario pai | M7: Despesa Fixa | N7: Pessoal | O7: Pró-labore pai | P7: Mensal
A8: 03/02/2025 | B8: 1675015 | C8: DÉB.EMPRÉSTIMO | D8: -2429.27 | E8: financiamento placa solar | F8: DESPESA | G8: FEV | H8: {=VLOOKUP(E8,L1:N306,2,0)} -> Investimento | I8: {=VLOOKUP(E8,L1:N306,3,0)} -> Financiamento | L8: fornecedor | M8: Despesa Variável | N8: Custo Direto | O8: Pagamento de fornecedor | P8: Conforme demanda
A9: 03/02/2025 | B9: Pix | C9: PIX RECEBIDO - OUTRA IF - MESMA TIT. | D9: 74 | E9: venda | F9: RECEITA | G9: FEV | H9: Receita | I9: VENDA | L9: telefone | M9: Despesa Fixa | N9: Comunicação | O9: Conta de telefone | P9: Mensal
A10: 03/02/2025 | B10: Pix | C10: PIX EMITIDO OUTRA IF | D10: -124 | E10: prolabore | F10: DESPESA | G10: FEV | H10: {=VLOOKUP(E10,L1:N306,2,0)} | I10: salario pai | J10: explicar para Jussara | L10: internet | M10: Despesa Fixa | N10: Comunicação | O10: Conta de internet | P10: Mensal
A11: 03/02/2025 | B11: 38351258 | C11: DÉB.TIT.COMPE EFETIVADO | D11: -1848.96 | E11: prolabore | F11: DESPESA | G11: FEV | H11: {=VLOOKUP(E11,L1:N306,2,0)} | I11: salario pai | J11: explicar para Jussara | L11: taxa conta | M11: Despesa Fixa | N11: Bancária | O11: Tarifas bancárias | P11: Mensal
A12: 03/02/2025 | B12: 38351930 | C12: DÉB.TIT.COMPE EFETIVADO | D12: -1225.35 | E12: fornecedor | F12: DESPESA | G12: FEV | H12: {=VLOOKUP(E12,L1:N306,2,0)} -> Despesa Variável | I12: {=VLOOKUP(E12,L1:N306,3,0)} -> Custo Direto | L12: juros | M12: Despesa Fixa | N12: Financeira | O12: Juros diversos sobre contas ou dívidas | P12: Mensal/Eventual
A13: 03/02/2025 | B13: 38351942 | C13: DÉB.TIT.COMPE EFETIVADO | D13: -732.18 | E13: fornecedor | F13: DESPESA | G13: FEV | H13: {=VLOOKUP(E13,L1:N306,2,0)} -> Despesa Variável | I13: {=VLOOKUP(E13,L1:N306,3,0)} -> Custo Direto | L13: IPTU casa aluguel | M13: Despesa Fixa | N13: Tributária | O13: IPTU da casa alugada | P13: Anual
A14: 03/02/2025 | B14: 38351959 | C14: DÉB.TIT.COMPE EFETIVADO | D14: -2798.07 | E14: fornecedor | F14: DESPESA | G14: FEV | H14: {=VLOOKUP(E14,L1:N306,2,0)} -> Despesa Variável | I14: {=VLOOKUP(E14,L1:N306,3,0)} -> Custo Direto | L14: escritorio mensal | M14: Despesa Fixa | N14: Administrativa | O14: Aluguel ou estrutura de escritório | P14: Mensal
A15: 03/02/2025 | B15: 38351973 | C15: DÉB.TIT.COMPE EFETIVADO | D15: -247.63 | E15: fornecedor | F15: DESPESA | G15: FEV | H15: {=VLOOKUP(E15,L1:N306,2,0)} -> Despesa Variável | I15: {=VLOOKUP(E15,L1:N306,3,0)} -> Custo Direto | L15: salario pai (3.150,00 salario jussara) | M15: Despesa Fixa | N15: Pessoal | O15: Salário Jussara e/ou pró-labore pai | P15: Mensal
A16: 03/02/2025 | B16: 38352077 | C16: DÉB.CONV.TELECOMUNICAÇÕES | D16: -29.73 | E16: telefone | F16: DESPESA | G16: FEV | H16: {=VLOOKUP(E16,L1:N306,2,0)} -> Despesa Fixa | I16: {=VLOOKUP(E16,L1:N306,3,0)} -> Comunicação | L16: salario funcionarios | M16: Despesa Fixa | N16: Pessoal | O16: Salários da equipe | P16: Mensal
A17: 03/02/2025 | B17: Pix | C17: PIX EMITIDO OUTRA IF | D17: -99.9 | E17: internet | F17: DESPESA | G17: FEV | H17: {=VLOOKUP(E17,L1:N306,2,0)} -> Despesa Fixa | I17: {=VLOOKUP(E17,L1:N306,3,0)} -> Comunicação | L17: fornecedor estornou | M17: Ajuste de Receita | N17: Reembolso | O17: Estorno de fornecedor | P17: Eventual
A18: 03/02/2025 | B18: Pix | C18: PIX EMITIDO OUTRA IF | D18: -529.11 | E18: fornecedor | F18: DESPESA | G18: FEV | H18: {=VLOOKUP(E18,L1:N306,2,0)} -> Despesa Variável | I18: {=VLOOKUP(E18,L1:N306,3,0)} -> Custo Direto | L18: taxa de boleto | M18: Despesa Variável | N18: Financeira | O18: Taxas por emissão de boletos | P18: Conforme emissão
A19: 03/02/2025 | B19: Pix | C19: PIX EMITIDO OUTRA IF | D19: -500 | E19: prolabore | F19: DESPESA | G19: FEV | H19: {=VLOOKUP(E19,L1:N306,2,0)} | I19: salario pai | J19: explicar para Jussara | L19: CPFL | M19: Despesa Variável | N19: Energia | O19: Conta de energia elétrica | P19: Mensal
A20: 03/02/2025 | B20: Pix | C20: PIX RECEBIDO - OUTRA IF - MESMA TIT. | D20: 191 | E20: venda | F20: RECEITA | G20: FEV | H20: Receita | I20: VENDA | L20: emprestado | M20: Empréstimo | N20: Passivo | O20: Valor emprestado a terceiros | P20: Eventual
A21: 03/02/2025 | B21: 129 | C21: DÉBITO PACOTE SERVIÇOS | D21: -19.9 | E21: taxa conta | F21: DESPESA | G21: FEV | H21: {=VLOOKUP(E21,L1:N306,2,0)} -> Despesa Fixa | I21: {=VLOOKUP(E21,L1:N306,3,0)} -> Bancária | L21: emprestimo | M21: Empréstimo | N21: Passivo | O21: Empréstimo recebido | P21: Mensal/Eventual
A22: 03/02/2025 | B22: IOF/3-2 | C22: DÉB.IOF | D22: -1.71 | E22: juros | F22: DESPESA | G22: FEV | H22: {=VLOOKUP(E22,L1:N306,2,0)} -> Despesa Fixa | I22: {=VLOOKUP(E22,L1:N306,3,0)} -> Financeira | L22: guardei na caixinha | M22: Outros | N22: Reserva | O22: Valor separado em caixa | P22: Eventual
A23: 03/02/2025 | B23: IOF/3-2 | C23: DÉB.IOF | D23: -36.07 | E23: juros | F23: DESPESA | G23: FEV | H23: {=VLOOKUP(E23,L1:N306,2,0)} -> Despesa Fixa | I23: {=VLOOKUP(E23,L1:N306,3,0)} -> Financeira | L23: escritorio contabilidade | M23: Despesa Fixa | N23: Contábil | O23: Escritório ou serviço de contabilidade | P23: Mensal
A24: 04/02/2025 | B24: 38369735 | C24: TRANSF.RECEBIDA - PIX SICOOB | D24: 720 | E24: aluguel | F24: RECEITA | G24: FEV | H24: Receita | I24: Aluguel | L24: IPTU casa/serralheria | M24: Despesa Fixa | N24: Tributária | O24: IPTU do imóvel da serralheria | P24: Anual
A25: 04/02/2025 | B25: Pix | C25: PIX RECEBIDO - OUTRA IF | D25: 30 | E25: venda | F25: RECEITA | G25: FEV | H25: Receita | I25: VENDA | L25: agua salario pai | M25: Despesa Fixa | N25: Pessoal/Utilidade | O25: Água vinculada ao pró-labore do pai | P25: Mensal
A26: 04/02/2025 | B26: Pix | C26: PIX EMITIDO OUTRA IF | D26: -203.18 | E26: IPTU Casa Investimento | F26: DESPESA | G26: FEV | H26: {=VLOOKUP(E26,L1:N306,2,0)} | I26: {=VLOOKUP(E26,L1:N306,3,0)} | J26: PERGUNTAR PARA JUSSARA | L26: agua serralheria | M26: Despesa Fixa | N26: Utilidade | O26: Conta de água da serralheria | P26: Mensal
A27: 04/02/2025 | B27: Pix | C27: PIX RECEBIDO - OUTRA IF | D27: 1300 | E27: venda | F27: RECEITA | G27: FEV | H27: Receita | I27: VENDA | L27: celular internet | M27: Despesa Fixa | N27: Comunicação | O27: Planos de celular e internet | P27: Mensal
A28: 04/02/2025 | B28: Pix | C28: PIX EMITIDO OUTRA IF | D28: -170.72 | E28: fornecedor | F28: DESPESA | G28: FEV | H28: {=VLOOKUP(E28,L1:N306,2,0)} -> Despesa Variável | I28: {=VLOOKUP(E28,L1:N306,3,0)} -> Custo Direto | L28: financiamento | M28: Investimento | N28: Financiamento | O28: Financiamento genérico (verificar qual) | P28: Mensal
A29: 05/02/2025 | B29: Pix | C29: PIX EMITIDO OUTRA IF | D29: -2.34 | E29: fornecedor | F29: DESPESA | G29: FEV | H29: {=VLOOKUP(E29,L1:N306,2,0)} -> Despesa Variável | I29: {=VLOOKUP(E29,L1:N306,3,0)} -> Custo Direto | L29: funcionarios | M29: Despesa Fixa | N29: Pessoal | O29: Salários da equipe | P29: Mensal
A30: 05/02/2025 | B30: Pix | C30: PIX EMITIDO OUTRA IF | D30: -470 | E30: Mensalidade Contabilidade | F30: DESPESA | G30: FEV | H30: {=VLOOKUP(E30,L1:N306,2,0)} | I30: {=VLOOKUP(E30,L1:N306,3,0)} | J30: PERGUNTAR PARA JUSSARA | L30: financiamento placa | M30: Investimento | N30: Financiamento | O30: Referente à parcela de placas solares | P30: Mensal
A31: 05/02/2025 | B31: 38396284 | C31: DÉB.TRANSF.CONTAS DIF.TIT. INTERCREDIS | D31: -115 | E31: fornecedor | F31: DESPESA | G31: FEV | H31: {=VLOOKUP(E31,L1:N306,2,0)} -> Despesa Variável | I31: {=VLOOKUP(E31,L1:N306,3,0)} -> Custo Direto | L31: agua | M31: Despesa Fixa | N31: Utilidade | O31: Conta de água geral | P31: Mensal
A32: 05/02/2025 | B32: Pix | C32: PIX EMITIDO OUTRA IF | D32: -220 | E32: fornecedor | F32: DESPESA | G32: FEV | H32: {=VLOOKUP(E32,L1:N306,2,0)} -> Despesa Variável | I32: {=VLOOKUP(E32,L1:N306,3,0)} -> Custo Direto | L32: IPTU | M32: Despesa Fixa | N32: Tributária | O32: Imposto predial | P32: Anual
A33: 05/02/2025 | B33: Pix | C33: PIX RECEBIDO - OUTRA IF | D33: 220 | E33: venda | F33: RECEITA | G33: FEV | H33: Receita | I33: VENDA | L33: posto | M33: Despesa Variável | N33: Transporte | O33: Combustível / deslocamentos | P33: Variável
A34: 05/02/2025 | B34: Pix | C34: PIX EMITIDO OUTRA IF | D34: -150 | E34: fornecedor | F34: DESPESA | G34: FEV | H34: {=VLOOKUP(E34,L1:N306,2,0)} -> Despesa Variável | I34: {=VLOOKUP(E34,L1:N306,3,0)} -> Custo Direto | L34: funcionario | M34: Despesa Fixa | N34: Pessoal | O34: Salário de funcionário | P34: Mensal
A35: 05/02/2025 | B35: Pix | C35: PIX EMITIDO OUTRA IF | D35: -580 | E35: fornecedor | F35: DESPESA | G35: FEV | H35: {=VLOOKUP(E35,L1:N306,2,0)} -> Despesa Variável | I35: {=VLOOKUP(E35,L1:N306,3,0)} -> Custo Direto | L35: seguro casa | M35: Despesa Fixa | N35: Seguro | O35: Seguro de imóvel | P35: Anual ou mensal
A36: 06/02/2025 | B36: Pix | C36: PIX EMITIDO OUTRA IF | D36: -20429.27 | E36: prolabore | F36: DESPESA | G36: FEV | H36: {=VLOOKUP(E36,L1:N306,2,0)} | I36: salario pai | J36: explicar para Jussara | L36: contabilidade | M36: Despesa Fixa | N36: Contábil | O36: Honorários contábeis | P36: Mensal
A37: 06/02/2025 | B37: Pix | C37: PIX RECEBIDO - OUTRA IF | D37: 272 | E37: emprestado | F37: RECEITA | G37: FEV | H37: {=VLOOKUP(E37,L1:N306,2,0)} -> Empréstimo | I37: {=VLOOKUP(E37,L1:N306,3,0)} -> Passivo | L37: emprestado, salario pai e fornecedor | M37: Diversos | N37: Agrupamento | O37: Mistura de empréstimo, pró-labore e fornecedores | P37: Reavaliar
A38: 06/02/2025 | B38: Pix | C38: PIX RECEBIDO - OUTRA IF | D38: 290 | E38: venda | F38: RECEITA | G38: FEV | H38: Receita | I38: VENDA | L38: salario pai | M38: Despesa Fixa | N38: Pessoal | O38: Pró-labore pai | P38: Mensal
A39: 06/02/2025 | B39: 325057597 | C39: CRÉD.TED-STR | D39: 4372 | E39: aposentadoria | F39: RECEITA | G39: FEV | H39: Receita | I39: Receita | L39: salario funcionarios | M39: Despesa Fixa | N39: Pessoal | O39: Salários da equipe | P39: Mensal
A40: 06/02/2025 | B40: Pix | C40: PIX EMITIDO OUTRA IF | D40: -1405.63 | E40: funcionarios | F40: DESPESA | G40: FEV | H40: {=VLOOKUP(E40,L1:N306,2,0)} -> Despesa Fixa | I40: {=VLOOKUP(E40,L1:N306,3,0)} -> Pessoal | L40: escritorio contabilidade
A41: 06/02/2025 | B41: Pix | C41: PIX EMITIDO OUTRA IF | D41: -793.85 | E41: funcionarios | F41: DESPESA | G41: FEV | H41: {=VLOOKUP(E41,L1:N306,2,0)} -> Despesa Fixa | I41: {=VLOOKUP(E41,L1:N306,3,0)} -> Pessoal | L41: agua salario pai | M41: Despesa Fixa | N41: Pessoal/Utilidade | O41: Água vinculada ao pró-labore do pai | P41: Mensal
A42: 06/02/2025 | B42: Pix | C42: PIX EMITIDO OUTRA IF | D42: -616.99 | E42: funcionarios | F42: DESPESA | G42: FEV | H42: {=VLOOKUP(E42,L1:N306,2,0)} -> Despesa Fixa | I42: {=VLOOKUP(E42,L1:N306,3,0)} -> Pessoal | L42: agua serralheria
A43: 06/02/2025 | B43: Pix | C43: PIX EMITIDO OUTRA IF | D43: -92.48 | E43: funcionarios | F43: DESPESA | G43: FEV | H43: {=VLOOKUP(E43,L1:N306,2,0)} -> Despesa Fixa | I43: {=VLOOKUP(E43,L1:N306,3,0)} -> Pessoal | L43: salario funcionario | M43: Despesa Fixa | N43: Pessoal | O43: Salários da equipe | P43: Mensal
A44: 06/02/2025 | B44: 4411 | C44: CRED.TRANSF.CONTAS INTERCREDIS | D44: 900 | E44: emprestado | F44: RECEITA | G44: FEV | H44: {=VLOOKUP(E44,L1:N306,2,0)} -> Empréstimo | I44: {=VLOOKUP(E44,L1:N306,3,0)} -> Passivo | L44: celulares internet
A45: 07/02/2025 | B45: 3455320 | C45: CRÉD.LIQUIDAÇÃO COBRANÇA | D45: 8785 | E45: venda | F45: RECEITA | G45: FEV | H45: Receita | I45: VENDA | L45: taxa conta
A46: 07/02/2025 | B46: Pix | C46: PIX RECEBIDO - OUTRA IF - MESMA TIT. | D46: 19 | E46: venda | F46: RECEITA | G46: FEV | H46: Receita | I46: VENDA | L46: seguro casa
A47: 07/02/2025 | B47: 38438101 | C47: DÉB.TIT.COMPE EFETIVADO | D47: -300 | E47: fornecedor | F47: DESPESA | G47: FEV | H47: {=VLOOKUP(E47,L1:N306,2,0)} -> Despesa Variável | I47: {=VLOOKUP(E47,L1:N306,3,0)} -> Custo Direto | L47: emprestado, salario pai e fornecedor | M47: Diversos | N47: Agrupamento | O47: Mistura de empréstimo, pró-labore e fornecedores | P47: Reavaliar
A48: 07/02/2025 | B48: Pix | C48: PIX EMITIDO OUTRA IF | D48: -27.8 | E48: fornecedor | F48: DESPESA | G48: FEV | H48: {=VLOOKUP(E48,L1:N306,2,0)} -> Despesa Variável | I48: {=VLOOKUP(E48,L1:N306,3,0)} -> Custo Direto
A49: 07/02/2025 | B49: Pix | C49: PIX RECEBIDO - OUTRA IF | D49: 240 | E49: venda | F49: RECEITA | G49: FEV | H49: Receita | I49: VENDA
A50: 07/02/2025 | B50: Pix | C50: PIX EMITIDO OUTRA IF | D50: -1019 | E50: fornecedor | F50: DESPESA | G50: FEV | H50: {=VLOOKUP(E50,L1:N306,2,0)} -> Despesa Variável | I50: {=VLOOKUP(E50,L1:N306,3,0)} -> Custo Direto
A51: 07/02/2025 | B51: Pix | C51: ESTORNO PIX EMITIDO | D51: 1019 | E51: ESTORNO E DEVOLUÇÃO | F51: RECEITA | G51: FEV | H51: Receita | I51: Receita
A52: 07/02/2025 | B52: Pix | C52: PIX RECEBIDO - OUTRA IF | D52: 670 | E52: venda | F52: RECEITA | G52: FEV | H52: Receita | I52: VENDA
A53: 07/02/2025 | B53: Pix | C53: PIX RECEBIDO - OUTRA IF | D53: 290 | E53: venda | F53: RECEITA | G53: FEV | H53: Receita | I53: VENDA
A54: 07/02/2025 | B54: 3459935 | C54: TARIFA COBRANÇA | D54: -2.6 | E54: taxa de boleto | F54: DESPESA | G54: FEV | H54: {=VLOOKUP(E54,L1:N306,2,0)} -> Despesa Variável | I54: {=VLOOKUP(E54,L1:N306,3,0)} -> Financeira
A55: 10/02/2025 | B55: Pix | C55: PIX RECEBIDO - OUTRA IF | D55: 110 | E55: venda | F55: RECEITA | G55: FEV | H55: Receita | I55: VENDA
A56: 10/02/2025 | B56: Pix | C56: PIX EMITIDO OUTRA IF | D56: -1019 | E56: fornecedor | F56: DESPESA | G56: FEV | H56: {=VLOOKUP(E56,L1:N306,2,0)} -> Despesa Variável | I56: {=VLOOKUP(E56,L1:N306,3,0)} -> Custo Direto
A57: 11/02/2025 | B57: 34 | C57: DEP.DINHEIRO | D57: 2900 | E57: venda | F57: RECEITA | G57: FEV | H57: Receita | I57: VENDA
A58: 11/02/2025 | B58: Pix | C58: PIX RECEBIDO - OUTRA IF | D58: 65 | E58: venda | F58: RECEITA | G58: FEV | H58: Receita | I58: VENDA
A59: 11/02/2025 | B59: Pix | C59: PIX RECEBIDO - OUTRA IF | D59: 250 | E59: venda | F59: RECEITA | G59: FEV | H59: Receita | I59: VENDA
A60: 11/02/2025 | B60: 38534856 | C60: DÉB.CONV.EN.ELÉTRICA E GÁS | D60: -249.81 | E60: CPFL | F60: DESPESA | G60: FEV | H60: {=VLOOKUP(E60,L1:N306,2,0)} -> Despesa Variável | I60: {=VLOOKUP(E60,L1:N306,3,0)} -> Energia
A61: 11/02/2025 | B61: 38534922 | C61: DÉB.TRANSF.CONTAS DIF.TIT. INTERCREDIS | D61: -44 | E61: fornecedor | F61: DESPESA | G61: FEV | H61: {=VLOOKUP(E61,L1:N306,2,0)} -> Despesa Variável | I61: {=VLOOKUP(E61,L1:N306,3,0)} -> Custo Direto
A62: 12/02/2025 | B62: Pix | C62: PIX RECEBIDO - OUTRA IF | D62: 810 | E62: venda | F62: RECEITA | G62: FEV | H62: Receita | I62: VENDA
A63: 12/02/2025 | B63: Pix | C63: PIX RECEBIDO - OUTRA IF | D63: 21705 | E63: venda | F63: RECEITA | G63: FEV | H63: Receita | I63: VENDA
A64: 12/02/2025 | B64: Pix | C64: PIX RECEBIDO - OUTRA IF - MESMA TIT. | D64: 63 | E64: venda | F64: RECEITA | G64: FEV | H64: Receita | I64: VENDA
A65: 12/02/2025 | B65: 38556899 | C65: DÉB.TIT.COMPE EFETIVADO | D65: -17742.02 | E65: fornecedor | F65: DESPESA | G65: FEV | H65: {=VLOOKUP(E65,L1:N306,2,0)} -> Despesa Variável | I65: {=VLOOKUP(E65,L1:N306,3,0)} -> Custo Direto
A66: 12/02/2025 | B66: 38557062 | C66: DÉB.TRANSF.CONTAS DIF.TIT. INTERCREDIS | D66: -12.8 | E66: fornecedor | F66: DESPESA | G66: FEV | H66: {=VLOOKUP(E66,L1:N306,2,0)} -> Despesa Variável | I66: {=VLOOKUP(E66,L1:N306,3,0)} -> Custo Direto
A67: 12/02/2025 | B67: 38557161 | C67: DÉB.TRANSF.CONTAS DIF.TIT. INTERCREDIS | D67: -350 | E67: emprestado | F67: DESPESA | G67: FEV | H67: {=VLOOKUP(E67,L1:N306,2,0)} -> Empréstimo | I67: {=VLOOKUP(E67,L1:N306,3,0)} -> Passivo | J67: explicar para Jussara
A68: 12/02/2025 | B68: Pix | C68: PIX RECEBIDO - OUTRA IF | D68: 180 | E68: venda | F68: RECEITA | G68: FEV | H68: Receita | I68: VENDA
A69: 12/02/2025 | B69: 1869888 | C69: CRÉD.EMPRÉSTIMO | D69: 45000 | E69: emprestado | F69: RECEITA | G69: FEV | H69: {=VLOOKUP(E69,L1:N306,2,0)} -> Empréstimo | I69: {=VLOOKUP(E69,L1:N306,3,0)} -> Passivo
A70: 12/02/2025 | B70: 38558623 | C70: DÉB.TRANSF.CONTAS DIF.TIT. INTERCREDIS | D70: -45000 | E70: emprestado | F70: DESPESA | G70: FEV | H70: {=VLOOKUP(E70,L1:N306,2,0)} -> Empréstimo | I70: {=VLOOKUP(E70,L1:N306,3,0)} -> Passivo | J70: explicar para Jussara
A71: 12/02/2025 | B71: Pix | C71: PIX EMITIDO OUTRA IF | D71: -96 | E71: prolabore | F71: DESPESA | G71: FEV | H71: {=VLOOKUP(E71,L1:N306,2,0)} | I71: salario pai | J71: explicar para Jussara
A72: 12/02/2025 | B72: Pix | C72: PIX RECEBIDO - OUTRA IF | D72: 13200 | E72: venda | F72: RECEITA | G72: FEV | H72: Receita | I72: VENDA
A73: 12/02/2025 | B73: 3472002 | C73: TARIFA COBRANÇA | D73: -2.6 | E73: taxa de boleto | F73: DESPESA | G73: FEV | H73: {=VLOOKUP(E73,L1:N306,2,0)} -> Despesa Variável | I73: {=VLOOKUP(E73,L1:N306,3,0)} -> Financeira
A74: 13/02/2025 | B74: Pix | C74: PIX EMITIDO OUTRA IF | D74: -750 | E74: fornecedor | F74: DESPESA | G74: FEV | H74: {=VLOOKUP(E74,L1:N306,2,0)} -> Despesa Variável | I74: {=VLOOKUP(E74,L1:N306,3,0)} -> Custo Direto
A75: 13/02/2025 | B75: Pix | C75: PIX EMITIDO OUTRA IF | D75: -10000 | E75: APLICAÇÃO | F75: DESPESA | G75: FEV | H75: {=VLOOKUP(E75,L1:N306,2,0)} | I75: guardei na caixinha | J75: explicar para Jussara
A76: 13/02/2025 | B76: Pix | C76: PIX RECEBIDO - OUTRA IF | D76: 1900 | E76: venda | F76: RECEITA | G76: FEV | H76: Receita | I76: VENDA
A77: 13/02/2025 | B77: Pix | C77: PIX EMITIDO OUTRA IF | D77: -21 | E77: prolabore | F77: DESPESA | G77: FEV | H77: {=VLOOKUP(E77,L1:N306,2,0)} | I77: salario pai | J77: explicar para Jussara
A78: 14/02/2025 | B78: Pix | C78: PIX EMITIDO OUTRA IF | D78: -220 | E78: prolabore | F78: DESPESA | G78: FEV | H78: {=VLOOKUP(E78,L1:N306,2,0)} | I78: salario pai | J78: explicar para Jussara
A79: 14/02/2025 | B79: Pix | C79: PIX RECEBIDO - OUTRA IF | D79: 620 | E79: venda | F79: RECEITA | G79: FEV | H79: Receita | I79: VENDA
A80: 14/02/2025 | B80: Pix | C80: PIX RECEBIDO - OUTRA IF | D80: 2305 | E80: venda | F80: RECEITA | G80: FEV | H80: Receita | I80: VENDA
A81: 14/02/2025 | B81: Pix | C81: PIX RECEBIDO - OUTRA IF | D81: 2140 | E81: venda | F81: RECEITA | G81: FEV | H81: Receita | I81: VENDA
A82: 14/02/2025 | B82: Pix | C82: PIX EMITIDO OUTRA IF | D82: -2263.29 | E82: fornecedor | F82: DESPESA | G82: FEV | H82: {=VLOOKUP(E82,L1:N306,2,0)} -> Despesa Variável | I82: {=VLOOKUP(E82,L1:N306,3,0)} -> Custo Direto
A83: 14/02/2025 | B83: Pix | C83: PIX RECEBIDO - OUTRA IF | D83: 100 | E83: venda | F83: RECEITA | G83: FEV | H83: Receita | I83: VENDA
A84: 14/02/2025 | B84: Pix | C84: PIX RECEBIDO - OUTRA IF | D84: 500 | E84: venda | F84: RECEITA | G84: FEV | H84: Receita | I84: VENDA
A85: 17/02/2025 | B85: 3188 | C85: CRED.TRANSF.CONTAS INTERCREDIS | D85: 25 | E85: emprestado | F85: RECEITA | G85: FEV | H85: {=VLOOKUP(E85,L1:N306,2,0)} -> Empréstimo | I85: {=VLOOKUP(E85,L1:N306,3,0)} -> Passivo
A86: 17/02/2025 | B86: Pix | C86: PIX RECEBIDO - OUTRA IF | D86: 175 | E86: venda | F86: RECEITA | G86: FEV | H86: Receita | I86: VENDA
A87: 17/02/2025 | B87: 38657517 | C87: DÉB.CONV.TRIBUTOS FEDERAIS - RFB | D87: -6423.76 | E87: contabilidade | F87: DESPESA | G87: FEV | H87: {=VLOOKUP(E87,L1:N306,2,0)} -> Despesa Fixa | I87: {=VLOOKUP(E87,L1:N306,3,0)} -> Contábil | J87: explicar para Jussara
A88: 17/02/2025 | B88: 38657590 | C88: DÉB.CONV.TRIBUTOS FEDERAIS - RFB | D88: -1198.79 | E88: contabilidade | F88: DESPESA | G88: FEV | H88: {=VLOOKUP(E88,L1:N306,2,0)} -> Despesa Fixa | I88: {=VLOOKUP(E88,L1:N306,3,0)} -> Contábil | J88: explicar para Jussara
A89: 17/02/2025 | B89: Pix | C89: PIX EMITIDO OUTRA IF | D89: -1322.85 | E89: contabilidade | F89: DESPESA | G89: FEV | H89: {=VLOOKUP(E89,L1:N306,2,0)} -> Despesa Fixa | I89: {=VLOOKUP(E89,L1:N306,3,0)} -> Contábil | J89: explicar para Jussara
A90: 18/02/2025 | B90: Pix | C90: PIX RECEBIDO - OUTRA IF - MESMA TIT. | D90: 390 | E90: venda | F90: RECEITA | G90: FEV | H90: Receita | I90: VENDA
A91: 18/02/2025 | B91: 4411 | C91: CRED.TRANSF.CONTAS INTERCREDIS | D91: 350 | E91: emprestado | F91: RECEITA | G91: FEV | H91: {=VLOOKUP(E91,L1:N306,2,0)} -> Empréstimo | I91: {=VLOOKUP(E91,L1:N306,3,0)} -> Passivo
A92: 19/02/2025 | B92: 38683751 | C92: DÉB.TRANSF.CONTAS DIF.TIT. INTERCREDIS | D92: -39 | E92: fornecedor | F92: DESPESA | G92: FEV | H92: {=VLOOKUP(E92,L1:N306,2,0)} -> Despesa Variável | I92: {=VLOOKUP(E92,L1:N306,3,0)} -> Custo Direto
A93: 19/02/2025 | B93: Pix | C93: PIX RECEBIDO - OUTRA IF | D93: 1000 | E93: venda | F93: RECEITA | G93: FEV | H93: Receita | I93: VENDA
A94: 19/02/2025 | B94: Pix | C94: PIX EMITIDO OUTRA IF | D94: -504.37 | E94: IPTU casa/serralheria | F94: DESPESA | G94: FEV | H94: {=VLOOKUP(E94,L1:N306,2,0)} -> Despesa Fixa | I94: {=VLOOKUP(E94,L1:N306,3,0)} -> Tributária
A95: 19/02/2025 | B95: Pix | C95: PIX EMITIDO OUTRA IF | D95: -215 | E95: fornecedor | F95: DESPESA | G95: FEV | H95: {=VLOOKUP(E95,L1:N306,2,0)} -> Despesa Variável | I95: {=VLOOKUP(E95,L1:N306,3,0)} -> Custo Direto
A96: 19/02/2025 | B96: 38696576 | C96: DÉB.TRANSF.CONTAS DIF.TIT. INTERCREDIS | D96: -1300 | E96: prolabore | F96: DESPESA | G96: FEV | H96: {=VLOOKUP(E96,L1:N306,2,0)} | I96: salario pai | J96: explicar para Jussara
A97: 19/02/2025 | B97: Pix | C97: PIX EMITIDO OUTRA IF | D97: -184.5 | E97: fornecedor | F97: DESPESA | G97: FEV | H97: {=VLOOKUP(E97,L1:N306,2,0)} -> Despesa Variável | I97: {=VLOOKUP(E97,L1:N306,3,0)} -> Custo Direto
A98: 19/02/2025 | B98: Pix | C98: PIX EMITIDO OUTRA IF | D98: -100 | E98: prolabore | F98: DESPESA | G98: FEV | H98: {=VLOOKUP(E98,L1:N306,2,0)} | I98: salario pai | J98: explicar para Jussara
A99: 20/02/2025 | B99: 3488730 | C99: CRÉD.LIQUIDAÇÃO COBRANÇA | D99: 243.03 | E99: venda | F99: RECEITA | G99: FEV | H99: Receita | I99: VENDA
A100: 20/02/2025 | B100: Pix | C100: PIX RECEBIDO - OUTRA IF | D100: 56 | E100: venda | F100: RECEITA | G100: FEV | H100: Receita | I100: VENDA
...

Sheet Precificação
B7: PREÇO DE SERVIÇO | O7: PREÇO POR MARKUP | AB7: PREÇO DE INDUSTRIA E PRODUTO
O17: CUSTO FIXO | AB17: CUSTO VARIAVEL

Sheet MARKUP
B4: VALOR DE VENDA DO PRODUTO | C4: MARKUP | D4: 0 | E4: 150 | H4: Obs. Onde a célula estiver na cor cinza, tem fórmula
B6: CUSTOS E DESPESAS VARIÁVEIS | C6: % do preço | D6: R$ | E6: TOTAL | F6: % | I6: TOTAL
B7: IMPOSTOS E DESP. VENDA MÉDIO CATEGORIA | E7: {=SUM(E8:E17)} -> 45 | F7: {=SUM(F8:F17)} -> 0.3 | H7: COMPROMISSO FIXO MENSAL | I7: {=SUM(I8:I21)} -> 32450
B8: {='CUSTO VARIAVEL'!B7} -> 1. Impostos % | C8: {='CUSTO VARIAVEL'!C7} -> 0.22 | E8: {=C8*$E$4+D8} -> 33 | F8: {=E8/$E$4} -> 0.22 | H8: {='CUSTO FIXO'!B7} -> 1. Aluguéis | I8: {='CUSTO FIXO'!C7} -> 4000
B9: {='CUSTO VARIAVEL'!B8} -> 2. Taxa Cartão | C9: {='CUSTO VARIAVEL'!C8} -> 0.05 | E9: {=C9*$E$4+D9} -> 7.5 | F9: {=E9/$E$4} -> 0.05 | H9: {='CUSTO FIXO'!B8} -> 2. Salários e Benefícios Funcionários | I9: {='CUSTO FIXO'!C8} -> 8000
B10: {='CUSTO VARIAVEL'!B9} -> 3. Comissões | C10: {='CUSTO VARIAVEL'!C9} -> 0.03 | E10: {=C10*$E$4+D10} -> 4.5 | F10: {=E10/$E$4} -> 0.03 | H10: {='CUSTO FIXO'!B9} -> 3. Pró Labore e Benefícios Sócios | I10: {='CUSTO FIXO'!C9} -> 10000
B11: {='CUSTO VARIAVEL'!B10} -> 4. Inadimplencia | C11: {='CUSTO VARIAVEL'!C10} -> 0 | E11: {=C11*$E$4+D11} -> 0 | F11: {=E11/$E$4} -> 0 | H11: {='CUSTO FIXO'!B10} -> 4. Despesas de Viagem | I11: {='CUSTO FIXO'!C10} -> 2000
B12: {='CUSTO VARIAVEL'!B11} -> 5. Taxa boleto | C12: {='CUSTO VARIAVEL'!C11} -> 0 | E12: {=C12*$E$4+D12} -> 0 | F12: {=E12/$E$4} -> 0 | H12: {='CUSTO FIXO'!B11} -> 5. Contabilidade | I12: {='CUSTO FIXO'!C11} -> 1800
B13: {='CUSTO VARIAVEL'!B12} -> 6. Perda/Extravio/Não Receb. | C13: {='CUSTO VARIAVEL'!C12} -> 0 | E13: {=C13*$E$4+D13} -> 0 | F13: {=E13/$E$4} -> 0 | H13: {='CUSTO FIXO'!B12} -> 6. Luz/Água/Gás/Telefone | I13: {='CUSTO FIXO'!C12} -> 800
B14: {='CUSTO VARIAVEL'!B13} -> 7. Outro | C14: {='CUSTO VARIAVEL'!C13} -> 0 | E14: {=C14*$E$4+D14} -> 0 | F14: {=E14/$E$4} -> 0 | H14: {='CUSTO FIXO'!B13} -> 7. Manutenção, Segurança e Limpeza | I14: {='CUSTO FIXO'!C13} -> 1500
B15: {='CUSTO VARIAVEL'!B14} -> 8. Outro | C15: {='CUSTO VARIAVEL'!C14} -> 0 | E15: {=C15*$E$4+D15} -> 0 | F15: {=E15/$E$4} -> 0 | H15: {='CUSTO FIXO'!B14} -> 8. Carros e Seguros | I15: {='CUSTO FIXO'!C14} -> 0
F16: {=E16/$E$4} -> 0 | H16: {='CUSTO FIXO'!B15} -> 9. Desp. Financeiras (juros/taxas/tarifas) | I16: {='CUSTO FIXO'!C15} -> 350
F17: {=E17/$E$4} -> 0 | H17: {='CUSTO FIXO'!B16} -> 10. Desp. Administrativas | I17: {='CUSTO FIXO'!C16} -> 0
B18: CUSTO UNITÁRIO MÉDIO CATEGORIA | E18: {=SUM(E19:E30)} -> 45 | F18: {=SUM(F19:F30)} -> 0.3 | H18: {='CUSTO FIXO'!B17} -> Material no Geral | I18: {='CUSTO FIXO'!C17} -> 4000
B19: {='CUSTO VARIAVEL'!B18} -> 11. Valor de Compra | C19: {='CUSTO VARIAVEL'!C18} -> 0 | D19: {='CUSTO VARIAVEL'!D18} -> 45 | E19: {=D19} -> 45 | F19: {=E19/$E$4} -> 0.3 | H19: {='CUSTO FIXO'!B18} -> 0 | I19: {='CUSTO FIXO'!C18} -> 0
B20: {='CUSTO VARIAVEL'!B19} -> 12. Equipamentos | C20: {='CUSTO VARIAVEL'!C19} -> 0 | D20: {='CUSTO VARIAVEL'!D19} -> 0 | E20: 0 | F20: {=E20/$E$4} -> 0 | H20: {='CUSTO FIXO'!B19} -> 0 | I20: {='CUSTO FIXO'!C19} -> 0
B21: {='CUSTO VARIAVEL'!B20} -> 13. Materiais | C21: {='CUSTO VARIAVEL'!C20} -> 0 | D21: {='CUSTO VARIAVEL'!D20} -> 0 | E21: {=C21*$E$4+D21} -> 0 | F21: {=E21/$E$4} -> 0 | H21: {='CUSTO FIXO'!B20} -> 0 | I21: {='CUSTO FIXO'!C20} -> 0
B22: {='CUSTO VARIAVEL'!B21} -> 14. Insumos | C22: {='CUSTO VARIAVEL'!C21} -> 0 | D22: {='CUSTO VARIAVEL'!D21} -> 0 | E22: {=C22*$E$4+D22} -> 0 | F22: {=E22/$E$4} -> 0
B23: {='CUSTO VARIAVEL'!B22} -> 15. Outro | C23: {='CUSTO VARIAVEL'!C22} -> 0 | D23: {='CUSTO VARIAVEL'!D22} -> 0 | E23: {=C23*$E$4+D23} -> 0 | F23: {=E23/$E$4} -> 0 | H23: PONTO DE EQUILIBRIO DA VENDA | I23: {=I7/C33} -> 81125
B24: {='CUSTO VARIAVEL'!B23} -> 16. Outro | C24: {='CUSTO VARIAVEL'!C23} -> 0 | D24: {='CUSTO VARIAVEL'!D23} -> 0 | E24: {=C24*$E$4+D24} -> 0 | F24: {=E24/$E$4} -> 0 | H24: Quantidade de vendas | I24: {=I23/E4} -> 540.83333
B25: {='CUSTO VARIAVEL'!B24} -> 17. Outro | C25: {='CUSTO VARIAVEL'!C24} -> 0 | D25: {='CUSTO VARIAVEL'!D24} -> 0 | E25: {=C25*$E$4+D25} -> 0 | F25: {=E25/$E$4} -> 0
B26: {='CUSTO VARIAVEL'!B25} -> 18. Outro | C26: {='CUSTO VARIAVEL'!C25} -> 0 | D26: {='CUSTO VARIAVEL'!D25} -> 0 | E26: {=C26*$E$4+D26} -> 0 | F26: {=E26/$E$4} -> 0 | H26: CUSTO DO PPRODUTO | I26: {=I23*F19} -> 24337.5
B27: {='CUSTO VARIAVEL'!B26} -> 19. Outro | C27: {='CUSTO VARIAVEL'!C26} -> 0 | D27: {='CUSTO VARIAVEL'!D26} -> 0 | E27: {=C27*$E$4+D27} -> 0 | F27: {=E27/$E$4} -> 0 | H27: IMPOSTOS E DESP. VENDA MÉDIO CATEGORIA | I27: {=I23*(SUM(C8:C16))} -> 24337.5
B28: {='CUSTO VARIAVEL'!B27} -> 20. Outro | C28: {='CUSTO VARIAVEL'!C27} -> 0 | D28: {='CUSTO VARIAVEL'!D27} -> 0 | E28: {=C28*$E$4+D28} -> 0 | F28: {=E28/$E$4} -> 0 | H28: CUSTO FIXO | I28: {=I7} -> 32450
B29: {='CUSTO VARIAVEL'!B28} -> 21. Outro | C29: {='CUSTO VARIAVEL'!C28} -> 0 | D29: {='CUSTO VARIAVEL'!D28} -> 0 | E29: {=C29*$E$4+D29} -> 0 | F29: {=E29/$E$4} -> 0
B30: {='CUSTO VARIAVEL'!B29} -> 22. Outros | C30: {='CUSTO VARIAVEL'!C29} -> 0 | D30: {='CUSTO VARIAVEL'!D29} -> 0 | E30: {=C30*$E$4+D30} -> 0 | F30: {=E30/$E$4} -> 0 | H30: LUCRO DA EMPRESA | I30: {=I23-I26-I27-I28} -> 0
I31: {=I30/I23} -> 0
B33: Margem de Contribuição | C33: {=E33/E4} -> 0.4 | E33: {=E4-E7-E18} -> 60 | H33: O PONTO DE EQUILIBRIO DA VENDA REPRESENTA O QUANDO VOCË PRECISA VENDER PARA PAGAR TODAS AS CONTAS FIXAS DA EMPRESA, TODO VALOR FATURADO ACIMA DESSE VALOR REPRESENTA A MARGEM DE LUCRO LIQUIDA.
E34: {=IF(E33<0,"NEGATIVA, reduzir custos ou aumentar preço",IF(E33=0,"ARRISCADA, avaliar estratégia ou reduzir custos",IF(C33<0.05,"BAIXA, avaliar estratégia ou reduzir custos","POSITIVA")))} -> POSITIVA

Sheet INDUSTRIA
B4: VALOR DE VENDA DO PRODUTO | E4: 150 | H4: Obs. Onde a célula estiver na cor cinza, tem fórmula
B6: CUSTOS E DESPESAS VARIÁVEIS | C6: % do preço | D6: R$ | E6: TOTAL | F6: % | I6: TOTAL
B7: IMPOSTOS E DESP. VENDA MÉDIO CATEGORIA | E7: {=SUM(E8:E17)} -> 45 | F7: {=SUM(F8:F17)} -> 0.3 | H7: COMPROMISSO FIXO MENSAL | I7: {=SUM(I8:I23)} -> 32450
B8: {='CUSTO VARIAVEL'!B7} -> 1. Impostos % | C8: {='CUSTO VARIAVEL'!C7} -> 0.22 | E8: {=C8*$E$4+D8} -> 33 | F8: {=E8/$E$4} -> 0.22 | H8: {='CUSTO FIXO'!B7} -> 1. Aluguéis | I8: {='CUSTO FIXO'!C7} -> 4000
B9: {='CUSTO VARIAVEL'!B8} -> 2. Taxa Cartão | C9: {='CUSTO VARIAVEL'!C8} -> 0.05 | E9: {=C9*$E$4+D9} -> 7.5 | F9: {=E9/$E$4} -> 0.05 | H9: {='CUSTO FIXO'!B8} -> 2. Salários e Benefícios Funcionários | I9: {='CUSTO FIXO'!C8} -> 8000
B10: {='CUSTO VARIAVEL'!B9} -> 3. Comissões | C10: {='CUSTO VARIAVEL'!C9} -> 0.03 | E10: {=C10*$E$4+D10} -> 4.5 | F10: {=E10/$E$4} -> 0.03 | H10: {='CUSTO FIXO'!B9} -> 3. Pró Labore e Benefícios Sócios | I10: {='CUSTO FIXO'!C9} -> 10000
B11: {='CUSTO VARIAVEL'!B10} -> 4. Inadimplencia | C11: {='CUSTO VARIAVEL'!C10} -> 0 | E11: {=C11*$E$4+D11} -> 0 | F11: {=E11/$E$4} -> 0 | H11: {='CUSTO FIXO'!B10} -> 4. Despesas de Viagem | I11: {='CUSTO FIXO'!C10} -> 2000
B12: {='CUSTO VARIAVEL'!B11} -> 5. Taxa boleto | C12: {='CUSTO VARIAVEL'!C11} -> 0 | E12: {=C12*$E$4+D12} -> 0 | F12: {=E12/$E$4} -> 0 | H12: {='CUSTO FIXO'!B11} -> 5. Contabilidade | I12: {='CUSTO FIXO'!C11} -> 1800
B13: {='CUSTO VARIAVEL'!B12} -> 6. Perda/Extravio/Não Receb. | C13: {='CUSTO VARIAVEL'!C12} -> 0 | E13: {=C13*$E$4+D13} -> 0 | F13: {=E13/$E$4} -> 0 | H13: {='CUSTO FIXO'!B12} -> 6. Luz/Água/Gás/Telefone | I13: {='CUSTO FIXO'!C12} -> 800
B14: {='CUSTO VARIAVEL'!B13} -> 7. Outro | C14: {='CUSTO VARIAVEL'!C13} -> 0 | E14: {=C14*$E$4+D14} -> 0 | F14: {=E14/$E$4} -> 0 | H14: {='CUSTO FIXO'!B13} -> 7. Manutenção, Segurança e Limpeza | I14: {='CUSTO FIXO'!C13} -> 1500
B15: {='CUSTO VARIAVEL'!B14} -> 8. Outro | C15: {='CUSTO VARIAVEL'!C14} -> 0 | E15: {=C15*$E$4+D15} -> 0 | F15: {=E15/$E$4} -> 0 | H15: {='CUSTO FIXO'!B14} -> 8. Carros e Seguros | I15: {='CUSTO FIXO'!C14} -> 0
B16: {='CUSTO VARIAVEL'!B15} -> 9. Outro | C16: {='CUSTO VARIAVEL'!C15} -> 0 | F16: {=E16/$E$4} -> 0 | H16: {='CUSTO FIXO'!B15} -> 9. Desp. Financeiras (juros/taxas/tarifas) | I16: {='CUSTO FIXO'!C15} -> 350
F17: {=E17/$E$4} -> 0 | H17: {='CUSTO FIXO'!B16} -> 10. Desp. Administrativas | I17: {='CUSTO FIXO'!C16} -> 0
B18: CUSTO UNITÁRIO MÉDIO CATEGORIA | E18: {=SUM(E19:E30)} -> 45 | F18: {=SUM(F19:F30)} -> 0.3 | H18: {='CUSTO FIXO'!B17} -> Material no Geral | I18: {='CUSTO FIXO'!C17} -> 4000
B19: {='CUSTO VARIAVEL'!B18} -> 11. Valor de Compra | C19: {='CUSTO VARIAVEL'!C18} -> 0 | D19: {='CUSTO VARIAVEL'!D18} -> 45 | E19: {=D19} -> 45 | F19: {=E19/$E$4} -> 0.3 | H19: {='CUSTO FIXO'!B18} -> 0 | I19: {='CUSTO FIXO'!C18} -> 0
B20: {='CUSTO VARIAVEL'!B19} -> 12. Equipamentos | C20: {='CUSTO VARIAVEL'!C19} -> 0 | D20: {='CUSTO VARIAVEL'!D19} -> 0 | E20: 0 | F20: {=E20/$E$4} -> 0 | H20: {='CUSTO FIXO'!B19} -> 0 | I20: {='CUSTO FIXO'!C19} -> 0
B21: {='CUSTO VARIAVEL'!B20} -> 13. Materiais | C21: {='CUSTO VARIAVEL'!C20} -> 0 | D21: {='CUSTO VARIAVEL'!D20} -> 0 | E21: {=C21*$E$4+D21} -> 0 | F21: {=E21/$E$4} -> 0 | H21: {='CUSTO FIXO'!B20} -> 0 | I21: {='CUSTO FIXO'!C20} -> 0
B22: {='CUSTO VARIAVEL'!B21} -> 14. Insumos | C22: {='CUSTO VARIAVEL'!C21} -> 0 | D22: {='CUSTO VARIAVEL'!D21} -> 0 | E22: {=C22*$E$4+D22} -> 0 | F22: {=E22/$E$4} -> 0 | H22: {='CUSTO FIXO'!B21} -> 0 | I22: {='CUSTO FIXO'!C21} -> 0
B23: {='CUSTO VARIAVEL'!B22} -> 15. Outro | C23: {='CUSTO VARIAVEL'!C22} -> 0 | D23: {='CUSTO VARIAVEL'!D22} -> 0 | E23: {=C23*$E$4+D23} -> 0 | F23: {=E23/$E$4} -> 0 | H23: {='CUSTO FIXO'!B22} -> 0 | I23: {='CUSTO FIXO'!C22} -> 0
B24: {='CUSTO VARIAVEL'!B23} -> 16. Outro | C24: {='CUSTO VARIAVEL'!C23} -> 0 | D24: {='CUSTO VARIAVEL'!D23} -> 0 | E24: {=C24*$E$4+D24} -> 0 | F24: {=E24/$E$4} -> 0
B25: {='CUSTO VARIAVEL'!B24} -> 17. Outro | C25: {='CUSTO VARIAVEL'!C24} -> 0 | D25: {='CUSTO VARIAVEL'!D24} -> 0 | E25: {=C25*$E$4+D25} -> 0 | F25: {=E25/$E$4} -> 0 | H25: CAPACIDADE DE PRODUÇÃO | I25: 3000
B26: {='CUSTO VARIAVEL'!B25} -> 18. Outro | C26: {='CUSTO VARIAVEL'!C25} -> 0 | D26: {='CUSTO VARIAVEL'!D25} -> 0 | E26: {=C26*$E$4+D26} -> 0 | F26: {=E26/$E$4} -> 0
B27: {='CUSTO VARIAVEL'!B26} -> 19. Outro | C27: {='CUSTO VARIAVEL'!C26} -> 0 | D27: {='CUSTO VARIAVEL'!D26} -> 0 | E27: {=C27*$E$4+D27} -> 0 | F27: {=E27/$E$4} -> 0 | H27: CUSTO INDIRETO POR PRODUTO | I27: {=I7/I25} -> 10.816667
B28: {='CUSTO VARIAVEL'!B27} -> 20. Outro | C28: {='CUSTO VARIAVEL'!C27} -> 0 | D28: {='CUSTO VARIAVEL'!D27} -> 0 | E28: {=C28*$E$4+D28} -> 0 | F28: {=E28/$E$4} -> 0
B29: {='CUSTO VARIAVEL'!B28} -> 21. Outro | C29: {='CUSTO VARIAVEL'!C28} -> 0 | D29: {='CUSTO VARIAVEL'!D28} -> 0 | E29: {=C29*$E$4+D29} -> 0 | F29: {=E29/$E$4} -> 0 | H29: VALOR MÍNINO DO ORÇAMENTO | I29: {=E7+E18+I27} -> 100.81667
B30: {='CUSTO VARIAVEL'!B29} -> 22. Outros | C30: {='CUSTO VARIAVEL'!C29} -> 0 | D30: {='CUSTO VARIAVEL'!D29} -> 0 | E30: {=C30*$E$4+D30} -> 0 | F30: {=E30/$E$4} -> 0
H32: PONTO DE EQUILIBRIO DA VENDA | I32: {=I7/C36} -> 81125
B33: MARGEM DE LUCRO | C33: {=E33/E4} -> 0.32788889 | E33: {=E4-E7-E18-I27} -> 49.183333 | H33: Quantidade de vendas | I33: {=I32/E4} -> 540.83333
E34: {=IF(E33<0,"NEGATIVA, reduzir custos ou aumentar preço",IF(E33=0,"ARRISCADA, avaliar estratégia ou reduzir custos",IF(C33<0.05,"BAIXA, avaliar estratégia ou reduzir custos","POSITIVA")))} -> POSITIVA
H35: CUSTO DO PPRODUTO | I35: {=I32*F19} -> 24337.5
B36: MARGEM DE CONTRIBUIÇÃO | C36: {=1-(F7+F18)} -> 0.4 | H36: IMPOSTOS E DESP. VENDA MÉDIO CATEGORIA | I36: {=I32*(SUM(C8:C16))} -> 24337.5
H37: CUSTO FIXO | I37: {=I7} -> 32450
H39: LUCRO DA EMPRESA | I39: {=I32-I35-I36-I37} -> 0
I40: {=I39/I32} -> 0
H42: O PONTO DE EQUILIBRIO DA VENDA REPRESENTA O QUANDO VOCË PRECISA VENDER PARA PAGAR TODAS AS CONTAS FIXAS DA EMPRESA, TODO VALOR FATURADO ACIMA DESSE VALOR REPRESENTA A MARGEM DE LUCRO LIQUIDA.

Sheet TABELA DE PREÇOS
B5: COMPROMISSO FIXO MENSAL | C5: QUANTIDADE DE HORAS por mês | D5: TOTAL DE HORAS subtraindo 20% de faltas, atrasos e ociosidade | E5: CUSTO DA HORA | F5: CADEIRAS
B6: {='CUSTO FIXO'!C6} -> 32450 | C6: {=C7*F6} -> 160 | D6: {=C6-(C6*0.2)} -> 128 | E6: {=B6/D6} -> 253.51562 | F6: 1 | L6: ALTERAR AS CELULAS AMARELAS
C7: 160 | D7: horas
H9: 0.03 | I9: 0.12 | J9: 0.1
B10: PROCEDIMENTO | C10: MINUTOS | D10: VALOR A COBRAR | E10: QUANTIDADE DE HORAS | F10: CUSTO TOTAL DE HORAS | G10: VALOR MÍNINO DO ORÇAMENTO | H10: 2. Taxa Cartão | I10: IMPOSTO | J10: Material | K10: DENTISTA | L10: Laboratório | M10: LUCRO | N10: %
B12: DENTÍSTICA
B13: Raspagem | C13: 60 | D13: 450 | E13: 1 | F13: {=$E$6*E13} -> 253.51562 | G13: {=H13+I13+K13+F13+J13+L13} -> 321.01562 | H13: {=D13*$H$9} -> 13.5 | I13: {=$I$9*D13} -> 54 | J13: 0 | M13: {=D13-K13-I13-H13-F13-J13-L13} -> 128.98438 | N13: {=M13/D13} -> 0.28663194 | O13: 30% de Lucro
B14: Faceta Estética em Resina Composta Foto | C14: 90 | D14: 600 | E14: {=C14/60} -> 1.5 | F14: {=$E$6*E14} -> 380.27344 | G14: {=H14+I14+K14+F14+J14+L14} -> 530.27344 | H14: {=D14*$H$9} -> 18 | I14: {=$I$9*D14} -> 72 | J14: {=$J$9*D14} -> 60 | M14: {=D14-K14-I14-H14-F14-J14-L14} -> 69.726562 | N14: {=M14/D14} -> 0.11621094
B15: Fechamento de Diastema por Dente | C15: 60 | D15: 400 | E15: {=C15/60} -> 1 | F15: {=$E$6*E15} -> 253.51562 | G15: {=H15+I15+K15+F15+J15+L15} -> 353.51562 | H15: {=D15*$H$9} -> 12 | I15: {=$I$9*D15} -> 48 | J15: {=$J$9*D15} -> 40 | M15: {=D15-K15-I15-H15-F15-J15-L15} -> 46.484375 | N15: {=M15/D15} -> 0.11621094
B16: Reanatomização | C16: 60 | D16: 650 | E16: {=C16/60} -> 1 | F16: {=$E$6*E16} -> 253.51562 | G16: {=H16+I16+K16+F16+J16+L16} -> 416.01562 | H16: {=D16*$H$9} -> 19.5 | I16: {=$I$9*D16} -> 78 | J16: {=$J$9*D16} -> 65 | M16: {=D16-K16-I16-H16-F16-J16-L16} -> 233.98438 | N16: {=M16/D16} -> 0.35997596
B17: Rest. em Ionômero de Vidro ( definitiva ) | C17: 30 | D17: 250 | E17: {=C17/60} -> 0.5 | F17: {=$E$6*E17} -> 126.75781 | G17: {=H17+I17+K17+F17+J17+L17} -> 189.25781 | H17: {=D17*$H$9} -> 7.5 | I17: {=$I$9*D17} -> 30 | J17: {=$J$9*D17} -> 25 | M17: {=D17-K17-I17-H17-F17-J17-L17} -> 60.742188 | N17: {=M17/D17} -> 0.24296875
B18: Rest. em Resina Comp. Foto Classe I | C18: 60 | D18: 300 | E18: {=C18/60} -> 1 | F18: {=$E$6*E18} -> 253.51562 | G18: {=H18+I18+K18+F18+J18+L18} -> 328.51562 | H18: {=D18*$H$9} -> 9 | I18: {=$I$9*D18} -> 36 | J18: {=$J$9*D18} -> 30 | M18: {=D18-K18-I18-H18-F18-J18-L18} -> -28.515625 | N18: {=M18/D18} -> -0.095052083
B19: Rest. em Resina Comp. Foto Classe II 01 Face | C19: 60 | D19: 350 | E19: {=C19/60} -> 1 | F19: {=$E$6*E19} -> 253.51562 | G19: {=H19+I19+K19+F19+J19+L19} -> 341.01562 | H19: {=D19*$H$9} -> 10.5 | I19: {=$I$9*D19} -> 42 | J19: {=$J$9*D19} -> 35 | M19: {=D19-K19-I19-H19-F19-J19-L19} -> 8.984375 | N19: {=M19/D19} -> 0.025669643
B20: Rest. em Resina Comp. Foto Classe II 02 Faces | C20: 60 | D20: 400 | E20: {=C20/60} -> 1 | F20: {=$E$6*E20} -> 253.51562 | G20: {=H20+I20+K20+F20+J20+L20} -> 353.51562 | H20: {=D20*$H$9} -> 12 | I20: {=$I$9*D20} -> 48 | J20: {=$J$9*D20} -> 40 | M20: {=D20-K20-I20-H20-F20-J20-L20} -> 46.484375 | N20: {=M20/D20} -> 0.11621094
B21: Rest. em Resina Comp. Foto Classe II 03 Faces | C21: 60 | D21: 450 | E21: {=C21/60} -> 1 | F21: {=$E$6*E21} -> 253.51562 | G21: {=H21+I21+K21+F21+J21+L21} -> 366.01562 | H21: {=D21*$H$9} -> 13.5 | I21: {=$I$9*D21} -> 54 | J21: {=$J$9*D21} -> 45 | M21: {=D21-K21-I21-H21-F21-J21-L21} -> 83.984375 | N21: {=M21/D21} -> 0.18663194
B22: Rest. em Resina Comp. Foto Classe III | C22: 60 | D22: 350 | E22: {=C22/60} -> 1 | F22: {=$E$6*E22} -> 253.51562 | G22: {=H22+I22+K22+F22+J22+L22} -> 341.01562 | H22: {=D22*$H$9} -> 10.5 | I22: {=$I$9*D22} -> 42 | J22: {=$J$9*D22} -> 35 | M22: {=D22-K22-I22-H22-F22-J22-L22} -> 8.984375 | N22: {=M22/D22} -> 0.025669643
B23: Rest. em Resina Comp. Foto Classe IV | C23: 60 | D23: 400 | E23: {=C23/60} -> 1 | F23: {=$E$6*E23} -> 253.51562 | G23: {=H23+I23+K23+F23+J23+L23} -> 353.51562 | H23: {=D23*$H$9} -> 12 | I23: {=$I$9*D23} -> 48 | J23: {=$J$9*D23} -> 40 | M23: {=D23-K23-I23-H23-F23-J23-L23} -> 46.484375 | N23: {=M23/D23} -> 0.11621094
B24: Rest. em Resina Comp. Foto Classe V | C24: 30 | D24: 300 | E24: {=C24/60} -> 0.5 | F24: {=$E$6*E24} -> 126.75781 | G24: {=H24+I24+K24+F24+J24+L24} -> 201.75781 | H24: {=D24*$H$9} -> 9 | I24: {=$I$9*D24} -> 36 | J24: {=$J$9*D24} -> 30 | M24: {=D24-K24-I24-H24-F24-J24-L24} -> 98.242188 | N24: {=M24/D24} -> 0.32747396
B25: Restauração Inlay em Resina Composta | C25: 120 | D25: 1500 | E25: {=C25/60} -> 2 | F25: {=$E$6*E25} -> 507.03125 | G25: {=H25+I25+K25+F25+J25+L25} -> 882.03125 | H25: {=D25*$H$9} -> 45 | I25: {=$I$9*D25} -> 180 | J25: {=$J$9*D25} -> 150 | M25: {=D25-K25-I25-H25-F25-J25-L25} -> 617.96875 | N25: {=M25/D25} -> 0.41197917
... B28: Selante Invasivo | C28: 30 | D28: 350 | E28: {=C28/60} -> 0.5 | F28: {=$E$6*E28} -> 126.75781 | G28: {=H28+I28+K28+F28+J28+L28} -> 214.25781 | H28: {=D28*$H$9} -> 10.5 | I28: {=$I$9*D28} -> 42 | J28: {=$J$9*D28} -> 35 | M28: {=D28-K28-I28-H28-F28-J28-L28} -> 135.74219 | N28: {=M28/D28} -> 0.38783482
B29: ENDODONTIA
B30: Retratamento Endodôntico / Necro 01 Conduto | C30: 90 | D30: 1600 | E30: {=C30/60} -> 1.5 | F30: {=$E$6*E30} -> 380.27344 | G30: {=H30+I30+K30+F30+J30+L30} -> 780.27344 | H30: {=D30*$H$9} -> 48 | I30: {=$I$9*D30} -> 192 | J30: {=$J$9*D30} -> 160 | M30: {=D30-K30-I30-H30-F30-J30-L30} -> 819.72656 | N30: {=M30/D30} -> 0.5123291
B31: Retratamento Endodôntico / Necro 02 Condutos | C31: 120 | D31: 1600 | E31: {=C31/60} -> 2 | F31: {=$E$6*E31} -> 507.03125 | G31: {=H31+I31+K31+F31+J31+L31} -> 907.03125 | H31: {=D31*$H$9} -> 48 | I31: {=$I$9*D31} -> 192 | J31: {=$J$9*D31} -> 160 | M31: {=D31-K31-I31-H31-F31-J31-L31} -> 692.96875 | N31: {=M31/D31} -> 0.43310547
B32: Retratamento Endodôntico / Necro 03 Condutos | C32: 120 | D32: 1600 | E32: {=C32/60} -> 2 | F32: {=$E$6*E32} -> 507.03125 | G32: {=H32+I32+K32+F32+J32+L32} -> 907.03125 | H32: {=D32*$H$9} -> 48 | I32: {=$I$9*D32} -> 192 | J32: {=$J$9*D32} -> 160 | M32: {=D32-K32-I32-H32-F32-J32-L32} -> 692.96875 | N32: {=M32/D32} -> 0.43310547
B33: Retratamento Endodôntico / Necro 04 Condutos | C33: 120 | D33: 1600 | E33: {=C33/60} -> 2 | F33: {=$E$6*E33} -> 507.03125 | G33: {=H33+I33+K33+F33+J33+L33} -> 907.03125 | H33: {=D33*$H$9} -> 48 | I33: {=$I$9*D33} -> 192 | J33: {=$J$9*D33} -> 160 | M33: {=D33-K33-I33-H33-F33-J33-L33} -> 692.96875 | N33: {=M33/D33} -> 0.43310547
B34: Tratamento Endodôntico 01 Conduto - Bio | C34: 90 | D34: 1600 | E34: {=C34/60} -> 1.5 | F34: {=$E$6*E34} -> 380.27344 | G34: {=H34+I34+K34+F34+J34+L34} -> 780.27344 | H34: {=D34*$H$9} -> 48 | I34: {=$I$9*D34} -> 192 | J34: {=$J$9*D34} -> 160 | M34: {=D34-K34-I34-H34-F34-J34-L34} -> 819.72656 | N34: {=M34/D34} -> 0.5123291
B35: Tratamento Endodôntico 02 Condutos - Bio | C35: 90 | D35: 1600 | E35: {=C35/60} -> 1.5 | F35: {=$E$6*E35} -> 380.27344 | G35: {=H35+I35+K35+F35+J35+L35} -> 780.27344 | H35: {=D35*$H$9} -> 48 | I35: {=$I$9*D35} -> 192 | J35: {=$J$9*D35} -> 160 | M35: {=D35-K35-I35-H35-F35-J35-L35} -> 819.72656 | N35: {=M35/D35} -> 0.5123291
B36: Tratamento Endodôntico 03 Condutos - Bio | C36: 90 | D36: 1300 | E36: {=C36/60} -> 1.5 | F36: {=$E$6*E36} -> 380.27344 | G36: {=H36+I36+K36+F36+J36+L36} -> 705.27344 | H36: {=D36*$H$9} -> 39 | I36: {=$I$9*D36} -> 156 | J36: {=$J$9*D36} -> 130 | M36: {=D36-K36-I36-H36-F36-J36-L36} -> 594.72656 | N36: {=M36/D36} -> 0.45748197
B37: Tratamento Endodôntico 04 Condutos - Bio | C37: 90 | D37: 1600 | E37: {=C37/60} -> 1.5 | F37: {=$E$6*E37} -> 380.27344 | G37: {=H37+I37+K37+F37+J37+L37} -> 780.27344 | H37: {=D37*$H$9} -> 48 | I37: {=$I$9*D37} -> 192 | J37: {=$J$9*D37} -> 160 | M37: {=D37-K37-I37-H37-F37-J37-L37} -> 819.72656 | N37: {=M37/D37} -> 0.5123291
B38: Urgência Endodôntica | C38: 30 | D38: 350 | E38: {=C38/60} -> 0.5 | F38: {=$E$6*E38} -> 126.75781 | G38: {=H38+I38+K38+F38+J38+L38} -> 214.25781 | H38: {=D38*$H$9} -> 10.5 | I38: {=$I$9*D38} -> 42 | J38: {=$J$9*D38} -> 35 | M38: {=D38-K38-I38-H38-F38-J38-L38} -> 135.74219 | N38: {=M38/D38} -> 0.38783482
B39: PERIODONTIA
B40: Acesso Cirúrgico | C40: 60 | D40: 800 | E40: {=C40/60} -> 1 | F40: {=$E$6*E40} -> 253.51562 | G40: {=H40+I40+K40+F40+J40+L40} -> 453.51562 | H40: {=D40*$H$9} -> 24 | I40: {=$I$9*D40} -> 96 | J40: {=$J$9*D40} -> 80 | M40: {=D40-K40-I40-H40-F40-J40-L40} -> 346.48438 | N40: {=M40/D40} -> 0.43310547
B41: Aumento de Coroa Clínica | C41: 90 | D41: 600 | E41: {=C41/60} -> 1.5 | F41: {=$E$6*E41} -> 380.27344 | G41: {=H41+I41+K41+F41+J41+L41} -> 530.27344 | H41: {=D41*$H$9} -> 18 | I41: {=$I$9*D41} -> 72 | J41: {=$J$9*D41} -> 60 | M41: {=D41-K41-I41-H41-F41-J41-L41} -> 69.726562 | N41: {=M41/D41} -> 0.11621094
B42: Cirurgia à Retalho | C42: 120 | D42: 1500 | E42: {=C42/60} -> 2 | F42: {=$E$6*E42} -> 507.03125 | G42: {=H42+I42+K42+F42+J42+L42} -> 882.03125 | H42: {=D42*$H$9} -> 45 | I42: {=$I$9*D42} -> 180 | J42: {=$J$9*D42} -> 150 | M42: {=D42-K42-I42-H42-F42-J42-L42} -> 617.96875 | N42: {=M42/D42} -> 0.41197917
B43: Cunha Distal | C43: 60 | D43: 600 | E43: {=C43/60} -> 1 | F43: {=$E$6*E43} -> 253.51562 | G43: {=H43+I43+K43+F43+J43+L43} -> 403.51562 | H43: {=D43*$H$9} -> 18 | I43: {=$I$9*D43} -> 72 | J43: {=$J$9*D43} -> 60 | M43: {=D43-K43-I43-H43-F43-J43-L43} -> 196.48438 | N43: {=M43/D43} -> 0.32747396
B44: Enxerto com Endogain + Bone Ceramic | C44: 60 | D44: 1600 | E44: {=C44/60} -> 1 | F44: {=$E$6*E44} -> 253.51562 | G44: {=H44+I44+K44+F44+J44+L44} -> 653.51562 | H44: {=D44*$H$9} -> 48 | I44: {=$I$9*D44} -> 192 | J44: {=$J$9*D44} -> 160 | M44: {=D44-K44-I44-H44-F44-J44-L44} -> 946.48438 | N44: {=M44/D44} -> 0.59155273
B45: Enxerto Conjuntivo Subepitelial | C45: 120 | D45: 2000 | E45: {=C45/60} -> 2 | F45: {=$E$6*E45} -> 507.03125 | G45: {=H45+I45+K45+F45+J45+L45} -> 1007.0312 | H45: {=D45*$H$9} -> 60 | I45: {=$I$9*D45} -> 240 | J45: {=$J$9*D45} -> 200 | M45: {=D45-K45-I45-H45-F45-J45-L45} -> 992.96875 | N45: {=M45/D45} -> 0.49648437
B46: Enxerto Gengival Livre | C46: 120 | D46: 2000 | E46: {=C46/60} -> 2 | F46: {=$E$6*E46} -> 507.03125 | G46: {=H46+I46+K46+F46+J46+L46} -> 1007.0312 | H46: {=D46*$H$9} -> 60 | I46: {=$I$9*D46} -> 240 | J46: {=$J$9*D46} -> 200 | M46: {=D46-K46-I46-H46-F46-J46-L46} -> 992.96875 | N46: {=M46/D46} -> 0.49648437
B47: Enxerto Gengival Pediculado (Retalho Deslizante) | C47: 120 | D47: 2000 | E47: {=C47/60} -> 2 | F47: {=$E$6*E47} -> 507.03125 | G47: {=H47+I47+K47+F47+J47+L47} -> 1007.0312 | H47: {=D47*$H$9} -> 60 | I47: {=$I$9*D47} -> 240 | J47: {=$J$9*D47} -> 200 | M47: {=D47-K47-I47-H47-F47-J47-L47} -> 992.96875 | N47: {=M47/D47} -> 0.49648437
B48: Gengivectomia | C48: 90 | D48: 1200 | E48: {=C48/60} -> 1.5 | F48: {=$E$6*E48} -> 380.27344 | G48: {=H48+I48+K48+F48+J48+L48} -> 680.27344 | H48: {=D48*$H$9} -> 36 | I48: {=$I$9*D48} -> 144 | J48: {=$J$9*D48} -> 120 | M48: {=D48-K48-I48-H48-F48-J48-L48} -> 519.72656 | N48: {=M48/D48} -> 0.43310547
B49: Imobilização Dentária por Dente | C49: 30 | D49: 0 | E49: {=C49/60} -> 0.5 | F49: {=$E$6*E49} -> 126.75781 | G49: {=H49+I49+K49+F49+J49+L49} -> 126.75781 | H49: {=D49*$H$9} -> 0 | I49: {=$I$9*D49} -> 0 | J49: {=$J$9*D49} -> 0 | M49: {=D49-K49-I49-H49-F49-J49-L49} -> -126.75781 | N49: {=M49/D49}
B50: Raspagem e Alisamento Radicular (Tartarotomia) | C50: 60 | D50: 380 | E50: {=C50/60} -> 1 | F50: {=$E$6*E50} -> 253.51562 | G50: {=H50+I50+K50+F50+J50+L50} -> 348.51562 | H50: {=D50*$H$9} -> 11.4 | I50: {=$I$9*D50} -> 45.6 | J50: {=$J$9*D50} -> 38 | M50: {=D50-K50-I50-H50-F50-J50-L50} -> 31.484375 | N50: {=M50/D50} -> 0.082853618
B51: Sondagem + periograma + Instrução de higiene Oral | C51: 60 | D51: 350 | E51: {=C51/60} -> 1 | F51: {=$E$6*E51} -> 253.51562 | G51: {=H51+I51+K51+F51+J51+L51} -> 341.01562 | H51: {=D51*$H$9} -> 10.5 | I51: {=$I$9*D51} -> 42 | J51: {=$J$9*D51} -> 35 | M51: {=D51-K51-I51-H51-F51-J51-L51} -> 8.984375 | N51: {=M51/D51} -> 0.025669643
... B53: Tunelização | C53: 90 | D53: 1200 | E53: {=C53/60} -> 1.5 | F53: {=$E$6*E53} -> 380.27344 | G53: {=H53+I53+K53+F53+J53+L53} -> 680.27344 | H53: {=D53*$H$9} -> 36 | I53: {=$I$9*D53} -> 144 | J53: {=$J$9*D53} -> 120 | M53: {=D53-K53-I53-H53-F53-J53-L53} -> 519.72656 | N53: {=M53/D53} -> 0.43310547
B54: PRÓTESE CONVENCIONAL
B55: Enceramento | C55: 60 | D55: 600 | E55: {=C55/60} -> 1 | F55: {=$E$6*E55} -> 253.51562 | G55: {=H55+I55+K55+F55+J55+L55} -> 403.51562 | H55: {=D55*$H$9} -> 18 | I55: {=$I$9*D55} -> 72 | J55: {=$J$9*D55} -> 60 | M55: {=D55-K55-I55-H55-F55-J55-L55} -> 196.48438 | N55: {=M55/D55} -> 0.32747396
B56: Conserto em Prótese Total ou Parcial | C56: 60 | D56: 350 | E56: {=C56/60} -> 1 | F56: {=$E$6*E56} -> 253.51562 | G56: {=H56+I56+K56+F56+J56+L56} -> 341.01562 | H56: {=D56*$H$9} -> 10.5 | I56: {=$I$9*D56} -> 42 | J56: {=$J$9*D56} -> 35 | M56: {=D56-K56-I56-H56-F56-J56-L56} -> 8.984375 | N56: {=M56/D56} -> 0.025669643
B57: Coroa em zircônia (otimizar tempo) | C57: 240 | D57: 2000 | E57: {=C57/60} -> 4 | F57: {=$E$6*E57} -> 1014.0625 | G57: {=H57+I57+K57+F57+J57+L57} -> 1514.0625 | H57: {=D57*$H$9} -> 60 | I57: {=$I$9*D57} -> 240 | J57: {=$J$9*D57} -> 200 | M57: {=D57-K57-I57-H57-F57-J57-L57} -> 485.9375 | N57: {=M57/D57} -> 0.24296875
B58: Coroa E-MAX (otimizar tempo) | C58: 240 | D58: 2700 | E58: {=C58/60} -> 4 | F58: {=$E$6*E58} -> 1014.0625 | G58: {=H58+I58+K58+F58+J58+L58} -> 1689.0625 | H58: {=D58*$H$9} -> 81 | I58: {=$I$9*D58} -> 324 | J58: {=$J$9*D58} -> 270 | M58: {=D58-K58-I58-H58-F58-J58-L58} -> 1010.9375 | N58: {=M58/D58} -> 0.3744213
B59: Coroa Metalocerâmica sobre implante (otimizar tempo) | C59: 90 | D59: 2000 | E59: {=C59/60} -> 1.5 | F59: {=$E$6*E59} -> 380.27344 | G59: {=H59+I59+K59+F59+J59+L59} -> 880.27344 | H59: {=D59*$H$9} -> 60 | I59: {=$I$9*D59} -> 240 | J59: {=$J$9*D59} -> 200 | M59: {=D59-K59-I59-H59-F59-J59-L59} -> 1119.7266 | N59: {=M59/D59} -> 0.55986328
B60: Coroa Provisória Prensada em Resina | C60: 60 | D60: 350 | E60: {=C60/60} -> 1 | F60: {=$E$6*E60} -> 253.51562 | G60: {=H60+I60+K60+F60+J60+L60} -> 341.01562 | H60: {=D60*$H$9} -> 10.5 | I60: {=$I$9*D60} -> 42 | J60: {=$J$9*D60} -> 35 | M60: {=D60-K60-I60-H60-F60-J60-L60} -> 8.984375 | N60: {=M60/D60} -> 0.025669643
B61: Elemento Pilar Prótese Fixa - Metalo Cerâmica | C61: 240 | D61: 2000 | E61: {=C61/60} -> 4 | F61: {=$E$6*E61} -> 1014.0625 | G61: {=H61+I61+K61+F61+J61+L61} -> 1514.0625 | H61: {=D61*$H$9} -> 60 | I61: {=$I$9*D61} -> 240 | J61: {=$J$9*D61} -> 200 | M61: {=D61-K61-I61-H61-F61-J61-L61} -> 485.9375 | N61: {=M61/D61} -> 0.24296875
B62: Elemento Suspenso Prótese Fixa - Metalo Cerâmica | C62: 30 | D62: 2000 | E62: {=C62/60} -> 0.5 | F62: {=$E$6*E62} -> 126.75781 | G62: {=H62+I62+K62+F62+J62+L62} -> 626.75781 | H62: {=D62*$H$9} -> 60 | I62: {=$I$9*D62} -> 240 | J62: {=$J$9*D62} -> 200 | M62: {=D62-K62-I62-H62-F62-J62-L62} -> 1373.2422 | N62: {=M62/D62} -> 0.68662109
B63: Faceta Laminada em Porcelana | C63: 120 | D63: 2000 | E63: {=C63/60} -> 2 | F63: {=$E$6*E63} -> 507.03125 | G63: {=H63+I63+K63+F63+J63+L63} -> 1007.0312 | H63: {=D63*$H$9} -> 60 | I63: {=$I$9*D63} -> 240 | J63: {=$J$9*D63} -> 200 | M63: {=D63-K63-I63-H63-F63-J63-L63} -> 992.96875 | N63: {=M63/D63} -> 0.49648437
B64: instalação de componente - prótese cimentada sobre implante | C64: 30 | D64: 800 | E64: {=C64/60} -> 0.5 | F64: {=$E$6*E64} -> 126.75781 | G64: {=H64+I64+K64+F64+J64+L64} -> 326.75781 | H64: {=D64*$H$9} -> 24 | I64: {=$I$9*D64} -> 96 | J64: {=$J$9*D64} -> 80 | M64: {=D64-K64-I64-H64-F64-J64-L64} -> 473.24219 | N64: {=M64/D64} -> 0.59155273
B65: instalação de componente - | C65: 30 | D65: 800 | E65: {=C65/60} -> 0.5 | F65: {=$E$6*E65} -> 126.75781 | G65: {=H65+I65+K65+F65+J65+L65} -> 326.75781 | H65: {=D65*$H$9} -> 24 | I65: {=$I$9*D65} -> 96 | J65: {=$J$9*D65} -> 80 | M65: {=D65-K65-I65-H65-F65-J65-L65} -> 473.24219 | N65: {=M65/D65} -> 0.59155273
B66: instalação de componente overdenture | C66: 30 | D66: 1600 | E66: {=C66/60} -> 0.5 | F66: {=$E$6*E66} -> 126.75781 | G66: {=H66+I66+K66+F66+J66+L66} -> 526.75781 | H66: {=D66*$H$9} -> 48 | I66: {=$I$9*D66} -> 192 | J66: {=$J$9*D66} -> 160 | M66: {=D66-K66-I66-H66-F66-J66-L66} -> 1073.2422 | N66: {=M66/D66} -> 0.67077637
... B87: Troca de Borracha de O'ring | C87: 30 | D87: 400 | E87: {=C87/60} -> 0.5 | F87: {=$E$6*E87} -> 126.75781 | G87: {=H87+I87+K87+F87+J87+L87} -> 226.75781 | H87: {=D87*$H$9} -> 12 | I87: {=$I$9*D87} -> 48 | J87: {=$J$9*D87} -> 40 | M87: {=D87-K87-I87-H87-F87-J87-L87} -> 173.24219 | N87: {=M87/D87} -> 0.43310547
B88: CIRURGIA
B89: Drenagem de Abscesso | C89: 30 | D89: 300 | E89: {=C89/60} -> 0.5 | F89: {=$E$6*E89} -> 126.75781 | G89: {=H89+I89+K89+F89+J89+L89} -> 201.75781 | H89: {=D89*$H$9} -> 9 | I89: {=$I$9*D89} -> 36 | J89: {=$J$9*D89} -> 30 | M89: {=D89-K89-I89-H89-F89-J89-L89} -> 98.242188 | N89: {=M89/D89} -> 0.32747396
B90: Enxerto Ósseo | C90: 60 | D90: 1800 | E90: {=C90/60} -> 1 | F90: {=$E$6*E90} -> 253.51562 | G90: {=H90+I90+K90+F90+J90+L90} -> 703.51562 | H90: {=D90*$H$9} -> 54 | I90: {=$I$9*D90} -> 216 | J90: {=$J$9*D90} -> 180 | M90: {=D90-K90-I90-H90-F90-J90-L90} -> 1096.4844 | N90: {=M90/D90} -> 0.60915799
B91: Exo + Membrana para RTG | C91: 90 | D91: 1500 | E91: {=C91/60} -> 1.5 | F91: {=$E$6*E91} -> 380.27344 | G91: {=H91+I91+K91+F91+J91+L91} -> 755.27344 | H91: {=D91*$H$9} -> 45 | I91: {=$I$9*D91} -> 180 | J91: {=$J$9*D91} -> 150 | M91: {=D91-K91-I91-H91-F91-J91-L91} -> 744.72656 | N91: {=M91/D91} -> 0.49648437
B92: Exodontia de Raiz Residual | C92: 60 | D92: 600 | E92: {=C92/60} -> 1 | F92: {=$E$6*E92} -> 253.51562 | G92: {=H92+I92+K92+F92+J92+L92} -> 403.51562 | H92: {=D92*$H$9} -> 18 | I92: {=$I$9*D92} -> 72 | J92: {=$J$9*D92} -> 60 | M92: {=D92-K92-I92-H92-F92-J92-L92} -> 196.48438 | N92: {=M92/D92} -> 0.32747396
B93: Exodontia Incluso | C93: 90 | D93: 1200 | E93: {=C93/60} -> 1.5 | F93: {=$E$6*E93} -> 380.27344 | G93: {=H93+I93+K93+F93+J93+L93} -> 680.27344 | H93: {=D93*$H$9} -> 36 | I93: {=$I$9*D93} -> 144 | J93: {=$J$9*D93} -> 120 | M93: {=D93-K93-I93-H93-F93-J93-L93} -> 519.72656 | N93: {=M93/D93} -> 0.43310547
B94: Exodontia Semi-incluso | C94: 60 | D94: 800 | E94: {=C94/60} -> 1 | F94: {=$E$6*E94} -> 253.51562 | G94: {=H94+I94+K94+F94+J94+L94} -> 453.51562 | H94: {=D94*$H$9} -> 24 | I94: {=$I$9*D94} -> 96 | J94: {=$J$9*D94} -> 80 | M94: {=D94-K94-I94-H94-F94-J94-L94} -> 346.48438 | N94: {=M94/D94} -> 0.43310547
B95: Exodontia Simples | C95: 60 | D95: 600 | E95: {=C95/60} -> 1 | F95: {=$E$6*E95} -> 253.51562 | G95: {=H95+I95+K95+F95+J95+L95} -> 403.51562 | H95: {=D95*$H$9} -> 18 | I95: {=$I$9*D95} -> 72 | J95: {=$J$9*D95} -> 60 | M95: {=D95-K95-I95-H95-F95-J95-L95} -> 196.48438 | N95: {=M95/D95} -> 0.32747396
B96: Frenectomia Labial Superior | C96: 60 | D96: 600 | E96: {=C96/60} -> 1 | F96: {=$E$6*E96} -> 253.51562 | G96: {=H96+I96+K96+F96+J96+L96} -> 403.51562 | H96: {=D96*$H$9} -> 18 | I96: {=$I$9*D96} -> 72 | J96: {=$J$9*D96} -> 60 | M96: {=D96-K96-I96-H96-F96-J96-L96} -> 196.48438 | N96: {=M96/D96} -> 0.32747396
B97: Frenectomia Lingual | C97: 60 | D97: 800 | E97: {=C97/60} -> 1 | F97: {=$E$6*E97} -> 253.51562 | G97: {=H97+I97+K97+F97+J97+L97} -> 453.51562 | H97: {=D97*$H$9} -> 24 | I97: {=$I$9*D97} -> 96 | J97: {=$J$9*D97} -> 80 | M97: {=D97-K97-I97-H97-F97-J97-L97} -> 346.48438 | N97: {=M97/D97} -> 0.43310547
B98: Tratamento cirúrgico Peri-implantite | C98: 90 | D98: 2000 | E98: {=C98/60} -> 1.5 | F98: {=$E$6*E98} -> 380.27344 | G98: {=H98+I98+K98+F98+J98+L98} -> 880.27344 | H98: {=D98*$H$9} -> 60 | I98: {=$I$9*D98} -> 240 | J98: {=$J$9*D98} -> 200 | M98: {=D98-K98-I98-H98-F98-J98-L98} -> 1119.7266 | N98: {=M98/D98} -> 0.55986328
B99: ORTODONTIA
B100: Controle Mensal - Aparelho Fixo | C100: 30 | D100: 250 | E100: {=C100/60} -> 0.5 | F100: {=$E$6*E100} -> 126.75781 | G100: {=H100+I100+K100+F100+J100+L100} -> 189.25781 | H100: {=D100*$H$9} -> 7.5 | I100: {=$I$9*D100} -> 30 | J100: {=$J$9*D100} -> 25 | M100: {=D100-K100-I100-H100-F100-J100-L100} -> 60.742188 | N100: {=M100/D100} -> 0.24296875
B101: Controle Mensal - Aparelho Móvel | C101: 30 | D101: 300 | E101: {=C101/60} -> 0.5 | F101: {=$E$6*E101} -> 126.75781 | G101: {=H101+I101+K101+F101+J101+L101} -> 201.75781 | H101: {=D101*$H$9} -> 9 | I101: {=$I$9*D101} -> 36 | J101: {=$J$9*D101} -> 30 | M101: {=D101-K101-I101-H101-F101-J101-L101} -> 98.242188 | N101: {=M101/D101} -> 0.32747396
B102: RADIOLOGIA
B103: Radiografia Interproximal | C103: 15 | D103: 30 | E103: {=C103/60} -> 0.25 | F103: {=$E$6*E103} -> 63.378906 | G103: {=H103+I103+K103+F103+J103+L103} -> 70.878906 | H103: {=D103*$H$9} -> 0.9 | I103: {=$I$9*D103} -> 3.6 | J103: {=$J$9*D103} -> 3 | M103: {=D103-K103-I103-H103-F103-J103-L103} -> -40.878906 | N103: {=M103/D103} -> -1.3626302
B104: Radiografia Periapical | C104: 15 | D104: 30 | E104: {=C104/60} -> 0.25 | F104: {=$E$6*E104} -> 63.378906 | G104: {=H104+I104+K104+F104+J104+L104} -> 70.878906 | H104: {=D104*$H$9} -> 0.9 | I104: {=$I$9*D104} -> 3.6 | J104: {=$J$9*D104} -> 3 | M104: {=D104-K104-I104-H104-F104-J104-L104} -> -40.878906 | N104: {=M104/D104} -> -1.3626302
B105: HARMONIZAÇÃO OROFACIAL
E106: {=C106/60} -> 0 | F106: {=$E$6*E106} -> 0 | G106: {=H106+I106+K106+F106+J106+L106} -> 0 | H106: {=D106*$H$9} -> 0 | I106: {=$I$9*D106} -> 0 | J106: {=$J$9*D106} -> 0 | M106: {=D106-K106-I106-H106-F106-J106-L106} -> 0 | N106: {=M106/D106}
E107: {=C107/60} -> 0 | F107: {=$E$6*E107} -> 0 | G107: {=H107+I107+K107+F107+J107+L107} -> 0 | H107: {=D107*$H$9} -> 0 | I107: {=$I$9*D107} -> 0 | J107: {=$J$9*D107} -> 0 | M107: {=D107-K107-I107-H107-F107-J107-L107} -> 0 | N107: {=M107/D107}
E108: {=C108/60} -> 0 | F108: {=$E$6*E108} -> 0 | G108: {=H108+I108+K108+F108+J108+L108} -> 0 | H108: {=D108*$H$9} -> 0 | I108: {=$I$9*D108} -> 0 | J108: {=$J$9*D108} -> 0 | M108: {=D108-K108-I108-H108-F108-J108-L108} -> 0 | N108: {=M108/D108}
E109: {=C109/60} -> 0 | F109: {=$E$6*E109} -> 0 | G109: {=H109+I109+K109+F109+J109+L109} -> 0 | H109: {=D109*$H$9} -> 0 | I109: {=$I$9*D109} -> 0 | J109: {=$J$9*D109} -> 0 | M109: {=D109-K109-I109-H109-F109-J109-L109} -> 0 | N109: {=M109/D109}
E110: {=C110/60} -> 0 | F110: {=$E$6*E110} -> 0 | G110: {=H110+I110+K110+F110+J110+L110} -> 0 | H110: {=D110*$H$9} -> 0 | I110: {=$I$9*D110} -> 0 | J110: {=$J$9*D110} -> 0 | M110: {=D110-K110-I110-H110-F110-J110-L110} -> 0 | N110: {=M110/D110}
E111: {=C111/60} -> 0 | F111: {=$E$6*E111} -> 0 | G111: {=H111+I111+K111+F111+J111+L111} -> 0 | H111: {=D111*$H$9} -> 0 | I111: {=$I$9*D111} -> 0 | J111: {=$J$9*D111} -> 0 | M111: {=D111-K111-I111-H111-F111-J111-L111} -> 0 | N111: {=M111/D111}
B112: IMPLANTE - FASE PROTÉTICA
E113: {=C113/60} -> 0 | F113: {=$E$6*E113} -> 0 | G113: {=H113+I113+K113+F113+J113+L113} -> 0 | H113: {=D113*$H$9} -> 0 | I113: {=$I$9*D113} -> 0 | J113: {=$J$9*D113} -> 0 | M113: {=D113-K113-I113-H113-F113-J113-L113} -> 0 | N113: {=M113/D113}
E114: {=C114/60} -> 0 | F114: {=$E$6*E114} -> 0 | G114: {=H114+I114+K114+F114+J114+L114} -> 0 | H114: {=D114*$H$9} -> 0 | I114: {=$I$9*D114} -> 0 | J114: {=$J$9*D114} -> 0 | M114: {=D114-K114-I114-H114-F114-J114-L114} -> 0 | N114: {=M114/D114}
E115: {=C115/60} -> 0 | F115: {=$E$6*E115} -> 0 | G115: {=H115+I115+K115+F115+J115+L115} -> 0 | H115: {=D115*$H$9} -> 0 | I115: {=$I$9*D115} -> 0 | J115: {=$J$9*D115} -> 0 | M115: {=D115-K115-I115-H115-F115-J115-L115} -> 0 | N115: {=M115/D115}
E116: {=C116/60} -> 0 | F116: {=$E$6*E116} -> 0 | G116: {=H116+I116+K116+F116+J116+L116} -> 0 | H116: {=D116*$H$9} -> 0 | I116: {=$I$9*D116} -> 0 | J116: {=$J$9*D116} -> 0 | M116: {=D116-K116-I116-H116-F116-J116-L116} -> 0 | N116: {=M116/D116}
B117: IMPLANTE - FASE CIRÚRGICA
B118: Cirurgia de Implante | C118: 90 | D118: 1200 | E118: {=C118/60} -> 1.5 | F118: {=$E$6*E118} -> 380.27344 | G118: {=H118+I118+K118+F118+J118+L118} -> 680.27344 | H118: {=D118*$H$9} -> 36 | I118: {=$I$9*D118} -> 144 | J118: {=$J$9*D118} -> 120 | M118: {=D118-K118-I118-H118-F118-J118-L118} -> 519.72656 | N118: {=M118/D118} -> 0.43310547
B119: Guia Cirúrgico | C119: 60 | D119: 600 | E119: {=C119/60} -> 1 | F119: {=$E$6*E119} -> 253.51562 | G119: {=H119+I119+K119+F119+J119+L119} -> 403.51562 | H119: {=D119*$H$9} -> 18 | I119: {=$I$9*D119} -> 72 | J119: {=$J$9*D119} -> 60 | M119: {=D119-K119-I119-H119-F119-J119-L119} -> 196.48438 | N119: {=M119/D119} -> 0.32747396
B120: Levantamento de Seio Maxilar | C120: 150 | D120: 3000 | E120: {=C120/60} -> 2.5 | F120: {=$E$6*E120} -> 633.78906 | G120: {=H120+I120+K120+F120+J120+L120} -> 1383.7891 | H120: {=D120*$H$9} -> 90 | I120: {=$I$9*D120} -> 360 | J120: {=$J$9*D120} -> 300 | M120: {=D120-K120-I120-H120-F120-J120-L120} -> 1616.2109 | N120: {=M120/D120} -> 0.53873698
B121: Protocolo implantes | C121: 480 | D121: 15000 | E121: {=C121/60} -> 8 | F121: {=$E$6*E121} -> 2028.125 | G121: {=H121+I121+K121+F121+J121+L121} -> 5778.125 | H121: {=D121*$H$9} -> 450 | I121: {=$I$9*D121} -> 1800 | J121: {=$J$9*D121} -> 1500 | M121: {=D121-K121-I121-H121-F121-J121-L121} -> 9221.875 | N121: {=M121/D121} -> 0.61479167
B122: tratamento peri-implantite | C122: 120 | D122: 1800 | E122: {=C122/60} -> 2 | F122: {=$E$6*E122} -> 507.03125 | G122: {=H122+I122+K122+F122+J122+L122} -> 957.03125 | H122: {=D122*$H$9} -> 54 | I122: {=$I$9*D122} -> 216 | J122: {=$J$9*D122} -> 180 | M122: {=D122-K122-I122-H122-F122-J122-L122} -> 842.96875 | N122: {=M122/D122} -> 0.46831597
B123: URGÊNCIAS
B124: Consulta Emergência (horário normal) | C124: 60 | D124: 250 | E124: {=C124/60} -> 1 | F124: {=$E$6*E124} -> 253.51562 | G124: {=H124+I124+K124+F124+J124+L124} -> 316.01562 | H124: {=D124*$H$9} -> 7.5 | I124: {=$I$9*D124} -> 30 | J124: {=$J$9*D124} -> 25 | M124: {=D124-K124-I124-H124-F124-J124-L124} -> -66.015625 | N124: {=M124/D124} -> -0.2640625
B125: Consulta Emergência (noturna, sáb., dom., feriado) | C125: 60 | D125: 350 | E125: {=C125/60} -> 1 | F125: {=$E$6*E125} -> 253.51562 | G125: {=H125+I125+K125+F125+J125+L125} -> 341.01562 | H125: {=D125*$H$9} -> 10.5 | I125: {=$I$9*D125} -> 42 | J125: {=$J$9*D125} -> 35 | M125: {=D125-K125-I125-H125-F125-J125-L125} -> 8.984375 | N125: {=M125/D125} -> 0.025669643

Sheet SERVIÇO
B4: INSIRA O VALOR DO PRODUTO / SERVIÇO | E4: 500 | H4: Obs. Onde a célula estiver na cor cinza, tem fórmula
B6: CUSTOS E DESPESAS VARIÁVEIS | C6: % do preço | D6: R$ | E6: TOTAL | F6: % | I6: TOTAL
B7: IMPOSTOS E DESP. VENDA MÉDIO CATEGORIA | E7: {=SUM(E8:E17)} -> 150 | F7: {=SUM(F8:F17)} -> 0.3 | H7: COMPROMISSO FIXO MENSAL | I7: {=SUM(I8:I23)} -> 32450
B8: {='CUSTO VARIAVEL'!B7} -> 1. Impostos % | C8: {='CUSTO VARIAVEL'!C7} -> 0.22 | E8: {=C8*$E$4+D8} -> 110 | F8: {=E8/$E$4} -> 0.22 | H8: {='CUSTO FIXO'!B7} -> 1. Aluguéis | I8: {='CUSTO FIXO'!C7} -> 4000
B9: {='CUSTO VARIAVEL'!B8} -> 2. Taxa Cartão | C9: {='CUSTO VARIAVEL'!C8} -> 0.05 | E9: {=C9*$E$4+D9} -> 25 | F9: {=E9/$E$4} -> 0.05 | H9: {='CUSTO FIXO'!B8} -> 2. Salários e Benefícios Funcionários | I9: {='CUSTO FIXO'!C8} -> 8000
B10: {='CUSTO VARIAVEL'!B9} -> 3. Comissões | C10: {='CUSTO VARIAVEL'!C9} -> 0.03 | E10: {=C10*$E$4+D10} -> 15 | F10: {=E10/$E$4} -> 0.03 | H10: {='CUSTO FIXO'!B9} -> 3. Pró Labore e Benefícios Sócios | I10: {='CUSTO FIXO'!C9} -> 10000
B11: {='CUSTO VARIAVEL'!B10} -> 4. Inadimplencia | C11: {='CUSTO VARIAVEL'!C10} -> 0 | E11: {=C11*$E$4+D11} -> 0 | F11: {=E11/$E$4} -> 0 | H11: {='CUSTO FIXO'!B10} -> 4. Despesas de Viagem | I11: {='CUSTO FIXO'!C10} -> 2000
B12: {='CUSTO VARIAVEL'!B11} -> 5. Taxa boleto | C12: {='CUSTO VARIAVEL'!C11} -> 0 | E12: {=C12*$E$4+D12} -> 0 | F12: {=E12/$E$4} -> 0 | H12: {='CUSTO FIXO'!B11} -> 5. Contabilidade | I12: {='CUSTO FIXO'!C11} -> 1800
B13: {='CUSTO VARIAVEL'!B12} -> 6. Perda/Extravio/Não Receb. | C13: {='CUSTO VARIAVEL'!C12} -> 0 | E13: {=C13*$E$4+D13} -> 0 | F13: {=E13/$E$4} -> 0 | H13: {='CUSTO FIXO'!B12} -> 6. Luz/Água/Gás/Telefone | I13: {='CUSTO FIXO'!C12} -> 800
B14: {='CUSTO VARIAVEL'!B13} -> 7. Outro | C14: {='CUSTO VARIAVEL'!C13} -> 0 | E14: {=C14*$E$4+D14} -> 0 | F14: {=E14/$E$4} -> 0 | H14: {='CUSTO FIXO'!B13} -> 7. Manutenção, Segurança e Limpeza | I14: {='CUSTO FIXO'!C13} -> 1500
B15: {='CUSTO VARIAVEL'!B14} -> 8. Outro | C15: {='CUSTO VARIAVEL'!C14} -> 0 | E15: {=C15*$E$4+D15} -> 0 | F15: {=E15/$E$4} -> 0 | H15: {='CUSTO FIXO'!B14} -> 8. Carros e Seguros | I15: {='CUSTO FIXO'!C14} -> 0
B16: {='CUSTO VARIAVEL'!B15} -> 9. Outro | C16: {='CUSTO VARIAVEL'!C15} -> 0 | E16: {=C16*$E$4+D16} -> 0 | F16: {=E16/$E$4} -> 0 | H16: {='CUSTO FIXO'!B15} -> 9. Desp. Financeiras (juros/taxas/tarifas) | I16: {='CUSTO FIXO'!C15} -> 350
B17: {='CUSTO VARIAVEL'!B16} -> 10. Outros | C17: {='CUSTO VARIAVEL'!C16} -> 0 | E17: {=C17*$E$4+D17} -> 0 | F17: {=E17/$E$4} -> 0 | H17: {='CUSTO FIXO'!B16} -> 10. Desp. Administrativas | I17: {='CUSTO FIXO'!C16} -> 0
B18: CUSTO UNITÁRIO MÉDIO CATEGORIA | E18: {=SUM(E19:E30)} -> 45 | F18: {=SUM(F19:F30)} -> 0.09 | H18: {='CUSTO FIXO'!B17} -> Material no Geral | I18: {='CUSTO FIXO'!C17} -> 4000
B19: {='CUSTO VARIAVEL'!B18} -> 11. Valor de Compra | C19: {='CUSTO VARIAVEL'!C18} -> 0 | D19: {='CUSTO VARIAVEL'!D18} -> 45 | E19: {=D19} -> 45 | F19: {=E19/$E$4} -> 0.09 | H19: {='CUSTO FIXO'!B18} -> 0 | I19: {='CUSTO FIXO'!C18} -> 0
B20: {='CUSTO VARIAVEL'!B19} -> 12. Equipamentos | C20: {='CUSTO VARIAVEL'!C19} -> 0 | D20: {='CUSTO VARIAVEL'!D19} -> 0 | E20: 0 | F20: {=E20/$E$4} -> 0 | H20: {='CUSTO FIXO'!B19} -> 0 | I20: {='CUSTO FIXO'!C19} -> 0
B21: {='CUSTO VARIAVEL'!B20} -> 13. Materiais | C21: {='CUSTO VARIAVEL'!C20} -> 0 | D21: {='CUSTO VARIAVEL'!D20} -> 0 | E21: {=C21*$E$4+D21} -> 0 | F21: {=E21/$E$4} -> 0 | H21: {='CUSTO FIXO'!B20} -> 0 | I21: {='CUSTO FIXO'!C20} -> 0
B22: {='CUSTO VARIAVEL'!B21} -> 14. Insumos | C22: {='CUSTO VARIAVEL'!C21} -> 0 | D22: {='CUSTO VARIAVEL'!D21} -> 0 | E22: {=C22*$E$4+D22} -> 0 | F22: {=E22/$E$4} -> 0 | H22: {='CUSTO FIXO'!B21} -> 0 | I22: {='CUSTO FIXO'!C21} -> 0
B23: {='CUSTO VARIAVEL'!B22} -> 15. Outro | C23: {='CUSTO VARIAVEL'!C22} -> 0 | D23: {='CUSTO VARIAVEL'!D22} -> 0 | E23: {=C23*$E$4+D23} -> 0 | F23: {=E23/$E$4} -> 0 | H23: {='CUSTO FIXO'!B22} -> 0 | I23: {='CUSTO FIXO'!C22} -> 0
B24: {='CUSTO VARIAVEL'!B23} -> 16. Outro | C24: {='CUSTO VARIAVEL'!C23} -> 0 | D24: {='CUSTO VARIAVEL'!D23} -> 0 | E24: {=C24*$E$4+D24} -> 0 | F24: {=E24/$E$4} -> 0
B25: {='CUSTO VARIAVEL'!B24} -> 17. Outro | C25: {='CUSTO VARIAVEL'!C24} -> 0 | D25: {='CUSTO VARIAVEL'!D24} -> 0 | E25: {=C25*$E$4+D25} -> 0 | F25: {=E25/$E$4} -> 0 | H25: EQUIPES | I25: 10
B26: {='CUSTO VARIAVEL'!B25} -> 18. Outro | C26: {='CUSTO VARIAVEL'!C25} -> 0 | D26: {='CUSTO VARIAVEL'!D25} -> 0 | E26: {=C26*$E$4+D26} -> 0 | F26: {=E26/$E$4} -> 0
B27: {='CUSTO VARIAVEL'!B26} -> 19. Outro | C27: {='CUSTO VARIAVEL'!C26} -> 0 | D27: {='CUSTO VARIAVEL'!D26} -> 0 | E27: {=C27*$E$4+D27} -> 0 | F27: {=E27/$E$4} -> 0 | H27: QUANTIDADE DE HORAS por mês (Capacidade de Execução) | I27: {=160*I25} -> 1600
B28: {='CUSTO VARIAVEL'!B27} -> 20. Outro | C28: {='CUSTO VARIAVEL'!C27} -> 0 | D28: {='CUSTO VARIAVEL'!D27} -> 0 | E28: {=C28*$E$4+D28} -> 0 | F28: {=E28/$E$4} -> 0
B29: {='CUSTO VARIAVEL'!B28} -> 21. Outro | C29: {='CUSTO VARIAVEL'!C28} -> 0 | D29: {='CUSTO VARIAVEL'!D28} -> 0 | E29: {=C29*$E$4+D29} -> 0 | F29: {=E29/$E$4} -> 0 | H29: TOTAL DE HORAS subtraindo 20% de faltas, atrasos e ociosidade | I29: {=I27-(I27*0.2)} -> 1280
B30: {='CUSTO VARIAVEL'!B29} -> 22. Outros | C30: {='CUSTO VARIAVEL'!C29} -> 0 | D30: {='CUSTO VARIAVEL'!D29} -> 0 | E30: {=C30*$E$4+D30} -> 0 | F30: {=E30/$E$4} -> 0
H31: CUSTO DA HORA | I31: {=I7/I29} -> 25.351562
B33: MARGEM DE LUCRO DO ORÇAMENTO | C33: {=E33/E4} -> 0.50859375 | E33: {=E4-E7-E18-I35} -> 254.29688 | H33: QUANTIDADE DE HORAS | I33: 2
E34: {=IF(E33<0,"NEGATIVA, reduzir custos ou aumentar preço",IF(E33=0,"ARRISCADA, avaliar estratégia ou reduzir custos",IF(C33<0.05,"BAIXA, avaliar estratégia ou reduzir custos","POSITIVA")))} -> POSITIVA
H35: CUSTO TOTAL DE HORAS | I35: {=I31*I33} -> 50.703125
B37: MARGEM DE CONTRIBUIÇÃO | C37: {=1-(F18+F7)} -> 0.61 | H37: VALOR MÍNINO DO ORÇAMENTO | I37: {=E7+E18+I35} -> 245.70312
H40: PONTO DE EQUILIBRIO DE SERVIÇO | I40: {=I7/C37} -> 53196.721
H41: Quantidade de vendas | I41: {=I40/E4} -> 106.39344
H43: CUSTO DO PPRODUTO | I43: {=I40*F19} -> 4787.7049
H44: IMPOSTOS E DESP. VENDA MÉDIO CATEGORIA | I44: {=SUM(C8:C10)*I40} -> 15959.016
H45: CUSTO FIXO | I45: {=I7} -> 32450
H47: LUCRO DA EMPRESA | I47: {=I40-I43-I44-I45} -> 1e-11
I48: {=I47/I40} -> 1.8798151e-16
H50: O PONTO DE EQUILIBRIO DA VENDA REPRESENTA O QUANDO VOCË PRECISA VENDER PARA PAGAR TODAS AS CONTAS FIXAS DA EMPRESA, TODO VALOR FATURADO ACIMA DESSE VALOR REPRESENTA A MARGEM DE LUCRO LIQUIDA.

Sheet CUSTO FIXO
C5: TOTAL
B6: COMPROMISSO FIXO MENSAL | C6: {=SUM(C7:C25)} -> 32450
B7: 1. Aluguéis | C7: 4000
B8: 2. Salários e Benefícios Funcionários | C8: 8000
B9: 3. Pró Labore e Benefícios Sócios | C9: 10000
B10: 4. Despesas de Viagem | C10: 2000
B11: 5. Contabilidade | C11: 1800
B12: 6. Luz/Água/Gás/Telefone | C12: 800
B13: 7. Manutenção, Segurança e Limpeza | C13: 1500
B14: 8. Carros e Seguros | C14: 0
B15: 9. Desp. Financeiras (juros/taxas/tarifas) | C15: 350
B16: 10. Desp. Administrativas | C16: 0
B17: Material no Geral | C17: 4000

Sheet CUSTO VARIAVEL
B5: CUSTOS E DESPESAS VARIÁVEIS | C5: % do preço | D5: R$ | E5: TOTAL
B6: IMPOSTOS E DESP. VENDA MÉDIO CATEGORIA | E6: {=SUM(E7:E16)} -> 0
B7: 1. Impostos % | C7: 0.22 | E7: {=C7*$E$4+D7} -> 0
B8: 2. Taxa Cartão | C8: 0.05 | E8: {=C8*$E$4+D8} -> 0
B9: 3. Comissões | C9: 0.03 | E9: {=C9*$E$4+D9} -> 0
B10: 4. Inadimplencia | E10: {=C10*$E$4+D10} -> 0
B11: 5. Taxa boleto | E11: {=C11*$E$4+D11} -> 0
B12: 6. Perda/Extravio/Não Receb. | E12: {=C12*$E$4+D12} -> 0
B13: 7. Outro | E13: {=C13*$E$4+D13} -> 0
B14: 8. Outro | E14: {=C14*$E$4+D14} -> 0
B15: 9. Outro | E15: {=C15*$E$4+D15} -> 0
B16: 10. Outros | E16: {=C16*$E$4+D16} -> 0
B17: CUSTO UNITÁRIO MÉDIO CATEGORIA | E17: {=SUM(E18:E29)} -> 45
B18: 11. Valor de Compra | D18: 45 | E18: {=C18*$E$4+D18} -> 45
B19: 12. Equipamentos | D19: 0 | E19: {=C19*$E$4+D19} -> 0
B20: 13. Materiais | E20: {=C20*$E$4+D20} -> 0
B21: 14. Insumos | E21: {=C21*$E$4+D21} -> 0
B22: 15. Outro | E22: {=C22*$E$4+D22} -> 0
B23: 16. Outro | E23: {=C23*$E$4+D23} -> 0
B24: 17. Outro | E24: {=C24*$E$4+D24} -> 0
B25: 18. Outro | E25: {=C25*$E$4+D25} -> 0
B26: 19. Outro | E26: {=C26*$E$4+D26} -> 0
B27: 20. Outro | E27: {=C27*$E$4+D27} -> 0
B28: 21. Outro | E28: {=C28*$E$4+D28} -> 0
B29: 22. Outros | E29: {=C29*$E$4+D29} -> 0

Sheet 1.Financeiro
B2: INDICADORES FINANCEIROS
B5: 1. Direção | C5: 1. Meta | D5: 3. Iniciativas | E5: 5. Meta | F5: Janeiro | G5: Fevereiro | H5: Março | I5: Abril | J5: Maio | K5: Junho | L5: Julho | M5: Agosto | N5: Setembro | O5: Outubro | P5: Novembro | Q5: Dezembro | R5: ANUALIZADO | T5: AUMENTAR
B6: REDUZIR | D6: Iniciativa 1 | E6: Projetada | R6: {=SUM(F6:Q6)} -> 0 | T6: REDUZIR
E7: Realizada | R7: {=SUM(F7:Q7)} -> 0
E8: % | F8: {=_xlfn.IFERROR((IF($B6="AUMENTAR",(F7/F6),IF($B6="REDUZIR",F6/F7,"0"))),"")} | G8: {=_xlfn.IFERROR((IF($B6="AUMENTAR",(G7/G6),IF($B6="REDUZIR",G6/G7,"0"))),"")} | H8: {=_xlfn.IFERROR((IF($B6="AUMENTAR",(H7/H6),IF($B6="REDUZIR",H6/H7,"0"))),"")} | I8: {=_xlfn.IFERROR((IF($B6="AUMENTAR",(I7/I6),IF($B6="REDUZIR",I6/I7,"0"))),"")} | J8: {=_xlfn.IFERROR((IF($B6="AUMENTAR",(J7/J6),IF($B6="REDUZIR",J6/J7,"0"))),"")} | K8: {=_xlfn.IFERROR((IF($B6="AUMENTAR",(K7/K6),IF($B6="REDUZIR",K6/K7,"0"))),"")} | L8: {=_xlfn.IFERROR((IF($B6="AUMENTAR",(L7/L6),IF($B6="REDUZIR",L6/L7,"0"))),"")} | M8: {=_xlfn.IFERROR((IF($B6="AUMENTAR",(M7/M6),IF($B6="REDUZIR",M6/M7,"0"))),"")} | ... R8: {=_xlfn.IFERROR((IF($B6="AUMENTAR",(R7/R6),IF($B6="REDUZIR",R6/R7,"0"))),"")}
B9: REDUZIR | D9: Iniciativa 2 | E9: Projetada | R9: {=SUM(F9:Q9)} -> 0
E10: Realizada | R10: {=SUM(F10:Q10)} -> 0
E11: % | F11: {=_xlfn.IFERROR((IF($B9="AUMENTAR",(F10/F9),IF($B9="REDUZIR",F9/F10,"0"))),"")} | G11: {=_xlfn.IFERROR((IF($B9="AUMENTAR",(G10/G9),IF($B9="REDUZIR",G9/G10,"0"))),"")} | H11: {=_xlfn.IFERROR((IF($B9="AUMENTAR",(H10/H9),IF($B9="REDUZIR",H9/H10,"0"))),"")} | I11: {=_xlfn.IFERROR((IF($B9="AUMENTAR",(I10/I9),IF($B9="REDUZIR",I9/I10,"0"))),"")} | J11: {=_xlfn.IFERROR((IF($B9="AUMENTAR",(J10/J9),IF($B9="REDUZIR",J9/J10,"0"))),"")} | K11: {=_xlfn.IFERROR((IF($B9="AUMENTAR",(K10/K9),IF($B9="REDUZIR",K9/K10,"0"))),"")} | L11: {=_xlfn.IFERROR((IF($B9="AUMENTAR",(L10/L9),IF($B9="REDUZIR",L9/L10,"0"))),"")} | M11: {=_xlfn.IFERROR((IF($B9="AUMENTAR",(M10/M9),IF($B9="REDUZIR",M9/M10,"0"))),"")} | ... R11: {=_xlfn.IFERROR((IF($B9="AUMENTAR",(R10/R9),IF($B9="REDUZIR",R9/R10,"0"))),"")}
B12: AUMENTAR | D12: Iniciativa 3 | E12: Projetada | R12: {=SUM(F12:Q12)} -> 0
E13: Realizada | R13: {=SUM(F13:Q13)} -> 0
E14: % | F14: {=_xlfn.IFERROR((IF($B12="AUMENTAR",(F13/F12),IF($B12="REDUZIR",F12/F13,"0"))),"")} | G14: {=_xlfn.IFERROR((IF($B12="AUMENTAR",(G13/G12),IF($B12="REDUZIR",G12/G13,"0"))),"")} | H14: {=_xlfn.IFERROR((IF($B12="AUMENTAR",(H13/H12),IF($B12="REDUZIR",H12/H13,"0"))),"")} | I14: {=_xlfn.IFERROR((IF($B12="AUMENTAR",(I13/I12),IF($B12="REDUZIR",I12/I13,"0"))),"")} | J14: {=_xlfn.IFERROR((IF($B12="AUMENTAR",(J13/J12),IF($B12="REDUZIR",J12/J13,"0"))),"")} | K14: {=_xlfn.IFERROR((IF($B12="AUMENTAR",(K13/K12),IF($B12="REDUZIR",K12/K13,"0"))),"")} | L14: {=_xlfn.IFERROR((IF($B12="AUMENTAR",(L13/L12),IF($B12="REDUZIR",L12/L13,"0"))),"")} | M14: {=_xlfn.IFERROR((IF($B12="AUMENTAR",(M13/M12),IF($B12="REDUZIR",M12/M13,"0"))),"")} | ... R14: {=_xlfn.IFERROR((IF($B12="AUMENTAR",(R13/R12),IF($B12="REDUZIR",R12/R13,"0"))),"")}
B15: AUMENTAR | D15: Iniciativa 4 | E15: Projetada | R15: {=SUM(F15:Q15)} -> 0
E16: Realizada | R16: {=SUM(F16:Q16)} -> 0
E17: % | F17: {=_xlfn.IFERROR((IF($B15="AUMENTAR",(F16/F15),IF($B15="REDUZIR",F15/F16,"0"))),"")} | G17: {=_xlfn.IFERROR((IF($B15="AUMENTAR",(G16/G15),IF($B15="REDUZIR",G15/G16,"0"))),"")} | H17: {=_xlfn.IFERROR((IF($B15="AUMENTAR",(H16/H15),IF($B15="REDUZIR",H15/H16,"0"))),"")} | I17: {=_xlfn.IFERROR((IF($B15="AUMENTAR",(I16/I15),IF($B15="REDUZIR",I15/I16,"0"))),"")} | J17: {=_xlfn.IFERROR((IF($B15="AUMENTAR",(J16/J15),IF($B15="REDUZIR",J15/J16,"0"))),"")} | K17: {=_xlfn.IFERROR((IF($B15="AUMENTAR",(K16/K15),IF($B15="REDUZIR",K15/K16,"0"))),"")} | L17: {=_xlfn.IFERROR((IF($B15="AUMENTAR",(L16/L15),IF($B15="REDUZIR",L15/L16,"0"))),"")} | M17: {=_xlfn.IFERROR((IF($B15="AUMENTAR",(M16/M15),IF($B15="REDUZIR",M15/M16,"0"))),"")} | ... R17: {=_xlfn.IFERROR((IF($B15="AUMENTAR",(R16/R15),IF($B15="REDUZIR",R15/R16,"0"))),"")}
B21: PLANO DE AÇÃO
B23: Item | C23: Iniciativa | D23: Ação | E23: Responsável | F23: Prazo | G23: Status | H23: Objetivo
G24: {=IF(F24="","Aguardando",IF(F24<=TODAY(),"Atrasado",IF(F24>TODAY(),"Em Execução","Aguardando")))} -> Aguardando
G25: {=IF(F25="","Aguardando",IF(F25<=TODAY(),"Atrasado",IF(F25>TODAY(),"Em Execução","Aguardando")))} -> Aguardando
G26: {=IF(F26="","Aguardando",IF(F26<=TODAY(),"Atrasado",IF(F26>TODAY(),"Em Execução","Aguardando")))} -> Aguardando
G27: {=IF(F27="","Aguardando",IF(F27<=TODAY(),"Atrasado",IF(F27>TODAY(),"Em Execução","Aguardando")))} -> Aguardando
G28: {=IF(F28="","Aguardando",IF(F28<=TODAY(),"Atrasado",IF(F28>TODAY(),"Em Execução","Aguardando")))} -> Aguardando
G29: {=IF(F29="","Aguardando",IF(F29<=TODAY(),"Atrasado",IF(F29>TODAY(),"Em Execução","Aguardando")))} -> Aguardando
G30: {=IF(F30="","Aguardando",IF(F30<=TODAY(),"Atrasado",IF(F30>TODAY(),"Em Execução","Aguardando")))} -> Aguardando
G31: {=IF(F31="","Aguardando",IF(F31<=TODAY(),"Atrasado",IF(F31>TODAY(),"Em Execução","Aguardando")))} -> Aguardando
G32: {=IF(F32="","Aguardando",IF(F32<=TODAY(),"Atrasado",IF(F32>TODAY(),"Em Execução","Aguardando")))} -> Aguardando
G33: {=IF(F33="","Aguardando",IF(F33<=TODAY(),"Atrasado",IF(F33>TODAY(),"Em Execução","Aguardando")))} -> Aguardando
G34: {=IF(F34="","Aguardando",IF(F34<=TODAY(),"Atrasado",IF(F34>TODAY(),"Em Execução","Aguardando")))} -> Aguardando
G35: {=IF(F35="","Aguardando",IF(F35<=TODAY(),"Atrasado",IF(F35>TODAY(),"Em Execução","Aguardando")))} -> Aguardando
G36: {=IF(F36="","Aguardando",IF(F36<=TODAY(),"Atrasado",IF(F36>TODAY(),"Em Execução","Aguardando")))} -> Aguardando

Sheet 2.Comercial
B2: INDICADORES COMERCIAIS
B5: 1. Direção | C5: 1. Meta | D5: 3. Iniciativas | E5: 5. Meta | F5: Janeiro | G5: Fevereiro | H5: Março | I5: Abril | J5: Maio | K5: Junho | L5: Julho | M5: Agosto | N5: Setembro | O5: Outubro | P5: Novembro | Q5: Dezembro | R5: ANUALIZADO | T5: AUMENTAR
B6: AUMENTAR | D6: Iniciativa 1 | E6: Projetada | R6: {=AVERAGE(F6:Q6)} | T6: REDUZIR
E7: Realizada | R7: {=SUM(F7:Q7)} -> 0
E8: % | F8: {=_xlfn.IFERROR((IF($B6="AUMENTAR",(F7/F6),IF($B6="REDUZIR",F6/F7,"0"))),"")} | G8: {=_xlfn.IFERROR((IF($B6="AUMENTAR",(G7/G6),IF($B6="REDUZIR",G6/G7,"0"))),"")} | H8: {=_xlfn.IFERROR((IF($B6="AUMENTAR",(H7/H6),IF($B6="REDUZIR",H6/H7,"0"))),"")} | I8: {=_xlfn.IFERROR((IF($B6="AUMENTAR",(I7/I6),IF($B6="REDUZIR",I6/I7,"0"))),"")} | J8: {=_xlfn.IFERROR((IF($B6="AUMENTAR",(J7/J6),IF($B6="REDUZIR",J6/J7,"0"))),"")} | K8: {=_xlfn.IFERROR((IF($B6="AUMENTAR",(K7/K6),IF($B6="REDUZIR",K6/K7,"0"))),"")} | L8: {=_xlfn.IFERROR((IF($B6="AUMENTAR",(L7/L6),IF($B6="REDUZIR",L6/L7,"0"))),"")} | M8: {=_xlfn.IFERROR((IF($B6="AUMENTAR",(M7/M6),IF($B6="REDUZIR",M6/M7,"0"))),"")} | ... R8: {=_xlfn.IFERROR((IF($B6="AUMENTAR",(R7/R6),IF($B6="REDUZIR",R6/R7,"0"))),"")}
B9: AUMENTAR | D9: Iniciativa 2 | E9: Projetada | R9: {=AVERAGE(F9:Q9)}
E10: Realizada | R10: {=SUM(F10:Q10)} -> 0
E11: % | F11: {=_xlfn.IFERROR((IF($B9="AUMENTAR",(F10/F9),IF($B9="REDUZIR",F9/F10,"0"))),"")} | G11: {=_xlfn.IFERROR((IF($B9="AUMENTAR",(G10/G9),IF($B9="REDUZIR",G9/G10,"0"))),"")} | H11: {=_xlfn.IFERROR((IF($B9="AUMENTAR",(H10/H9),IF($B9="REDUZIR",H9/H10,"0"))),"")} | I11: {=_xlfn.IFERROR((IF($B9="AUMENTAR",(I10/I9),IF($B9="REDUZIR",I9/I10,"0"))),"")} | J11: {=_xlfn.IFERROR((IF($B9="AUMENTAR",(J10/J9),IF($B9="REDUZIR",J9/J10,"0"))),"")} | K11: {=_xlfn.IFERROR((IF($B9="AUMENTAR",(K10/K9),IF($B9="REDUZIR",K9/K10,"0"))),"")} | L11: {=_xlfn.IFERROR((IF($B9="AUMENTAR",(L10/L9),IF($B9="REDUZIR",L9/L10,"0"))),"")} | M11: {=_xlfn.IFERROR((IF($B9="AUMENTAR",(M10/M9),IF($B9="REDUZIR",M9/M10,"0"))),"")} | ... R11: {=_xlfn.IFERROR((IF($B9="AUMENTAR",(R10/R9),IF($B9="REDUZIR",R9/R10,"0"))),"")}
B12: REDUZIR | D12: Iniciativa 3 | E12: Projetada | R12: {=SUM(F12:Q12)} -> 0
E13: Realizada | R13: {=SUM(F13:Q13)} -> 0
E14: % | F14: {=_xlfn.IFERROR((IF($B12="AUMENTAR",(F13/F12),IF($B12="REDUZIR",F12/F13,"0"))),"")} | G14: {=_xlfn.IFERROR((IF($B12="AUMENTAR",(G13/G12),IF($B12="REDUZIR",G12/G13,"0"))),"")} | H14: {=_xlfn.IFERROR((IF($B12="AUMENTAR",(H13/H12),IF($B12="REDUZIR",H12/H13,"0"))),"")} | I14: {=_xlfn.IFERROR((IF($B12="AUMENTAR",(I13/I12),IF($B12="REDUZIR",I12/I13,"0"))),"")} | J14: {=_xlfn.IFERROR((IF($B12="AUMENTAR",(J13/J12),IF($B12="REDUZIR",J12/J13,"0"))),"")} | K14: {=_xlfn.IFERROR((IF($B12="AUMENTAR",(K13/K12),IF($B12="REDUZIR",K12/K13,"0"))),"")} | L14: {=_xlfn.IFERROR((IF($B12="AUMENTAR",(L13/L12),IF($B12="REDUZIR",L12/L13,"0"))),"")} | M14: {=_xlfn.IFERROR((IF($B12="AUMENTAR",(M13/M12),IF($B12="REDUZIR",M12/M13,"0"))),"")} | ... R14: {=_xlfn.IFERROR((IF($B12="AUMENTAR",(R13/R12),IF($B12="REDUZIR",R12/R13,"0"))),"")}
B15: REDUZIR | D15: Iniciativa 4 | E15: Projetada | R15: {=SUM(F15:Q15)} -> 0
E16: Realizada | H16: 0 | I16: 0 | J16: 0 | K16: 0 | L16: 0 | M16: 0 | N16: 0 | O16: 0 | P16: 0 | Q16: 0 | R16: {=SUM(F16:Q16)} -> 0
E17: % | F17: {=_xlfn.IFERROR((IF($B15="AUMENTAR",(F16/F15),IF($B15="REDUZIR",F15/F16,"0"))),"")} | G17: {=_xlfn.IFERROR((IF($B15="AUMENTAR",(G16/G15),IF($B15="REDUZIR",G15/G16,"0"))),"")} | H17: {=_xlfn.IFERROR((IF($B15="AUMENTAR",(H16/H15),IF($B15="REDUZIR",H15/H16,"0"))),"")} | I17: {=_xlfn.IFERROR((IF($B15="AUMENTAR",(I16/I15),IF($B15="REDUZIR",I15/I16,"0"))),"")} | J17: {=_xlfn.IFERROR((IF($B15="AUMENTAR",(J16/J15),IF($B15="REDUZIR",J15/J16,"0"))),"")} | K17: {=_xlfn.IFERROR((IF($B15="AUMENTAR",(K16/K15),IF($B15="REDUZIR",K15/K16,"0"))),"")} | L17: {=_xlfn.IFERROR((IF($B15="AUMENTAR",(L16/L15),IF($B15="REDUZIR",L15/L16,"0"))),"")} | M17: {=_xlfn.IFERROR((IF($B15="AUMENTAR",(M16/M15),IF($B15="REDUZIR",M15/M16,"0"))),"")} | ... R17: {=_xlfn.IFERROR((IF($B15="AUMENTAR",(R16/R15),IF($B15="REDUZIR",R15/R16,"0"))),"")}
B21: PLANO DE AÇÃO
B23: Item | C23: Iniciativa | D23: Ação | E23: Responsável | F23: Prazo | G23: Status | H23: Objetivo
G24: {=IF(F24="","Aguardando",IF(F24<=TODAY(),"Atrasado",IF(F24>TODAY(),"Em Execução","Aguardando")))} -> Aguardando
G25: {=IF(F25="","Aguardando",IF(F25<=TODAY(),"Atrasado",IF(F25>TODAY(),"Em Execução","Aguardando")))} -> Aguardando
G26: {=IF(F26="","Aguardando",IF(F26<=TODAY(),"Atrasado",IF(F26>TODAY(),"Em Execução","Aguardando")))} -> Aguardando
G27: {=IF(F27="","Aguardando",IF(F27<=TODAY(),"Atrasado",IF(F27>TODAY(),"Em Execução","Aguardando")))} -> Aguardando
G28: {=IF(F28="","Aguardando",IF(F28<=TODAY(),"Atrasado",IF(F28>TODAY(),"Em Execução","Aguardando")))} -> Aguardando
G29: {=IF(F29="","Aguardando",IF(F29<=TODAY(),"Atrasado",IF(F29>TODAY(),"Em Execução","Aguardando")))} -> Aguardando
G30: {=IF(F30="","Aguardando",IF(F30<=TODAY(),"Atrasado",IF(F30>TODAY(),"Em Execução","Aguardando")))} -> Aguardando
G31: {=IF(F31="","Aguardando",IF(F31<=TODAY(),"Atrasado",IF(F31>TODAY(),"Em Execução","Aguardando")))} -> Aguardando
G32: {=IF(F32="","Aguardando",IF(F32<=TODAY(),"Atrasado",IF(F32>TODAY(),"Em Execução","Aguardando")))} -> Aguardando
G33: {=IF(F33="","Aguardando",IF(F33<=TODAY(),"Atrasado",IF(F33>TODAY(),"Em Execução","Aguardando")))} -> Aguardando
G34: {=IF(F34="","Aguardando",IF(F34<=TODAY(),"Atrasado",IF(F34>TODAY(),"Em Execução","Aguardando")))} -> Aguardando
G35: {=IF(F35="","Aguardando",IF(F35<=TODAY(),"Atrasado",IF(F35>TODAY(),"Em Execução","Aguardando")))} -> Aguardando
G36: {=IF(F36="","Aguardando",IF(F36<=TODAY(),"Atrasado",IF(F36>TODAY(),"Em Execução","Aguardando")))} -> Aguardando

Sheet 3.Marketing
B2: INDICADORES MARKETING
B5: 1. Direção | C5: 1. Meta | D5: 3. Iniciativas | E5: 5. Meta | F5: Janeiro | G5: Fevereiro | H5: Março | I5: Abril | J5: Maio | K5: Junho | L5: Julho | M5: Agosto | N5: Setembro | O5: Outubro | P5: Novembro | Q5: Dezembro | R5: ANUALIZADO | T5: AUMENTAR
B6: AUMENTAR | D6: Iniciativa 1 | E6: Projetada | R6: {=SUM(F6:Q6)} -> 0 | T6: REDUZIR
E7: Realizada | R7: {=SUM(F7:Q7)} -> 0
E8: % | F8: {=_xlfn.IFERROR((IF($B6="AUMENTAR",(F7/F6),IF($B6="REDUZIR",F6/F7,"0"))),"")} | G8: {=_xlfn.IFERROR((IF($B6="AUMENTAR",(G7/G6),IF($B6="REDUZIR",G6/G7,"0"))),"")} | H8: {=_xlfn.IFERROR((IF($B6="AUMENTAR",(H7/H6),IF($B6="REDUZIR",H6/H7,"0"))),"")} | I8: {=_xlfn.IFERROR((IF($B6="AUMENTAR",(I7/I6),IF($B6="REDUZIR",I6/I7,"0"))),"")} | J8: {=_xlfn.IFERROR((IF($B6="AUMENTAR",(J7/J6),IF($B6="REDUZIR",J6/J7,"0"))),"")} | K8: {=_xlfn.IFERROR((IF($B6="AUMENTAR",(K7/K6),IF($B6="REDUZIR",K6/K7,"0"))),"")} | L8: {=_xlfn.IFERROR((IF($B6="AUMENTAR",(L7/L6),IF($B6="REDUZIR",L6/L7,"0"))),"")} | M8: {=_xlfn.IFERROR((IF($B6="AUMENTAR",(M7/M6),IF($B6="REDUZIR",M6/M7,"0"))),"")} | ... R8: {=_xlfn.IFERROR((IF($B6="AUMENTAR",(R7/R6),IF($B6="REDUZIR",R6/R7,"0"))),"")}
B9: REDUZIR | D9: Iniciativa 2 | E9: Projetada | R9: {=SUM(F9:Q9)} -> 0
E10: Realizada | R10: {=SUM(F10:Q10)} -> 0
E11: % | F11: {=_xlfn.IFERROR((IF($B9="AUMENTAR",(F10/F9),IF($B9="REDUZIR",F9/F10,"0"))),"")} | G11: {=_xlfn.IFERROR((IF($B9="AUMENTAR",(G10/G9),IF($B9="REDUZIR",G9/G10,"0"))),"")} | H11: {=_xlfn.IFERROR((IF($B9="AUMENTAR",(H10/H9),IF($B9="REDUZIR",H9/H10,"0"))),"")} | I11: {=_xlfn.IFERROR((IF($B9="AUMENTAR",(I10/I9),IF($B9="REDUZIR",I9/I10,"0"))),"")} | J11: {=_xlfn.IFERROR((IF($B9="AUMENTAR",(J10/J9),IF($B9="REDUZIR",J9/J10,"0"))),"")} | K11: {=_xlfn.IFERROR((IF($B9="AUMENTAR",(K10/K9),IF($B9="REDUZIR",K9/K10,"0"))),"")} | L11: {=_xlfn.IFERROR((IF($B9="AUMENTAR",(L10/L9),IF($B9="REDUZIR",L9/L10,"0"))),"")} | M11: {=_xlfn.IFERROR((IF($B9="AUMENTAR",(M10/M9),IF($B9="REDUZIR",M9/M10,"0"))),"")} | ... R11: {=_xlfn.IFERROR((IF($B9="AUMENTAR",(R10/R9),IF($B9="REDUZIR",R9/R10,"0"))),"")}
B12: REDUZIR | D12: Iniciativa 3 | E12: Projetada | R12: {=SUM(F12:Q12)} -> 0
E13: Realizada | R13: {=SUM(F13:Q13)} -> 0
E14: % | F14: {=_xlfn.IFERROR((IF($B12="AUMENTAR",(F13/F12),IF($B12="REDUZIR",F12/F13,"0"))),"")} | G14: {=_xlfn.IFERROR((IF($B12="AUMENTAR",(G13/G12),IF($B12="REDUZIR",G12/G13,"0"))),"")} | H14: {=_xlfn.IFERROR((IF($B12="AUMENTAR",(H13/H12),IF($B12="REDUZIR",H12/H13,"0"))),"")} | I14: {=_xlfn.IFERROR((IF($B12="AUMENTAR",(I13/I12),IF($B12="REDUZIR",I12/I13,"0"))),"")} | J14: {=_xlfn.IFERROR((IF($B12="AUMENTAR",(J13/J12),IF($B12="REDUZIR",J12/J13,"0"))),"")} | K14: {=_xlfn.IFERROR((IF($B12="AUMENTAR",(K13/K12),IF($B12="REDUZIR",K12/K13,"0"))),"")} | L14: {=_xlfn.IFERROR((IF($B12="AUMENTAR",(L13/L12),IF($B12="REDUZIR",L12/L13,"0"))),"")} | M14: {=_xlfn.IFERROR((IF($B12="AUMENTAR",(M13/M12),IF($B12="REDUZIR",M12/M13,"0"))),"")} | ... R14: {=_xlfn.IFERROR((IF($B12="AUMENTAR",(R13/R12),IF($B12="REDUZIR",R12/R13,"0"))),"")}
B15: REDUZIR | D15: Iniciativa 4 | E15: Projetada | R15: {=SUM(F15:Q15)} -> 0
E16: Realizada | H16: 0 | I16: 0 | J16: 0 | K16: 0 | L16: 0 | M16: 0 | N16: 0 | O16: 0 | P16: 0 | Q16: 0 | R16: {=SUM(F16:Q16)} -> 0
E17: % | F17: {=_xlfn.IFERROR((IF($B15="AUMENTAR",(F16/F15),IF($B15="REDUZIR",F15/F16,"0"))),"")} | G17: {=_xlfn.IFERROR((IF($B15="AUMENTAR",(G16/G15),IF($B15="REDUZIR",G15/G16,"0"))),"")} | H17: {=_xlfn.IFERROR((IF($B15="AUMENTAR",(H16/H15),IF($B15="REDUZIR",H15/H16,"0"))),"")} | I17: {=_xlfn.IFERROR((IF($B15="AUMENTAR",(I16/I15),IF($B15="REDUZIR",I15/I16,"0"))),"")} | J17: {=_xlfn.IFERROR((IF($B15="AUMENTAR",(J16/J15),IF($B15="REDUZIR",J15/J16,"0"))),"")} | K17: {=_xlfn.IFERROR((IF($B15="AUMENTAR",(K16/K15),IF($B15="REDUZIR",K15/K16,"0"))),"")} | L17: {=_xlfn.IFERROR((IF($B15="AUMENTAR",(L16/L15),IF($B15="REDUZIR",L15/L16,"0"))),"")} | M17: {=_xlfn.IFERROR((IF($B15="AUMENTAR",(M16/M15),IF($B15="REDUZIR",M15/M16,"0"))),"")} | ... R17: {=_xlfn.IFERROR((IF($B15="AUMENTAR",(R16/R15),IF($B15="REDUZIR",R15/R16,"0"))),"")}
B21: PLANO DE AÇÃO
B23: Item | C23: Iniciativa | D23: Ação | E23: Responsável | F23: Prazo | G23: Status | H23: Objetivo
G24: {=IF(F24="","Aguardando",IF(F24<=TODAY(),"Atrasado",IF(F24>TODAY(),"Em Execução","Aguardando")))} -> Aguardando
G25: {=IF(F25="","Aguardando",IF(F25<=TODAY(),"Atrasado",IF(F25>TODAY(),"Em Execução","Aguardando")))} -> Aguardando
G26: {=IF(F26="","Aguardando",IF(F26<=TODAY(),"Atrasado",IF(F26>TODAY(),"Em Execução","Aguardando")))} -> Aguardando
G27: {=IF(F27="","Aguardando",IF(F27<=TODAY(),"Atrasado",IF(F27>TODAY(),"Em Execução","Aguardando")))} -> Aguardando
G28: {=IF(F28="","Aguardando",IF(F28<=TODAY(),"Atrasado",IF(F28>TODAY(),"Em Execução","Aguardando")))} -> Aguardando
G29: {=IF(F29="","Aguardando",IF(F29<=TODAY(),"Atrasado",IF(F29>TODAY(),"Em Execução","Aguardando")))} -> Aguardando
G30: {=IF(F30="","Aguardando",IF(F30<=TODAY(),"Atrasado",IF(F30>TODAY(),"Em Execução","Aguardando")))} -> Aguardando
G31: {=IF(F31="","Aguardando",IF(F31<=TODAY(),"Atrasado",IF(F31>TODAY(),"Em Execução","Aguardando")))} -> Aguardando
G32: {=IF(F32="","Aguardando",IF(F32<=TODAY(),"Atrasado",IF(F32>TODAY(),"Em Execução","Aguardando")))} -> Aguardando
G33: {=IF(F33="","Aguardando",IF(F33<=TODAY(),"Atrasado",IF(F33>TODAY(),"Em Execução","Aguardando")))} -> Aguardando
G34: {=IF(F34="","Aguardando",IF(F34<=TODAY(),"Atrasado",IF(F34>TODAY(),"Em Execução","Aguardando")))} -> Aguardando
G35: {=IF(F35="","Aguardando",IF(F35<=TODAY(),"Atrasado",IF(F35>TODAY(),"Em Execução","Aguardando")))} -> Aguardando
G36: {=IF(F36="","Aguardando",IF(F36<=TODAY(),"Atrasado",IF(F36>TODAY(),"Em Execução","Aguardando")))} -> Aguardando

Sheet 4.Operacional
B2: INDICADORES OPERACIONAL
B5: 1. Direção | C5: 1. Meta | D5: 3. Iniciativas | E5: 5. Meta | F5: Janeiro | G5: Fevereiro | H5: Março | I5: Abril | J5: Maio | K5: Junho | L5: Julho | M5: Agosto | N5: Setembro | O5: Outubro | P5: Novembro | Q5: Dezembro | R5: ANUALIZADO | T5: AUMENTAR
B6: REDUZIR | D6: Iniciativa 1 | E6: Projetada | R6: {=AVERAGE(F6:Q6)} | T6: REDUZIR
E7: Realizada | R7: {=SUM(F7:Q7)} -> 0
E8: % | F8: {=_xlfn.IFERROR((IF($B6="AUMENTAR",(F7/F6),IF($B6="REDUZIR",F6/F7,"0"))),"")} | G8: {=_xlfn.IFERROR((IF($B6="AUMENTAR",(G7/G6),IF($B6="REDUZIR",G6/G7,"0"))),"")} | H8: {=_xlfn.IFERROR((IF($B6="AUMENTAR",(H7/H6),IF($B6="REDUZIR",H6/H7,"0"))),"")} | I8: {=_xlfn.IFERROR((IF($B6="AUMENTAR",(I7/I6),IF($B6="REDUZIR",I6/I7,"0"))),"")} | J8: {=_xlfn.IFERROR((IF($B6="AUMENTAR",(J7/J6),IF($B6="REDUZIR",J6/J7,"0"))),"")} | K8: {=_xlfn.IFERROR((IF($B6="AUMENTAR",(K7/K6),IF($B6="REDUZIR",K6/K7,"0"))),"")} | L8: {=_xlfn.IFERROR((IF($B6="AUMENTAR",(L7/L6),IF($B6="REDUZIR",L6/L7,"0"))),"")} | M8: {=_xlfn.IFERROR((IF($B6="AUMENTAR",(M7/M6),IF($B6="REDUZIR",M6/M7,"0"))),"")} | ... R8: {=_xlfn.IFERROR((IF($B6="AUMENTAR",(R7/R6),IF($B6="REDUZIR",R6/R7,"0"))),"")}
B9: AUMENTAR | D9: Iniciativa 2 | E9: Projetada | R9: {=AVERAGE(F9:Q9)}
E10: Realizada | R10: {=SUM(F10:Q10)} -> 0
E11: % | F11: {=_xlfn.IFERROR((IF($B9="AUMENTAR",(F10/F9),IF($B9="REDUZIR",F9/F10,"0"))),"")} | G11: {=_xlfn.IFERROR((IF($B9="AUMENTAR",(G10/G9),IF($B9="REDUZIR",G9/G10,"0"))),"")} | H11: {=_xlfn.IFERROR((IF($B9="AUMENTAR",(H10/H9),IF($B9="REDUZIR",H9/H10,"0"))),"")} | I11: {=_xlfn.IFERROR((IF($B9="AUMENTAR",(I10/I9),IF($B9="REDUZIR",I9/I10,"0"))),"")} | J11: {=_xlfn.IFERROR((IF($B9="AUMENTAR",(J10/J9),IF($B9="REDUZIR",J9/J10,"0"))),"")} | K11: {=_xlfn.IFERROR((IF($B9="AUMENTAR",(K10/K9),IF($B9="REDUZIR",K9/K10,"0"))),"")} | L11: {=_xlfn.IFERROR((IF($B9="AUMENTAR",(L10/L9),IF($B9="REDUZIR",L9/L10,"0"))),"")} | M11: {=_xlfn.IFERROR((IF($B9="AUMENTAR",(M10/M9),IF($B9="REDUZIR",M9/M10,"0"))),"")} | ... R11: {=_xlfn.IFERROR((IF($B9="AUMENTAR",(R10/R9),IF($B9="REDUZIR",R9/R10,"0"))),"")}
B12: REDUZIR | D12: Iniciativa 3 | E12: Projetada | R12: {=SUM(F12:Q12)} -> 0
E13: Realizada | R13: {=SUM(F13:Q13)} -> 0
E14: % | F14: {=_xlfn.IFERROR((IF($B12="AUMENTAR",(F13/F12),IF($B12="REDUZIR",F12/F13,"0"))),"")} | G14: {=_xlfn.IFERROR((IF($B12="AUMENTAR",(G13/G12),IF($B12="REDUZIR",G12/G13,"0"))),"")} | H14: {=_xlfn.IFERROR((IF($B12="AUMENTAR",(H13/H12),IF($B12="REDUZIR",H12/H13,"0"))),"")} | I14: {=_xlfn.IFERROR((IF($B12="AUMENTAR",(I13/I12),IF($B12="REDUZIR",I12/I13,"0"))),"")} | J14: {=_xlfn.IFERROR((IF($B12="AUMENTAR",(J13/J12),IF($B12="REDUZIR",J12/J13,"0"))),"")} | K14: {=_xlfn.IFERROR((IF($B12="AUMENTAR",(K13/K12),IF($B12="REDUZIR",K12/K13,"0"))),"")} | L14: {=_xlfn.IFERROR((IF($B12="AUMENTAR",(L13/L12),IF($B12="REDUZIR",L12/L13,"0"))),"")} | M14: {=_xlfn.IFERROR((IF($B12="AUMENTAR",(M13/M12),IF($B12="REDUZIR",M12/M13,"0"))),"")} | ... R14: {=_xlfn.IFERROR((IF($B12="AUMENTAR",(R13/R12),IF($B12="REDUZIR",R12/R13,"0"))),"")}
B15: REDUZIR | D15: Iniciativa 4 | E15: Projetada | R15: {=SUM(F15:Q15)} -> 0
E16: Realizada | R16: {=SUM(F16:Q16)} -> 0
E17: % | F17: {=_xlfn.IFERROR((IF($B15="AUMENTAR",(F16/F15),IF($B15="REDUZIR",F15/F16,"0"))),"")} | G17: {=_xlfn.IFERROR((IF($B15="AUMENTAR",(G16/G15),IF($B15="REDUZIR",G15/G16,"0"))),"")} | H17: {=_xlfn.IFERROR((IF($B15="AUMENTAR",(H16/H15),IF($B15="REDUZIR",H15/H16,"0"))),"")} | I17: {=_xlfn.IFERROR((IF($B15="AUMENTAR",(I16/I15),IF($B15="REDUZIR",I15/I16,"0"))),"")} | J17: {=_xlfn.IFERROR((IF($B15="AUMENTAR",(J16/J15),IF($B15="REDUZIR",J15/J16,"0"))),"")} | K17: {=_xlfn.IFERROR((IF($B15="AUMENTAR",(K16/K15),IF($B15="REDUZIR",K15/K16,"0"))),"")} | L17: {=_xlfn.IFERROR((IF($B15="AUMENTAR",(L16/L15),IF($B15="REDUZIR",L15/L16,"0"))),"")} | M17: {=_xlfn.IFERROR((IF($B15="AUMENTAR",(M16/M15),IF($B15="REDUZIR",M15/M16,"0"))),"")} | ... R17: {=_xlfn.IFERROR((IF($B15="AUMENTAR",(R16/R15),IF($B15="REDUZIR",R15/R16,"0"))),"")}
B21: PLANO DE AÇÃO
B23: Item | C23: Iniciativa | D23: Ação | E23: Responsável | F23: Prazo | G23: Status | H23: Objetivo
G24: {=IF(F24="","Aguardando",IF(F24<=TODAY(),"Atrasado",IF(F24>TODAY(),"Em Execução","Aguardando")))} -> Aguardando
G25: {=IF(F25="","Aguardando",IF(F25<=TODAY(),"Atrasado",IF(F25>TODAY(),"Em Execução","Aguardando")))} -> Aguardando
G26: {=IF(F26="","Aguardando",IF(F26<=TODAY(),"Atrasado",IF(F26>TODAY(),"Em Execução","Aguardando")))} -> Aguardando
G27: {=IF(F27="","Aguardando",IF(F27<=TODAY(),"Atrasado",IF(F27>TODAY(),"Em Execução","Aguardando")))} -> Aguardando
G28: {=IF(F28="","Aguardando",IF(F28<=TODAY(),"Atrasado",IF(F28>TODAY(),"Em Execução","Aguardando")))} -> Aguardando
G29: {=IF(F29="","Aguardando",IF(F29<=TODAY(),"Atrasado",IF(F29>TODAY(),"Em Execução","Aguardando")))} -> Aguardando
G30: {=IF(F30="","Aguardando",IF(F30<=TODAY(),"Atrasado",IF(F30>TODAY(),"Em Execução","Aguardando")))} -> Aguardando
G31: {=IF(F31="","Aguardando",IF(F31<=TODAY(),"Atrasado",IF(F31>TODAY(),"Em Execução","Aguardando")))} -> Aguardando
G32: {=IF(F32="","Aguardando",IF(F32<=TODAY(),"Atrasado",IF(F32>TODAY(),"Em Execução","Aguardando")))} -> Aguardando
G33: {=IF(F33="","Aguardando",IF(F33<=TODAY(),"Atrasado",IF(F33>TODAY(),"Em Execução","Aguardando")))} -> Aguardando
G34: {=IF(F34="","Aguardando",IF(F34<=TODAY(),"Atrasado",IF(F34>TODAY(),"Em Execução","Aguardando")))} -> Aguardando
G35: {=IF(F35="","Aguardando",IF(F35<=TODAY(),"Atrasado",IF(F35>TODAY(),"Em Execução","Aguardando")))} -> Aguardando
G36: {=IF(F36="","Aguardando",IF(F36<=TODAY(),"Atrasado",IF(F36>TODAY(),"Em Execução","Aguardando")))} -> Aguardando

Sheet ANÁLISE HISTORICA
B2: Analise Histórica
B6: HISTORICO 2025 | C6: JAN | D6: FEV | E6: MAR | F6: ABR | G6: MAI | H6: JUN | I6: JUL | J6: AGO | K6: SET | L6: OUT | M6: NOV | N6: DEZ | O6: MÉDIA
B7: Descrição
B8: Descrição
B9: Descrição
B10: Descrição
B11: Descrição
B12: Descrição
B15: META 2026 | C15: JAN | D15: FEV | E15: MAR | F15: ABR | G15: MAI | H15: JUN | I15: JUL | J15: AGO | K15: SET | L15: OUT | M15: NOV | N15: DEZ | O15: MÉDIA
B16: Descrição
B17: Descrição
B18: Descrição
B19: Descrição
B20: Descrição
B21: Descrição

Sheet 5.Recursos Humanos
B2: INDICADORES RECURSOS HUMANOS
B5: 1. Direção | C5: 1. Meta | D5: 3. Iniciativas | E5: 5. Meta | F5: Janeiro | G5: Fevereiro | H5: Março | I5: Abril | J5: Maio | K5: Junho | L5: Julho | M5: Agosto | N5: Setembro | O5: Outubro | P5: Novembro | Q5: Dezembro | R5: ANUALIZADO | T5: AUMENTAR
B6: AUMENTAR | D6: Iniciativa 1 | E6: Projetada | R6: {=SUM(F6:Q6)} -> 0 | T6: REDUZIR
E7: Realizada | R7: {=SUM(F7:Q7)} -> 0
E8: % | F8: {=_xlfn.IFERROR((IF($B6="AUMENTAR",(F7/F6),IF($B6="REDUZIR",F6/F7,"0"))),"")} | G8: {=_xlfn.IFERROR((IF($B6="AUMENTAR",(G7/G6),IF($B6="REDUZIR",G6/G7,"0"))),"")} | H8: {=_xlfn.IFERROR((IF($B6="AUMENTAR",(H7/H6),IF($B6="REDUZIR",H6/H7,"0"))),"")} | I8: {=_xlfn.IFERROR((IF($B6="AUMENTAR",(I7/I6),IF($B6="REDUZIR",I6/I7,"0"))),"")} | J8: {=_xlfn.IFERROR((IF($B6="AUMENTAR",(J7/J6),IF($B6="REDUZIR",J6/J7,"0"))),"")} | K8: {=_xlfn.IFERROR((IF($B6="AUMENTAR",(K7/K6),IF($B6="REDUZIR",K6/K7,"0"))),"")} | L8: {=_xlfn.IFERROR((IF($B6="AUMENTAR",(L7/L6),IF($B6="REDUZIR",L6/L7,"0"))),"")} | M8: {=_xlfn.IFERROR((IF($B6="AUMENTAR",(M7/M6),IF($B6="REDUZIR",M6/M7,"0"))),"")} | ... R8: {=_xlfn.IFERROR((IF($B6="AUMENTAR",(R7/R6),IF($B6="REDUZIR",R6/R7,"0"))),"")}
B9: REDUZIR | D9: Iniciativa 2 | E9: Projetada | R9: {=SUM(F9:Q9)} -> 0
E10: Realizada | R10: {=SUM(F10:Q10)} -> 0
E11: % | F11: {=_xlfn.IFERROR((IF($B9="AUMENTAR",(F10/F9),IF($B9="REDUZIR",F9/F10,"0"))),"")} | G11: {=_xlfn.IFERROR((IF($B9="AUMENTAR",(G10/G9),IF($B9="REDUZIR",G9/G10,"0"))),"")} | H11: {=_xlfn.IFERROR((IF($B9="AUMENTAR",(H10/H9),IF($B9="REDUZIR",H9/H10,"0"))),"")} | I11: {=_xlfn.IFERROR((IF($B9="AUMENTAR",(I10/I9),IF($B9="REDUZIR",I9/I10,"0"))),"")} | J11: {=_xlfn.IFERROR((IF($B9="AUMENTAR",(J10/J9),IF($B9="REDUZIR",J9/J10,"0"))),"")} | K11: {=_xlfn.IFERROR((IF($B9="AUMENTAR",(K10/K9),IF($B9="REDUZIR",K9/K10,"0"))),"")} | L11: {=_xlfn.IFERROR((IF($B9="AUMENTAR",(L10/L9),IF($B9="REDUZIR",L9/L10,"0"))),"")} | M11: {=_xlfn.IFERROR((IF($B9="AUMENTAR",(M10/M9),IF($B9="REDUZIR",M9/M10,"0"))),"")} | ... R11: {=_xlfn.IFERROR((IF($B9="AUMENTAR",(R10/R9),IF($B9="REDUZIR",R9/R10,"0"))),"")}
B12: REDUZIR | D12: Iniciativa 3 | E12: Projetada | R12: {=SUM(F12:Q12)} -> 0
E13: Realizada | R13: {=SUM(F13:Q13)} -> 0
E14: % | F14: {=_xlfn.IFERROR((IF($B12="AUMENTAR",(F13/F12),IF($B12="REDUZIR",F12/F13,"0"))),"")} | G14: {=_xlfn.IFERROR((IF($B12="AUMENTAR",(G13/G12),IF($B12="REDUZIR",G12/G13,"0"))),"")} | H14: {=_xlfn.IFERROR((IF($B12="AUMENTAR",(H13/H12),IF($B12="REDUZIR",H12/H13,"0"))),"")} | I14: {=_xlfn.IFERROR((IF($B12="AUMENTAR",(I13/I12),IF($B12="REDUZIR",I12/I13,"0"))),"")} | J14: {=_xlfn.IFERROR((IF($B12="AUMENTAR",(J13/J12),IF($B12="REDUZIR",J12/J13,"0"))),"")} | K14: {=_xlfn.IFERROR((IF($B12="AUMENTAR",(K13/K12),IF($B12="REDUZIR",K12/K13,"0"))),"")} | L14: {=_xlfn.IFERROR((IF($B12="AUMENTAR",(L13/L12),IF($B12="REDUZIR",L12/L13,"0"))),"")} | M14: {=_xlfn.IFERROR((IF($B12="AUMENTAR",(M13/M12),IF($B12="REDUZIR",M12/M13,"0"))),"")} | ... R14: {=_xlfn.IFERROR((IF($B12="AUMENTAR",(R13/R12),IF($B12="REDUZIR",R12/R13,"0"))),"")}
B15: REDUZIR | D15: Iniciativa 4 | E15: Projetada | R15: {=SUM(F15:Q15)} -> 0
E16: Realizada | H16: 0 | I16: 0 | J16: 0 | K16: 0 | L16: 0 | M16: 0 | N16: 0 | O16: 0 | P16: 0 | Q16: 0 | R16: {=SUM(F16:Q16)} -> 0
E17: % | F17: {=_xlfn.IFERROR((IF($B15="AUMENTAR",(F16/F15),IF($B15="REDUZIR",F15/F16,"0"))),"")} | G17: {=_xlfn.IFERROR((IF($B15="AUMENTAR",(G16/G15),IF($B15="REDUZIR",G15/G16,"0"))),"")} | H17: {=_xlfn.IFERROR((IF($B15="AUMENTAR",(H16/H15),IF($B15="REDUZIR",H15/H16,"0"))),"")} | I17: {=_xlfn.IFERROR((IF($B15="AUMENTAR",(I16/I15),IF($B15="REDUZIR",I15/I16,"0"))),"")} | J17: {=_xlfn.IFERROR((IF($B15="AUMENTAR",(J16/J15),IF($B15="REDUZIR",J15/J16,"0"))),"")} | K17: {=_xlfn.IFERROR((IF($B15="AUMENTAR",(K16/K15),IF($B15="REDUZIR",K15/K16,"0"))),"")} | L17: {=_xlfn.IFERROR((IF($B15="AUMENTAR",(L16/L15),IF($B15="REDUZIR",L15/L16,"0"))),"")} | M17: {=_xlfn.IFERROR((IF($B15="AUMENTAR",(M16/M15),IF($B15="REDUZIR",M15/M16,"0"))),"")} | ... R17: {=_xlfn.IFERROR((IF($B15="AUMENTAR",(R16/R15),IF($B15="REDUZIR",R15/R16,"0"))),"")}
B21: PLANO DE AÇÃO
B23: Item | C23: Iniciativa | D23: Ação | E23: Responsável | F23: Prazo | G23: Status | H23: Objetivo
G24: {=IF(F24="","Aguardando",IF(F24<=TODAY(),"Atrasado",IF(F24>TODAY(),"Em Execução","Aguardando")))} -> Aguardando
G25: {=IF(F25="","Aguardando",IF(F25<=TODAY(),"Atrasado",IF(F25>TODAY(),"Em Execução","Aguardando")))} -> Aguardando
G26: {=IF(F26="","Aguardando",IF(F26<=TODAY(),"Atrasado",IF(F26>TODAY(),"Em Execução","Aguardando")))} -> Aguardando
G27: {=IF(F27="","Aguardando",IF(F27<=TODAY(),"Atrasado",IF(F27>TODAY(),"Em Execução","Aguardando")))} -> Aguardando
G28: {=IF(F28="","Aguardando",IF(F28<=TODAY(),"Atrasado",IF(F28>TODAY(),"Em Execução","Aguardando")))} -> Aguardando
G29: {=IF(F29="","Aguardando",IF(F29<=TODAY(),"Atrasado",IF(F29>TODAY(),"Em Execução","Aguardando")))} -> Aguardando
G30: {=IF(F30="","Aguardando",IF(F30<=TODAY(),"Atrasado",IF(F30>TODAY(),"Em Execução","Aguardando")))} -> Aguardando
G31: {=IF(F31="","Aguardando",IF(F31<=TODAY(),"Atrasado",IF(F31>TODAY(),"Em Execução","Aguardando")))} -> Aguardando
G32: {=IF(F32="","Aguardando",IF(F32<=TODAY(),"Atrasado",IF(F32>TODAY(),"Em Execução","Aguardando")))} -> Aguardando
G33: {=IF(F33="","Aguardando",IF(F33<=TODAY(),"Atrasado",IF(F33>TODAY(),"Em Execução","Aguardando")))} -> Aguardando
G34: {=IF(F34="","Aguardando",IF(F34<=TODAY(),"Atrasado",IF(F34>TODAY(),"Em Execução","Aguardando")))} -> Aguardando
G35: {=IF(F35="","Aguardando",IF(F35<=TODAY(),"Atrasado",IF(F35>TODAY(),"Em Execução","Aguardando")))} -> Aguardando
G36: {=IF(F36="","Aguardando",IF(F36<=TODAY(),"Atrasado",IF(F36>TODAY(),"Em Execução","Aguardando")))} -> Aguardando

Sheet 6.Indicadores de Performance

Sheet Graficos Tasks - Tabela dinâmic
A1: Tabela dinâmica10
A2: Status | B2: Status
A3: Responsável | B3: Aguardando | C3: Grand Total
A4: (blank) | B4: 0 | C4: 0
A5: Grand Total | B5: 0 | C5: 0

Sheet Graficos Tasks - Tabela dinâmi1
A1: Tabela dinâmica6
A2: Status | B2: Item (Count All)
A3: Aguardando | B3: 0
A4: Grand Total | B4: 0

Sheet Graficos Tasks - Tabela dinâmi2
A1: Tabela dinâmica3
A2: Status | B2: Item (Count All)
A3: Aguardando | B3: 0
A4: Grand Total | B4: 0

Sheet Graficos Tasks - Tabela dinâmi3
A1: Tabela dinâmica4
A2: Status | B2: Item (Count All)
A3: Aguardando | B3: 0
A4: Grand Total | B4: 0

Sheet Graficos Tasks - Tabela dinâmi4
A1: Tabela dinâmica2
A2: Status | B2: Status
A3: Responsável | B3: Aguardando | C3: Grand Total
A4: (blank) | B4: 0 | C4: 0
A5: Grand Total | B5: 0 | C5: 0

Sheet Graficos Tasks - Tabela dinâmi5
A1: Tabela dinâmica7
A2: Status | B2: Item (Count All)
A3: Aguardando | B3: 0
A4: Grand Total | B4: 0

Sheet Graficos Tasks - Tabela dinâmi6
A1: Tabela dinâmica9
A2: Status | B2: Item (Count All)
A3: Aguardando | B3: 0
A4: Grand Total | B4: 0

Sheet Graficos Tasks - Tabela dinâmi7
A1: Tabela dinâmica8
A2: Status | B2: Status
A3: Responsável | B3: Aguardando | C3: Grand Total
A4: (blank) | B4: 0 | C4: 0
A5: Grand Total | B5: 0 | C5: 0

Sheet Graficos Tasks - Tabela dinâmi8
A1: Tabela dinâmica5
A2: Status | B2: Status
A3: Responsável | B3: Aguardando | C3: Grand Total
A4: (blank) | B4: 0 | C4: 0
A5: Grand Total | B5: 0 | C5: 0

Sheet Graficos Tasks - Tabela dinâmi9
A1: Tabela dinâmica1
A2: Status | B2: Status
A3: Responsável | B3: Aguardando | C3: Grand Total
A4: (blank) | B4: 0 | C4: 0
A5: Grand Total | B5: 0 | C5: 0

Sheet Graficos Tasks - Table 1
B2: Financeiro
B30: Comercial
B58: Marketing
B86: Operacional
B114: Recursos Humanos

Sheet Graficos Tasks - Drawings
